Workbook

Sheet FAPEU
A1: Nº | B1: Projeto | D1: Contratado | E1: Rec até | F1: A Receber | S1: Total a Receber
E2: 46173 | F2: 46174 | G2: 46204 | H2: 46235 | I2: 46266 | J2: 46296 | K2: 46327 | L2: 46357 | M2: 46388 | N2: 46419 | O2: 46447 | P2: 46478 | Q2: 46508 | R2: jun/27 a dez/28
A3: 1 | B3: 011/2024 | C3: SAC 2023 | D3: ='SAC 2024'!D67 | E3: ='SAC 2024'!E67 | F3: ='SAC 2024'!E2 | G3: ='SAC 2024'!F2 | H3: ='SAC 2024'!G2 | I3: ='SAC 2024'!H2 | J3: ='SAC 2024'!I2 | K3: ='SAC 2024'!J2 | L3: ='SAC 2024'!K2 | M3: ='SAC 2024'!L2 | ... Q3: ='SAC 2024'!P2 | R3: =SUM('SAC 2024'!R2:AI2) | S3: =SUM(F3:R3)
A4: =A3+1 | B4: 062/2024 | C4: Prodesp | D4: =Prodesp!D92 | E4: =Prodesp!E92 | F4: =Prodesp!E2 | G4: =Prodesp!F2 | H4: =Prodesp!G2 | I4: =Prodesp!H2 | J4: =Prodesp!I2 | K4: =Prodesp!J2 | L4: =Prodesp!K2 | M4: =Prodesp!L2 | ... P4: =Prodesp!O2 | S4: =SUM(F4:R4)
A5: =A4+1 | B5: 087/2024 | C5: DER-MG | D5: ='DER-MG'!D44 | E5: ='DER-MG'!E45 | F5: ='DER-MG'!E2 | G5: ='DER-MG'!F2 | H5: ='DER-MG'!G2 | I5: ='DER-MG'!H2 | J5: ='DER-MG'!I2 | K5: ='DER-MG'!J2 | L5: ='DER-MG'!K2 | M5: ='DER-MG'!L2 | ... O5: ='DER-MG'!N2 | S5: =SUM(F5:R5)
A6: =A5+1 | B6: 050/2025 | C6: SGG Goiás | D6: =Goiás!D36 | E6: =Goiás!E36 | F6: =Goiás!D2 | G6: =Goiás!E2 | H6: =Goiás!F2 | S6: =SUM(F6:R6)
A7: =A6+1 | B7: 114/2025 | C7: SAC BIM | D7: ='SAC BIM'!D136 | E7: ='SAC BIM'!E136 | F7: ='SAC BIM'!E2 | G7: ='SAC BIM'!F2 | H7: ='SAC BIM'!G2 | I7: ='SAC BIM'!H2 | J7: ='SAC BIM'!I2 | K7: ='SAC BIM'!J2 | L7: ='SAC BIM'!K2 | M7: ='SAC BIM'!L2 | ... Q7: ='SAC BIM'!P2 | R7: =SUM('SAC BIM'!Q2:BG2) | S7: =SUM(F7:R7)
A8: =A7+1 | B8: 014/2026 | C8: RUMO | D8: =RUMO!D29 | E8: =RUMO!E28 | F8: =RUMO!E2 | G8: =RUMO!F2 | H8: =RUMO!G2 | I8: =RUMO!H2 | J8: =RUMO!I2 | K8: =RUMO!J2 | L8: =RUMO!K2 | M8: =RUMO!L2 | ... Q8: =RUMO!P2 | R8: =SUM(RUMO!Q2:V2) | S8: =SUM(F8:R8)
A9: =A8+1 | B9: 015/2026 | C9: SGG Goiás II | D9: ='Goias II'!D27 | E9: ='Goias II'!D2 | F9: ='Goias II'!E2 | G9: ='Goias II'!F2 | H9: ='Goias II'!G2 | I9: ='Goias II'!H2 | J9: ='Goias II'!I2 | K9: ='Goias II'!J2 | L9: ='Goias II'!K2 | ... N9: ='Goias II'!M2 | S9: =SUM(F9:R9)
A10: =A9+1 | B10: xxx/2026 | C10: DNIT CGPERT | D10: ='DNIT 2026'!D102 | E10: ='DNIT 2026'!E102 | S10: =SUM(F10:R10)
A11: Totais Receitas | D11: =SUM(D3:D10) | E11: =SUM(E3:E10) | F11: =SUM(F3:F10) | G11: =SUM(G3:G10) | H11: =SUM(H3:H10) | I11: =SUM(I3:I10) | J11: =SUM(J3:J10) | K11: =SUM(K3:K10) | ... S11: =SUM(S3:S10)
A13: Nº | B13: Projeto | E13: Realizado até | F13: A Realizar | S13: Total a Realizar
E14: =E2 | F14: =F2 | G14: =G2 | H14: =H2 | I14: =I2 | J14: =J2 | K14: =K2 | L14: =L2 | ... R14: =R2
A15: 1 | B15: =B3 | C15: =C3 | E15: =-'SAC 2024'!G67 | F15: ='SAC 2024'!E55 | G15: ='SAC 2024'!F55 | H15: ='SAC 2024'!G55 | I15: ='SAC 2024'!H55 | J15: ='SAC 2024'!I55 | K15: ='SAC 2024'!J55 | L15: ='SAC 2024'!K55 | M15: ='SAC 2024'!L55 | ... Q15: ='SAC 2024'!P55 | R15: =SUM('SAC 2024'!Q55:AI55) | S15: =SUM(F15:R15)
A16: =A15+1 | B16: =B4 | C16: =C4 | E16: =-Prodesp!G93 | F16: =Prodesp!E87 | G16: =Prodesp!F87 | H16: =Prodesp!G87 | I16: =Prodesp!H87 | J16: =Prodesp!I87 | K16: =Prodesp!J87 | L16: =Prodesp!K87 | M16: =Prodesp!L87 | ... P16: =Prodesp!O87 | S16: =SUM(F16:R16)
A17: =A16+1 | B17: =B5 | C17: =C5 | E17: =-'DER-MG'!G45 | F17: ='DER-MG'!E39 | G17: ='DER-MG'!F39 | H17: ='DER-MG'!G39 | I17: ='DER-MG'!H39 | J17: ='DER-MG'!I39 | K17: ='DER-MG'!J39 | L17: ='DER-MG'!K39 | M17: ='DER-MG'!L39 | ... O17: ='DER-MG'!N39 | S17: =SUM(F17:R17)
A18: =A17+1 | B18: =B6 | C18: =C6 | E18: =-Goiás!G36 | F18: =Goiás!D23 | G18: =Goiás!E23 | H18: =Goiás!F23 | S18: =SUM(F18:R18)
A19: =A18+1 | B19: =B7 | C19: =C7 | E19: =-'SAC BIM'!G136 | F19: ='SAC BIM'!E124 | G19: ='SAC BIM'!F124 | H19: ='SAC BIM'!G124 | I19: ='SAC BIM'!H124 | J19: ='SAC BIM'!I124 | K19: ='SAC BIM'!J124 | L19: ='SAC BIM'!K124 | M19: ='SAC BIM'!L124 | ... Q19: ='SAC BIM'!P124 | R19: =SUM('SAC BIM'!Q124:BG124) | S19: =SUM(F19:R19)
A20: =A19+1 | B20: =B8 | C20: =C8 | E20: =-RUMO!G28 | F20: =RUMO!E23 | G20: =RUMO!F23 | H20: =RUMO!G23 | I20: =RUMO!H23 | J20: =RUMO!I23 | K20: =RUMO!J23 | L20: =RUMO!K23 | M20: =RUMO!L23 | ... Q20: =RUMO!P23 | R20: =SUM(RUMO!Q23:V23) | S20: =SUM(F20:R20)
A21: =A20+1 | B21: =B9 | C21: =C9 | E21: =-'Goias II'!G27 | F21: ='Goias II'!E22 | G21: ='Goias II'!F22 | H21: ='Goias II'!G22 | I21: ='Goias II'!H22 | J21: ='Goias II'!I22 | K21: ='Goias II'!J22 | L21: ='Goias II'!K22 | M21: ='Goias II'!L22 | N21: ='Goias II'!M22 | S21: =SUM(F21:R21)
A22: =A21+1 | B22: =B10 | C22: =C10 | E22: =-'DNIT 2026'!G102 | S22: =SUM(F22:R22)
A23: Totais Despesas | E23: =SUM(E15:E22) | F23: =SUM(F15:F22) | G23: =SUM(G15:G22) | H23: =SUM(H15:H22) | I23: =SUM(I15:I22) | J23: =SUM(J15:J22) | K23: =SUM(K15:K22) | L23: =SUM(L15:L22) | ... S23: =SUM(S15:S22)
A25: Nº | B25: Projeto | E25: Saldo Atual | F25: Saldo Projetado | S25: Total projetado
F26: =F14 | G26: =G14 | H26: =H14 | I26: =I14 | J26: =J14 | K26: =K14 | L26: =L14 | M26: =M14 | ... R26: =R14
A27: 1 | B27: =B15 | C27: =C15 | E27: ='SAC 2024'!D56 | F27: =E27+F3-F15 | G27: =F27+G3-G15 | H27: =G27+H3-H15 | I27: =H27+I3-I15 | J27: =I27+J3-J15 | K27: =J27+K3-K15 | L27: =K27+L3-L15 | M27: =L27+M3-M15 | ... R27: =Q27+R3-R15 | S27: =R27
A28: =A27+1 | B28: =B16 | C28: =C16 | E28: =Prodesp!D88 | F28: =E28+F4-F16 | G28: =F28+G4-G16 | H28: =G28+H4-H16 | I28: =H28+I4-I16 | J28: =I28+J4-J16 | K28: =J28+K4-K16 | L28: =K28+L4-L16 | M28: =L28+M4-M16 | ... P28: =O28+P4-P16 | S28: =P28
A29: =A28+1 | B29: =B17 | C29: =C17 | E29: ='DER-MG'!D40 | F29: =E29+F5-F17 | G29: =F29+G5-G17 | H29: =G29+H5-H17 | I29: =H29+I5-I17 | J29: =I29+J5-J17 | K29: =J29+K5-K17 | L29: =K29+L5-L17 | M29: =L29+M5-M17 | ... O29: =N29+O5-O17 | S29: =O29
A30: =A29+1 | B30: =B18 | C30: =C18 | E30: =Goiás!C24 | F30: =E30+F6-F18 | G30: =F30+G6-G18 | H30: =G30+H6-H18 | S30: =H30
A31: =A30+1 | B31: =B19 | C31: =C19 | E31: ='SAC BIM'!H136 | F31: =E31+F7-F19 | G31: =F31+G7-G19 | H31: =G31+H7-H19 | I31: =H31+I7-I19 | J31: =I31+J7-J19 | K31: =J31+K7-K19 | L31: =K31+L7-L19 | M31: =L31+M7-M19 | ... R31: =Q31+R7-R19 | S31: =R31
A32: =A31+1 | B32: =B20 | C32: =C20 | E32: =RUMO!D24 | F32: =E32+F8-F20 | G32: =F32+G8-G20 | H32: =G32+H8-H20 | I32: =H32+I8-I20 | J32: =I32+J8-J20 | K32: =J32+K8-K20 | L32: =K32+L8-L20 | M32: =L32+M8-M20 | ... R32: =Q32+R8-R20 | S32: =R32
A33: =A32+1 | B33: =B21 | C33: =C21 | E33: ='Goias II'!D23 | F33: =E33+F9-F21 | G33: =F33+G9-G21 | H33: =G33+H9-H21 | I33: =H33+I9-I21 | J33: =I33+J9-J21 | K33: =J33+K9-K21 | L33: =K33+L9-L21 | M33: =L33+M9-M21 | N33: =M33+N9-N21 | S33: =N33
A34: =A33+1 | B34: =B22 | C34: =C22 | E34: ='DNIT 2026'!D90 | F34: =E34+F10-F22 | G34: =F34+G10-G22 | H34: =G34+H10-H22 | I34: =H34+I10-I22 | J34: =I34+J10-J22 | K34: =J34+K10-K22 | L34: =K34+L10-L22 | M34: =L34+M10-M22 | ... R34: =Q34+R10-R22 | S34: =R34
A35: Saldos dos Projetos | E35: =SUM(E27:E34) | F35: =SUM(F27:F34) | G35: =SUM(G27:G34) | H35: =SUM(H27:H34) | I35: =SUM(I27:I34) | J35: =SUM(J27:J34) | K35: =SUM(K27:K34) | L35: =SUM(L27:L34) | ... S35: =SUM(S27:S34)
A36: =A30+1 | B36: 999/9999 | C36: Provisões
A37: Saldo Total na Fundação | E37: =SUM(E35:E36) | F37: =SUM(F35:F36) | G37: =SUM(G35:G36) | H37: =SUM(H35:H36) | I37: =SUM(I35:I36) | J37: =SUM(J35:J36) | K37: =SUM(K35:K36) | L37: =SUM(L35:L36) | ... S37: =SUM(S35:S36)

Sheet FabioMattos
A1: Categorias Finaceiras | D1: Log de Cáculo
A2: Código | B2: Descrição
A3: 1 | B3: Reembolso | D3: Receita | E3: Categorias | F3: 15.55
A4: 2 | B4: Suprimento de fundos | D4: Despesas | E4: Categora Diferente | F4: 18
A5: 3 | B5: Adiantamento para viagens | D5: Clt | E5: Detalhamento Folha | F5: Formula | G5: CUSTO_PROJETO = (VALOR_PROVENTO + VALOR_BENEFICIO + VALOR_ENCARGO + VALOR_PROVISAO) - ESTORNO
A6: 4 | B6: Diarias CLT | D6: PessoalNaoContatado | E6: Categorias | F6: 6,10,11
A7: 5 | B7: Pessoa Jurídica - NF de VENDAS | D7: Redoa | E7: Categorias | F7: 26
A8: 6 | B8: Bolsa de estágio
A9: 7 | B9: Diárias Pessoal Sem Vínculo Empregatício | D9: Sql Consulta
A10: 8 | B10: Impostos e Contribuições PJ
A11: 9 | B11: Impostos Pessoal Sem Vínculo Empregatício - RPA | D11: WITH RECEITA AS
A12: 10 | B12: Pessoal sem Vínculo Empregatício - RPA | D12: (
A13: 11 | B13: Bolsas | D13: SELECT
A14: 12 | B14: Transferencia entre Contas | D14: LR.IDProjetoRateio,
A15: 13 | B15: Pessoa Fisica - ALUGUEL | D15: SUM(LR.ValorRateio) AS TotalReceita
A16: 14 | B16: Pessoa Contratado Celetista - CLT | D16: FROM TBLancamento L (NOLOCK)
A17: 15 | B17: Receita | D17: INNER JOIN TBLancamentoRateio LR (NOLOCK)
A18: 16 | B18: Despesas Bancárias | D18: ON LR.IDLancamentoRateio = L.IDLancamento
A19: 17 | B19: Ajuste de Saldo Inicial | D19: INNER JOIN TBProjeto P (NOLOCK)
A20: 18 | B20: Aplicação Financeira | D20: ON P.IDProjeto = LR.IDProjetoRateio
A21: 19 | B21: Devolução de Cheque | D21: WHERE L.IDCategoriaFinanceira in(15,55)
A22: 20 | B22: Devolução Recebida | D22: AND P.CodigoProjetoCompleto IN ('112024','622024','872024','502025','1142025','142026','152026')
... A67: 69 | B67: Transferência de Saldo de cutro prazo para longo prazo | D67: AND P.CodigoProjetoCompleto IN ('112024','622024','872024','502025','1142025','142026','152026')
D68: AND L.Data > 0
D69: GROUP BY LR.IDProjetoRateio
D70: ),
D71: DESPESAS AS
D72: (
D73: SELECT
D74: LR.IDProjetoRateio,
D75: SUM(LR.ValorRateio) AS TotalDespesas
D76: FROM TBLancamento L (NOLOCK)
D77: INNER JOIN TBLancamentoRateio LR (NOLOCK) ON LR.IDLancamentoRateio = L.IDLancamento
D78: INNER JOIN TBProjeto P (NOLOCK) ON P.IDProjeto = LR.IDProjetoRateio
D79: INNER JOIN tbcategoriafinanceira tbcategoriafinanceira (NOLOCK) ON tbcategoriafinanceira.IDCategoriaFinanceira = L.IDCategoriaFinanceira
... D106: ORDER BY P.CodigoProjetoCompleto;

Sheet saldoFAPEU
A1: cdProjeto | B1: PRJ | C1: TotalReceita | D1: TotalDespesas | E1: TotalCLT | F1: TotalPessoalNaoContratado | G1: TotalRedoa
A2: 112024 | B2: 2024.011 | C2: 37371852 | D2: 40809976 | E2: 27618823 | F2: 3022277.6 | G2: 2821574.8
A3: 1142025 | B3: 2025.114 | C3: 25200000 | D3: 9614566.6 | E3: 4604998.8 | F3: 456194.92 | G3: 1902600
A4: 142026 | B4: 2026.014 | C4: 330031 | D4: 281218.77 | E4: 166922.22 | F4: 43619.5 | G4: 24592.25
A5: 502025 | B5: 2025.050 | C5: 1989653 | D5: 1645034.7 | E5: 216680.51 | F5: 303083.46 | G5: 198965.3
A6: 622024 | B6: 2024.062 | C6: 14412319 | D6: 19260999 | E6: 15834735 | F6: 360237.76 | G6: 1191898.8
A7: 872024 | B7: 2024.087 | C7: 3116712.2 | D7: 4474028.8 | E7: 2914812.1 | F7: 275856.17 | G7: 257128.76

Sheet saldo fapeu
B2: Receitas | C2: Despesas
A3: 011/2024 | B3: 32902922 | C3: 40934160
A4: 062/2024 | B4: 11912464 | C4: 19520464 | E4: Excluir empréstimo
A5: 087/2024 | B5: 3016712.2 | C5: 4699312.2 | E5: Excluir aplicação
A6: 050/2025 | B6: 1989653 | C6: 2464282.9 | E6: incluir o rendimento de aplicação
A7: 114/2025 | B7: 25200000 | C7: 10271238
A8: 014/2026 | B8: 330031 | C8: 261157.66
A9: 015/2026 | B9: 0 | C9: 0

Sheet Análise
B2: Análise por projeto
B4: Número do Projeto | C4: 014/2026 | F4: =VLOOKUP(C4,FAPEU!B3:C10,2,0)
B7: Valor contratado | C7: =VLOOKUP(C4,FAPEU!B3:D10,3,0) | K7: Análise mensal | M7: 46419
B9: Recebido (Projeto) | C9: =VLOOKUP(C4,FAPEU!B3:E10,4,0) | E9: =C9/C7 | K9: Recebimento | M9: =VLOOKUP(C4,FAPEU!B3:R10,D31,0)
B10: Recebimento - Fapeu | C10: =VLOOKUP(C4,'saldo fapeu'!A3:B9,2,0) | E10: =C10/C7 | K10: Despesas programadas | M10: =VLOOKUP(C4,FAPEU!B15:R22,D31,0)
K11: Saldo projetado | M11: =VLOOKUP(C4,FAPEU!B27:R34,Análise!D31,0)
B12: À receber (Projeto) | C12: =C7-C9 | E12: =C12/C7
B13: À Receber FAPEU | C13: =C7-C10 | E13: =C13/C7 | K13: =MATCH(K14,FAPEU!$B$2:$R$2,0) | L13: =MATCH(L14,FAPEU!$B$2:$R$2,0) | M13: =MATCH(M14,FAPEU!$B$2:$R$2,0) | N13: =MATCH(N14,FAPEU!$B$2:$R$2,0) | O13: =MATCH(O14,FAPEU!$B$2:$R$2,0) | P13: =MATCH(P14,FAPEU!$B$2:$R$2,0) | Q13: =MATCH(Q14,FAPEU!$B$2:$R$2,0) | R13: =MATCH(R14,FAPEU!$B$2:$R$2,0) | ... W13: =MATCH(W14,FAPEU!$B$2:$R$2,0)
K14: 46174 | L14: 46204 | M14: 46235 | N14: 46266 | O14: 46296 | P14: 46327 | Q14: 46357 | R14: 46388 | S14: 46419 | T14: 46447 | U14: 46478 | V14: 46508 | W14: jun/27 a dez/28
B15: Gastos realizados (Projeto) | C15: =VLOOKUP(C4,FAPEU!B15:E22,4,0) | E15: =C15/C7 | I15: Entradas | K15: =VLOOKUP($C$4,FAPEU!$B$3:$R$10,K13,0) | L15: =VLOOKUP($C$4,FAPEU!$B$3:$R$10,L13,0) | M15: =VLOOKUP($C$4,FAPEU!$B$3:$R$10,M13,0) | N15: =VLOOKUP($C$4,FAPEU!$B$3:$R$10,N13,0) | O15: =VLOOKUP($C$4,FAPEU!$B$3:$R$10,O13,0) | P15: =VLOOKUP($C$4,FAPEU!$B$3:$R$10,P13,0) | Q15: =VLOOKUP($C$4,FAPEU!$B$3:$R$10,Q13,0) | R15: =VLOOKUP($C$4,FAPEU!$B$3:$R$10,R13,0) | ... W15: =VLOOKUP($C$4,FAPEU!$B$3:$R$10,W13,0)
B16: Gastos Realizado - Fapeu | C16: =VLOOKUP(C4,'saldo fapeu'!A3:C9,3,0) | E16: =C16/C7 | I16: Saídas | K16: =VLOOKUP($C$4,FAPEU!$B$15:$R$22,K13,0) | L16: =VLOOKUP($C$4,FAPEU!$B$15:$R$22,L13,0) | M16: =VLOOKUP($C$4,FAPEU!$B$15:$R$22,M13,0) | N16: =VLOOKUP($C$4,FAPEU!$B$15:$R$22,N13,0) | O16: =VLOOKUP($C$4,FAPEU!$B$15:$R$22,O13,0) | P16: =VLOOKUP($C$4,FAPEU!$B$15:$R$22,P13,0) | Q16: =VLOOKUP($C$4,FAPEU!$B$15:$R$22,Q13,0) | R16: =VLOOKUP($C$4,FAPEU!$B$15:$R$22,R13,0) | ... W16: =VLOOKUP($C$4,FAPEU!$B$15:$R$22,W13,0)
I17: Saldo | K17: =VLOOKUP($C$4,FAPEU!$B$27:$R$34,K13,0) | L17: =VLOOKUP($C$4,FAPEU!$B$27:$R$34,L13,0) | M17: =VLOOKUP($C$4,FAPEU!$B$27:$R$34,M13,0) | N17: =VLOOKUP($C$4,FAPEU!$B$27:$R$34,N13,0) | O17: =VLOOKUP($C$4,FAPEU!$B$27:$R$34,O13,0) | P17: =VLOOKUP($C$4,FAPEU!$B$27:$R$34,P13,0) | Q17: =VLOOKUP($C$4,FAPEU!$B$27:$R$34,Q13,0) | R17: =VLOOKUP($C$4,FAPEU!$B$27:$R$34,R13,0) | ... W17: =VLOOKUP($C$4,FAPEU!$B$27:$R$34,W13,0)
B18: Saldo financeiro projeto | C18: =C9-C15 | E18: =C18/C7
B19: Saldo Financeiro Fapeu | C19: =C10-C16 | E19: =C19/C7
B21: Saldo Restante (Projeto) | C21: =C7-C15 | E21: =C21/C7
B22: Saldo Restante Fapeu | C22: =C7-C16 | E22: =C22/C7
B24: Gastos programados (Projeto) | C24: =VLOOKUP(C4,FAPEU!B15:S22,18,0) | E24: =C24/C7
B26: Resultado Previsto (Projeto) | C26: =C9+C12-C15-C24 | E26: =C26/C7
B27: Resultado Previsto FAPEU | C27: =C10+C13-C16-C24 | E27: =C27/C7
D31: =MATCH(M7,FAPEU!B2:R2,0)

Sheet SAC 2024
A1: N˚ | B1: Receita | D1: Até mai/26 | E1: 46174 | F1: 46204 | G1: 46235 | H1: 46266 | I1: 46296 | J1: 46327 | K1: 46357 | L1: 46388 | M1: 46419 | N1: 46447 | O1: 46478 | P1: 46508 | Q1: 46539 | R1: 46569 | S1: 46600 | T1: 46631 | U1: 46661 | V1: 46692 | W1: 46722 | X1: 46753 | Y1: 46784 | Z1: 46813 | AA1: 46844 | AB1: 46874 | AC1: 46905 | AD1: 46935 | AE1: 46966 | AF1: 46997 | AG1: 47027 | AH1: 47058 | AI1: 47088 | AJ1: Totais
A2: 1 | B2: Parcelas | D2: =E67 | E2: 3468930 | F2: 0 | G2: 3468930 | H2: 0 | I2: 0 | J2: 0 | K2: 3468930 | L2: 0 | M2: 0 | N2: 0 | O2: 3468930 | P2: 0 | Q2: 0 | R2: 0 | S2: 3468930 | T2: 0 | U2: 0 | V2: 0 | W2: 3468930 | X2: 0 | Y2: 0 | Z2: 0 | AA2: 2914837 | AB2: 0 | AC2: 0 | AD2: 0 | AE2: 2360744 | AF2: 0 | AG2: 0 | AH2: 0 | AI2: 0 | AJ2: =SUM(D2:AI2)
A3: N˚ | B3: Despesas | E3: =E1 | F3: =F1 | G3: =G1 | H3: =H1 | I3: =I1 | J3: =J1 | K3: =K1 | L3: =L1 | ... AI3: =AI1 | AJ3: Totais
A4: 1 | B4: Alexandre Royes Schardosim | E4: 4174.4 | F4: 4174.4 | G4: 4174.4 | H4: 4174.4 | I4: 4174.4 | J4: 4174.4 | K4: 4174.4 | L4: 4174.4 | M4: 4174.4 | N4: =M4*1.05 | O4: =N4 | P4: =O4 | Q4: =P4 | R4: =Q4 | S4: =R4 | T4: =S4 | U4: =T4 | V4: =U4 | ... Y4: =X4 | Z4: =Y4*1.05 | AA4: =Z4 | AB4: =AA4 | AC4: =AB4 | AD4: =AC4 | AE4: =AD4 | AF4: =AE4 | AG4: =AF4 | AH4: =AG4 | AI4: =AH4 | AJ4: =SUM(E4:AI4)
A5: =A4+1 | B5: André Luis Fernandes do Espirito Santo | E5: 3830.48 | F5: 3830.48 | G5: 3830.48 | H5: 3830.48 | I5: 3830.48 | J5: 3830.48 | K5: 3830.48 | L5: 3830.48 | M5: 3830.48 | N5: =M5*1.05 | O5: =N5 | P5: =O5 | Q5: =P5 | R5: =Q5 | S5: =R5 | T5: =S5 | U5: =T5 | V5: =U5 | ... Y5: =X5 | Z5: =Y5*1.05 | AA5: =Z5 | AB5: =AA5 | AC5: =AB5 | AD5: =AC5 | AE5: =AD5 | AF5: =AE5 | AG5: =AF5 | AH5: =AG5 | AI5: =AH5 | AJ5: =SUM(E5:AI5)
A6: =A5+1 | B6: Bernardo Victor Engelke | E6: =9224.22+553.45 | F6: =9224.22+553.45 | G6: =9224.22+553.45 | H6: =9224.22+553.45 | I6: =9224.22+553.45 | J6: =9224.22+553.45 | K6: =9224.22+553.45 | L6: =9224.22+553.45 | M6: =9224.22+553.45 | N6: =M6*1.05 | O6: =N6 | P6: =O6 | Q6: =P6 | R6: =Q6 | S6: =R6 | T6: =S6 | U6: =T6 | V6: =U6 | ... Y6: =X6 | Z6: =Y6*1.05 | AA6: =Z6 | AB6: =AA6 | AC6: =AB6 | AD6: =AC6 | AE6: =AD6 | AF6: =AE6 | AG6: =AF6 | AH6: =AG6 | AI6: =AH6 | AJ6: =SUM(E6:AI6)
A7: =A6+1 | B7: Caroline Bettini Frison | E7: 11709.19 | F7: 11709.19 | G7: 11709.19 | H7: 11709.19 | I7: 11709.19 | J7: 11709.19 | K7: 11709.19 | L7: 11709.19 | M7: 11709.19 | N7: =M7*1.05 | O7: =N7 | P7: =O7 | Q7: =P7 | R7: =Q7 | S7: =R7 | T7: =S7 | U7: =T7 | V7: =U7 | ... Y7: =X7 | Z7: =Y7*1.05 | AA7: =Z7 | AB7: =AA7 | AC7: =AB7 | AD7: =AC7 | AE7: =AD7 | AF7: =AE7 | AG7: =AF7 | AH7: =AG7 | AI7: =AH7 | AJ7: =SUM(E7:AI7)
A8: =A7+1 | B8: César Augusto Pereira de Souza | E8: 4800 | F8: 4800 | G8: 4800 | H8: 4800 | I8: 4800 | J8: 4800 | K8: 4800 | L8: 4800 | M8: 4800 | N8: =M8*1.05 | O8: =N8 | P8: =O8 | Q8: =P8 | R8: =Q8 | S8: =R8 | T8: =S8 | U8: =T8 | V8: =U8 | ... Y8: =X8 | Z8: =Y8*1.05 | AA8: =Z8 | AB8: =AA8 | AC8: =AB8 | AD8: =AC8 | AE8: =AD8 | AF8: =AE8 | AG8: =AF8 | AH8: =AG8 | AI8: =AH8 | AJ8: =SUM(E8:AI8)
A9: =A8+1 | B9: Gabriel da Costa Cardoso | E9: 3391.7 | F9: 3391.7 | G9: 3391.7 | H9: 3391.7 | I9: 3391.7 | J9: 3391.7 | K9: 3391.7 | L9: 3391.7 | M9: 3391.7 | N9: =M9*1.05 | O9: =N9 | P9: =O9 | Q9: =P9 | R9: =Q9 | S9: =R9 | T9: =S9 | U9: =T9 | V9: =U9 | ... Y9: =X9 | Z9: =Y9*1.05 | AA9: =Z9 | AB9: =AA9 | AC9: =AB9 | AD9: =AC9 | AE9: =AD9 | AF9: =AE9 | AG9: =AF9 | AH9: =AG9 | AI9: =AH9 | AJ9: =SUM(E9:AI9)
A10: =A9+1 | B10: Guilherme Henrique Correia Sena | E10: =8400.25+252.01 | F10: =8400.25+252.01 | G10: =8400.25+252.01 | H10: =8400.25+252.01 | I10: =8400.25+252.01 | J10: =8400.25+252.01 | K10: =8400.25+252.01 | L10: =8400.25+252.01 | M10: =8400.25+252.01 | N10: =M10*1.05 | O10: =N10 | P10: =O10 | Q10: =P10 | R10: =Q10 | S10: =R10 | T10: =S10 | U10: =T10 | V10: =U10 | ... Y10: =X10 | Z10: =Y10*1.05 | AA10: =Z10 | AB10: =AA10 | AC10: =AB10 | AD10: =AC10 | AE10: =AD10 | AF10: =AE10 | AG10: =AF10 | AH10: =AG10 | AI10: =AH10 | AJ10: =SUM(E10:AI10)
A11: =A10+1 | B11: Helena Spaniol | E11: =7705.43+462.33 | F11: =7705.43+462.33 | G11: =7705.43+462.33 | H11: =7705.43+462.33 | I11: =7705.43+462.33 | J11: =7705.43+462.33 | K11: =7705.43+462.33 | L11: =7705.43+462.33 | M11: =7705.43+462.33 | N11: =M11*1.05 | O11: =N11 | P11: =O11 | Q11: =P11 | R11: =Q11 | S11: =R11 | T11: =S11 | U11: =T11 | V11: =U11 | ... Y11: =X11 | Z11: =Y11*1.05 | AA11: =Z11 | AB11: =AA11 | AC11: =AB11 | AD11: =AC11 | AE11: =AD11 | AF11: =AE11 | AG11: =AF11 | AH11: =AG11 | AI11: =AH11 | AJ11: =SUM(E11:AI11)
A12: =A11+1 | B12: João Vitor Ferreira Pedro | E12: =4377.69 | F12: =4377.69 | G12: =4377.69 | H12: =4377.69 | I12: =4377.69 | J12: =4377.69 | K12: =4377.69 | L12: =4377.69 | M12: =4377.69 | N12: =M12*1.05 | O12: =N12 | P12: =O12 | Q12: =P12 | R12: =Q12 | S12: =R12 | T12: =S12 | U12: =T12 | V12: =U12 | ... Y12: =X12 | Z12: =Y12*1.05 | AA12: =Z12 | AB12: =AA12 | AC12: =AB12 | AD12: =AC12 | AE12: =AD12 | AF12: =AE12 | AG12: =AF12 | AH12: =AG12 | AI12: =AH12 | AJ12: =SUM(E12:AI12)
A13: =A12+1 | B13: Julia Bronzatti Jochims | E13: 6261.6 | F13: 6261.6 | G13: 6261.6 | H13: 6261.6 | I13: 6261.6 | J13: 6261.6 | K13: 6261.6 | L13: 6261.6 | M13: 6261.6 | N13: =M13*1.05 | O13: =N13 | P13: =O13 | Q13: =P13 | R13: =Q13 | S13: =R13 | T13: =S13 | U13: =T13 | V13: =U13 | ... Y13: =X13 | Z13: =Y13*1.05 | AA13: =Z13 | AB13: =AA13 | AC13: =AB13 | AD13: =AC13 | AE13: =AD13 | AF13: =AE13 | AG13: =AF13 | AH13: =AG13 | AI13: =AH13 | AJ13: =SUM(E13:AI13)
A14: =A13+1 | B14: Julia Carmen Damiani Florentino | E14: =7046.3+422.78 | F14: =7046.3+422.78 | G14: =7046.3+422.78 | H14: =7046.3+422.78 | I14: =7046.3+422.78 | J14: =7046.3+422.78 | K14: =7046.3+422.78 | L14: =7046.3+422.78 | M14: =7046.3+422.78 | N14: =M14*1.05 | O14: =N14 | P14: =O14 | Q14: =P14 | R14: =Q14 | S14: =R14 | T14: =S14 | U14: =T14 | V14: =U14 | ... Y14: =X14 | Z14: =Y14*1.05 | AA14: =Z14 | AB14: =AA14 | AC14: =AB14 | AD14: =AC14 | AE14: =AD14 | AF14: =AE14 | AG14: =AF14 | AH14: =AG14 | AI14: =AH14 | AJ14: =SUM(E14:AI14)
A15: =A14+1 | B15: Karine Domingos | E15: =6019.33 | F15: =6019.33 | G15: =6019.33 | H15: =6019.33 | I15: =6019.33 | J15: =6019.33 | K15: =6019.33 | L15: =6019.33 | M15: =6019.33 | N15: =M15*1.05 | O15: =N15 | P15: =O15 | Q15: =P15 | R15: =Q15 | S15: =R15 | T15: =S15 | U15: =T15 | V15: =U15 | ... Y15: =X15 | Z15: =Y15*1.05 | AA15: =Z15 | AB15: =AA15 | AC15: =AB15 | AD15: =AC15 | AE15: =AD15 | AF15: =AE15 | AG15: =AF15 | AH15: =AG15 | AI15: =AH15 | AJ15: =SUM(E15:AI15)
A16: =A15+1 | B16: Leandro Quingerski | E16: =17446.25+1570.16 | F16: =17446.25+1570.16 | G16: =17446.25+1570.16 | H16: =17446.25+1570.16 | I16: =17446.25+1570.16 | J16: =17446.25+1570.16 | K16: =17446.25+1570.16 | L16: =17446.25+1570.16 | M16: =17446.25+1570.16 | N16: =M16*1.05 | O16: =N16 | P16: =O16 | Q16: =P16 | R16: =Q16 | S16: =R16 | T16: =S16 | U16: =T16 | V16: =U16 | ... Y16: =X16 | Z16: =Y16*1.05 | AA16: =Z16 | AB16: =AA16 | AC16: =AB16 | AD16: =AC16 | AE16: =AD16 | AF16: =AE16 | AG16: =AF16 | AH16: =AG16 | AI16: =AH16 | AJ16: =SUM(E16:AI16)
A17: =A16+1 | B17: Lucas Oliveira Pereira da Silva | E17: 5472.12 | F17: 5472.12 | G17: 5472.12 | H17: 5472.12 | I17: 5472.12 | J17: 5472.12 | K17: 5472.12 | L17: 5472.12 | M17: 5472.12 | N17: =M17*1.05 | O17: =N17 | P17: =O17 | Q17: =P17 | R17: =Q17 | S17: =R17 | T17: =S17 | U17: =T17 | V17: =U17 | ... Y17: =X17 | Z17: =Y17*1.05 | AA17: =Z17 | AB17: =AA17 | AC17: =AB17 | AD17: =AC17 | AE17: =AD17 | AF17: =AE17 | AG17: =AF17 | AH17: =AG17 | AI17: =AH17 | AJ17: =SUM(E17:AI17)
A18: =A17+1 | B18: Luciano Vecchi Biolo | E18: 5894.25 | F18: 5894.25 | G18: 5894.25 | H18: 5894.25 | I18: 5894.25 | J18: 5894.25 | K18: 5894.25 | L18: 5894.25 | M18: 5894.25 | N18: =M18*1.05 | O18: =N18 | P18: =O18 | Q18: =P18 | R18: =Q18 | S18: =R18 | T18: =S18 | U18: =T18 | V18: =U18 | ... Y18: =X18 | Z18: =Y18*1.05 | AA18: =Z18 | AB18: =AA18 | AC18: =AB18 | AD18: =AC18 | AE18: =AD18 | AF18: =AE18 | AG18: =AF18 | AH18: =AG18 | AI18: =AH18 | AJ18: =SUM(E18:AI18)
A19: =A18+1 | B19: Luisandro Nachtigal Bandeira | E19: =13341.57+1200.74 | F19: =13341.57+1200.74 | G19: =13341.57+1200.74 | H19: =13341.57+1200.74 | I19: =13341.57+1200.74 | J19: =13341.57+1200.74 | K19: =13341.57+1200.74 | L19: =13341.57+1200.74 | M19: =13341.57+1200.74 | N19: =M19*1.05 | O19: =N19 | P19: =O19 | Q19: =P19 | R19: =Q19 | S19: =R19 | T19: =S19 | U19: =T19 | V19: =U19 | ... Y19: =X19 | Z19: =Y19*1.05 | AA19: =Z19 | AB19: =AA19 | AC19: =AB19 | AD19: =AC19 | AE19: =AD19 | AF19: =AE19 | AG19: =AF19 | AH19: =AG19 | AI19: =AH19 | AJ19: =SUM(E19:AI19)
A20: =A19+1 | B20: Patricia Royes Schardosin | E20: =6015.01+541.35 | F20: =6015.01+541.35 | G20: =6015.01+541.35 | H20: =6015.01+541.35 | I20: =6015.01+541.35 | J20: =6015.01+541.35 | K20: =6015.01+541.35 | L20: =6015.01+541.35 | M20: =6015.01+541.35 | N20: =M20*1.05 | O20: =N20 | P20: =O20 | Q20: =P20 | R20: =Q20 | S20: =R20 | T20: =S20 | U20: =T20 | V20: =U20 | ... Y20: =X20 | Z20: =Y20*1.05 | AA20: =Z20 | AB20: =AA20 | AC20: =AB20 | AD20: =AC20 | AE20: =AD20 | AF20: =AE20 | AG20: =AF20 | AH20: =AG20 | AI20: =AH20 | AJ20: =SUM(E20:AI20)
A21: =A20+1 | B21: Paula Carolina Ribeiro | E21: =11430.05+685.8 | F21: =11430.05+685.8 | G21: =11430.05+685.8 | H21: =11430.05+685.8 | I21: =11430.05+685.8 | J21: =11430.05+685.8 | K21: =11430.05+685.8 | L21: =11430.05+685.8 | M21: =11430.05+685.8 | N21: =M21*1.05 | O21: =N21 | P21: =O21 | Q21: =P21 | R21: =Q21 | S21: =R21 | T21: =S21 | U21: =T21 | V21: =U21 | ... Y21: =X21 | Z21: =Y21*1.05 | AA21: =Z21 | AB21: =AA21 | AC21: =AB21 | AD21: =AC21 | AE21: =AD21 | AF21: =AE21 | AG21: =AF21 | AH21: =AG21 | AI21: =AH21 | AJ21: =SUM(E21:AI21)
A22: =A21+1 | B22: Renan Ferreira Renzo | E22: =5472.12 | F22: =5472.12 | G22: =5472.12 | H22: =5472.12 | I22: =5472.12 | J22: =5472.12 | K22: =5472.12 | L22: =5472.12 | M22: =5472.12 | N22: =M22*1.05 | O22: =N22 | P22: =O22 | Q22: =P22 | R22: =Q22 | S22: =R22 | T22: =S22 | U22: =T22 | V22: =U22 | ... Y22: =X22 | Z22: =Y22*1.05 | AA22: =Z22 | AB22: =AA22 | AC22: =AB22 | AD22: =AC22 | AE22: =AD22 | AF22: =AE22 | AG22: =AF22 | AH22: =AG22 | AI22: =AH22 | AJ22: =SUM(E22:AI22)
A23: =A22+1 | B23: Renata Bruckmann Gomes Machado | E23: =8903.28+267.1 | F23: =8903.28+267.1 | G23: =8903.28+267.1 | H23: =8903.28+267.1 | I23: =8903.28+267.1 | J23: =8903.28+267.1 | K23: =8903.28+267.1 | L23: =8903.28+267.1 | M23: =8903.28+267.1 | N23: =M23*1.05 | O23: =N23 | P23: =O23 | Q23: =P23 | R23: =Q23 | S23: =R23 | T23: =S23 | U23: =T23 | V23: =U23 | ... Y23: =X23 | Z23: =Y23*1.05 | AA23: =Z23 | AB23: =AA23 | AC23: =AB23 | AD23: =AC23 | AE23: =AD23 | AF23: =AE23 | AG23: =AF23 | AH23: =AG23 | AI23: =AH23 | AJ23: =SUM(E23:AI23)
A24: =A23+1 | B24: Ricardo da Cunha Pereira | E24: =13778.5+413.36 | F24: =13778.5+413.36 | G24: =13778.5+413.36 | H24: =13778.5+413.36 | I24: =13778.5+413.36 | J24: =13778.5+413.36 | K24: =13778.5+413.36 | L24: =13778.5+413.36 | M24: =13778.5+413.36 | N24: =M24*1.05 | O24: =N24 | P24: =O24 | Q24: =P24 | R24: =Q24 | S24: =R24 | T24: =S24 | U24: =T24 | V24: =U24 | ... Y24: =X24 | Z24: =Y24*1.05 | AA24: =Z24 | AB24: =AA24 | AC24: =AB24 | AD24: =AC24 | AE24: =AD24 | AF24: =AE24 | AG24: =AF24 | AH24: =AG24 | AI24: =AH24 | AJ24: =SUM(E24:AI24)
A25: =A24+1 | B25: Victor Lima Costa | E25: 7305.2 | F25: 7305.2 | G25: 7305.2 | H25: 7305.2 | I25: 7305.2 | J25: 7305.2 | K25: 7305.2 | L25: 7305.2 | M25: 7305.2 | N25: =M25*1.05 | O25: =N25 | P25: =O25 | Q25: =P25 | R25: =Q25 | S25: =R25 | T25: =S25 | U25: =T25 | V25: =U25 | ... Y25: =X25 | Z25: =Y25*1.05 | AA25: =Z25 | AB25: =AA25 | AC25: =AB25 | AD25: =AC25 | AE25: =AD25 | AF25: =AE25 | AG25: =AF25 | AH25: =AG25 | AI25: =AH25 | AJ25: =SUM(E25:AI25)
A26: =A25+1 | B26: Vitor Motoaki Yabiku | E26: =11495.69+689.74 | F26: =11495.69+689.74 | G26: =11495.69+689.74 | H26: =11495.69+689.74 | I26: =11495.69+689.74 | J26: =11495.69+689.74 | K26: =11495.69+689.74 | L26: =11495.69+689.74 | M26: =11495.69+689.74 | N26: =M26*1.05 | O26: =N26 | P26: =O26 | Q26: =P26 | R26: =Q26 | S26: =R26 | T26: =S26 | U26: =T26 | V26: =U26 | ... Y26: =X26 | Z26: =Y26*1.05 | AA26: =Z26 | AB26: =AA26 | AC26: =AB26 | AD26: =AC26 | AE26: =AD26 | AF26: =AE26 | AG26: =AF26 | AH26: =AG26 | AI26: =AH26 | AJ26: =SUM(E26:AI26)
A27: =A26+1 | B27: Encargos Trabalhistas | E27: =(SUM(E4:E26)*0.8) | F27: =(SUM(F4:F26)*0.8) | G27: =(SUM(G4:G26)*0.8) | H27: =(SUM(H4:H26)*0.8) | I27: =(SUM(I4:I26)*0.8) | J27: =(SUM(J4:J26)*0.8) | K27: =(SUM(K4:K26)*0.8) | L27: =(SUM(L4:L26)*0.8) | ... AI27: =(SUM(AI4:AI26)*0.8) | AJ27: =SUM(E27:AI27) | BK27: 5236091 | BL27: =AJ27-BK27
A28: =A27+1 | B28: Alana Piccoli de Mello Correa | E28: 1050 | F28: 1050 | G28: 1050 | H28: 1050 | I28: 1050 | J28: 1050 | K28: 1050 | L28: 1050 | M28: 1050 | N28: 1050 | O28: 1050 | P28: 1050 | Q28: 1050 | R28: 1050 | S28: 1050 | T28: 1050 | U28: 1050 | V28: 1050 | W28: 1050 | X28: 1050 | Y28: 1050 | Z28: 1050 | AA28: 1050 | AJ28: =SUM(E28:AI28)
A29: =A28+1 | B29: Eduarda Vieira Florindo Tinoco | E29: 2200 | F29: 2200 | G29: 2200 | H29: 2200 | I29: 2200 | J29: 2200 | K29: 2200 | L29: 2200 | M29: 2200 | N29: 2200 | O29: 2200 | P29: 2200 | Q29: 2200 | R29: 2200 | S29: 2200 | T29: 2200 | U29: 2200 | V29: 2200 | W29: 2200 | X29: 2200 | Y29: 2200 | Z29: 2200 | AA29: 2200 | AB29: 2200 | AC29: 2200 | AD29: 2200 | AE29: 2200 | AF29: 2200 | AG29: 2200 | AH29: 2200 | AJ29: =SUM(E29:AI29)
A30: =A29+1 | B30: Eduardo Lobo | E30: 3000 | AJ30: =SUM(E30:AI30)
A31: =A30+1 | B31: Fernando Seabra | E31: 3000 | F31: 3000 | G31: 3000 | H31: 3000 | I31: 3000 | J31: 3000 | K31: 3000 | L31: 3000 | M31: 3000 | N31: 3000 | O31: 3000 | P31: 3000 | Q31: 3000 | R31: 3000 | S31: 3000 | T31: 3000 | U31: 3000 | V31: 3000 | W31: 3000 | X31: 3000 | Y31: 3000 | Z31: 3000 | AA31: 3000 | AJ31: =SUM(E31:AI31)
A32: =A31+1 | B32: Germano dos Reis Rivera | E32: 1050 | F32: 1050 | G32: 1050 | H32: 1050 | I32: 1050 | J32: 1050 | K32: 1050 | L32: 1050 | M32: 1050 | AJ32: =SUM(E32:AI32)
A33: =A32+1 | B33: Giulia Kaminski | E33: 1050 | F33: 1050 | G33: 1050 | H33: 1050 | I33: 1050 | J33: 1050 | K33: 1050 | L33: 1050 | M33: 1050 | AJ33: =SUM(E33:AI33)
A34: =A33+1 | B34: Isadora da Silva Cardoso | E34: 1050 | F34: 1050 | G34: 1050 | H34: 1050 | I34: 1050 | J34: 1050 | K34: 1050 | L34: 1050 | M34: 1050 | N34: 1050 | O34: 1050 | P34: 1050 | Q34: 1050 | R34: 1050 | S34: 1050 | T34: 1050 | U34: 1050 | V34: 1050 | W34: 1050 | X34: 1050 | Y34: 1050 | Z34: 1050 | AA34: 1050 | AB34: 1050 | AC34: 1050 | AD34: 1050 | AE34: 1050 | AF34: 1050 | AG34: 1050 | AH34: 1050 | AJ34: =SUM(E34:AI34)
A35: =A34+1 | B35: João Sérgio Silva Santos | E35: 3200 | F35: 3200 | G35: 3200 | H35: 3200 | I35: 3200 | J35: 3200 | K35: 3200 | L35: 3200 | M35: 3200 | N35: 3200 | O35: 3200 | P35: 3200 | Q35: 3200 | R35: 3200 | S35: 3200 | T35: 3200 | U35: 3200 | V35: 3200 | W35: 3200 | X35: 3200 | Y35: 3200 | Z35: 3200 | AJ35: =SUM(E35:AI35)
A36: =A35+1 | B36: Liseane Padilha Thives | E36: 3000 | AJ36: =SUM(E36:AI36)
A37: =A36+1 | B37: Luiza Ana Vendramin | E37: 1625 | F37: 1625 | G37: 1625 | H37: 1625 | I37: 1625 | J37: 1625 | K37: 1625 | AJ37: =SUM(E37:AI37)
A38: =A37+1 | B38: Rafael Augusto Dos Reis Higashi | E38: 3000 | AJ38: =SUM(E38:AI38)
A39: =A38+1 | B39: Roberto Caldas De Andrade Pinto | E39: 3000 | AJ39: =SUM(E39:AI39)
A40: =A39+1 | B40: Stephanie Thiesen | E40: 3000 | AJ40: =SUM(E40:AI40)
A41: =A40+1 | B41: Vinícios Rosa Buzzi | E41: 1050 | F41: 1050 | G41: 1050 | H41: 1050 | I41: 1050 | J41: 1050 | K41: 1050 | L41: 1050 | M41: 1050 | AJ41: =SUM(E41:AI41)
A42: =A41+1 | B42: Vinícius Chaves | E42: 1050 | F42: 1050 | G42: 1050 | H42: 1050 | I42: 1050 | J42: 1050 | K42: 1050 | L42: 1050 | M42: 1050 | N42: 1050 | O42: 1050 | P42: 1050 | Q42: 1050 | R42: 1050 | AJ42: =SUM(E42:AI42)
A43: =A42+1 | B43: Wellington Longuini Repette | E43: 4800 | F43: 4800 | G43: 4800 | H43: 4800 | I43: 4800 | J43: 4800 | K43: 4800 | AJ43: =SUM(E43:AI43)
A44: =A43+1 | B44: Consultores | E44: 20000 | F44: 20000 | G44: 20000 | H44: 20000 | I44: 20000 | J44: 20000 | K44: 20000 | L44: 20000 | M44: 20000 | N44: 20000 | O44: 20000 | P44: 20000 | Q44: 20000 | R44: 20000 | S44: 20000 | T44: 20000 | U44: 20000 | V44: 20000 | W44: 20000 | X44: 20000 | Y44: 20000 | Z44: 20000 | AA44: 20000 | AB44: 20000 | AC44: 20000 | AD44: 20000 | AE44: 20000 | AF44: 20000 | AG44: 20000 | AH44: 20000 | AI44: 20000 | AJ44: =SUM(E44:AI44)
A45: =A44+1 | B45: Serviços de Terceiros | E45: 45000 | F45: 45000 | G45: 45000 | H45: 45000 | I45: 45000 | J45: 45000 | K45: 45000 | L45: 45000 | M45: 45000 | N45: 45000 | O45: 45000 | P45: 45000 | Q45: 45000 | R45: 45000 | S45: 45000 | T45: 45000 | U45: 45000 | V45: 45000 | W45: 45000 | X45: 45000 | Y45: 45000 | Z45: 45000 | AA45: 45000 | AB45: 45000 | AC45: 45000 | AD45: 45000 | AE45: 45000 | AF45: 45000 | AG45: 45000 | AH45: 45000 | AI45: 45000 | AJ45: =SUM(E45:AI45)
A46: =A45+1 | B46: Passagens aéreas | E46: 30000 | F46: 30000 | G46: 30000 | H46: 30000 | I46: 30000 | J46: 30000 | K46: 30000 | L46: 30000 | M46: 30000 | N46: 30000 | O46: 30000 | P46: 30000 | Q46: 30000 | R46: 30000 | S46: 30000 | T46: 30000 | U46: 30000 | V46: 30000 | W46: 30000 | X46: 30000 | Y46: 30000 | Z46: 30000 | AA46: 30000 | AB46: 30000 | AC46: 30000 | AD46: 30000 | AE46: 30000 | AF46: 30000 | AG46: 30000 | AH46: 30000 | AI46: 30000 | AJ46: =SUM(E46:AI46)
A47: =A46+1 | B47: Diárias | E47: 15000 | F47: 15000 | G47: 15000 | H47: 15000 | I47: 15000 | J47: 15000 | K47: 15000 | L47: 15000 | M47: 15000 | N47: 15000 | O47: 15000 | P47: 15000 | Q47: 15000 | R47: 15000 | S47: 15000 | T47: 15000 | U47: 15000 | V47: 15000 | W47: 15000 | X47: 15000 | Y47: 15000 | Z47: 15000 | AA47: 15000 | AB47: 15000 | AC47: 15000 | AD47: 15000 | AE47: 15000 | AF47: 15000 | AG47: 15000 | AH47: 15000 | AI47: 15000 | AJ47: =SUM(E47:AI47)
A48: =A47+1 | B48: Material de Consumo | E48: 3000 | F48: 3000 | G48: 3000 | H48: 3000 | I48: 3000 | J48: 3000 | K48: 3000 | L48: 3000 | M48: 3000 | N48: 3000 | O48: 3000 | P48: 3000 | Q48: 3000 | R48: 3000 | S48: 3000 | T48: 3000 | U48: 3000 | V48: 3000 | W48: 3000 | X48: 3000 | Y48: 3000 | Z48: 3000 | AA48: 3000 | AB48: 3000 | AC48: 3000 | AD48: 3000 | AE48: 3000 | AF48: 3000 | AG48: 3000 | AH48: 3000 | AI48: 3000 | AJ48: =SUM(E48:AI48)
A49: subtotal | E49: =SUM(E4:E48) | F49: =SUM(F4:F48) | G49: =SUM(G4:G48) | H49: =SUM(H4:H48) | I49: =SUM(I4:I48) | J49: =SUM(J4:J48) | K49: =SUM(K4:K48) | L49: =SUM(L4:L48) | ... AJ49: =SUM(AJ4:AJ48)
A50: =A48+1 | B50: FAPEU | D50: 0.0755 | E50: =E2*$D$50 | F50: =F2*$D$50 | G50: =G2*$D$50 | H50: =H2*$D$50 | I50: =I2*$D$50 | J50: =J2*$D$50 | K50: =K2*$D$50 | L50: =L2*$D$50 | ... AI50: =AI2*$D$50 | AJ50: =SUM(E50:AI50)
A51: =A50+1 | B51: Centro Tecnológico | D51: 0.01 | E51: =E2*$D$51 | F51: =F2*$D$51 | G51: =G2*$D$51 | H51: =H2*$D$51 | I51: =I2*$D$51 | J51: =J2*$D$51 | K51: =K2*$D$51 | L51: =L2*$D$51 | ... AI51: =AI2*$D$51 | AJ51: =SUM(E51:AI51)
A52: =A51+1 | B52: E.C.V. | D52: 0.02 | E52: =E2*$D$52 | F52: =F2*$D$52 | G52: =G2*$D$52 | H52: =H2*$D$52 | I52: =I2*$D$52 | J52: =J2*$D$52 | K52: =K2*$D$52 | L52: =L2*$D$52 | ... AI52: =AI2*$D$52 | AJ52: =SUM(E52:AI52)
A53: =A52+1 | B53: UFSC | D53: 0.04 | E53: =E2*$D$53 | F53: =F2*$D$53 | G53: =G2*$D$53 | H53: =H2*$D$53 | I53: =I2*$D$53 | J53: =J2*$D$53 | K53: =K2*$D$53 | L53: =L2*$D$53 | ... AI53: =AI2*$D$53 | AJ53: =SUM(E53:AI53)
A54: subtotal2 | E54: =SUM(E50:E53) | F54: =SUM(F50:F53) | G54: =SUM(G50:G53) | H54: =SUM(H50:H53) | I54: =SUM(I50:I53) | J54: =SUM(J50:J53) | K54: =SUM(K50:K53) | L54: =SUM(L50:L53) | ... AJ54: =SUM(AJ50:AJ53)
A55: Total Despesas | E55: =E54+E49 | F55: =F54+F49 | G55: =G54+G49 | H55: =H54+H49 | I55: =I54+I49 | J55: =J54+J49 | K55: =K54+K49 | L55: =L54+L49 | ... AJ55: =AJ54+AJ49
A56: Saldos | D56: =H67 | E56: =D56+E2-E55 | F56: =E56+F2-F55 | G56: =F56+G2-G55 | H56: =G56+H2-H55 | I56: =H56+I2-I55 | J56: =I56+J2-J55 | K56: =J56+K2-K55 | L56: =K56+L2-L55 | ... AI56: =AH56+AI2-AI55 | AJ56: =D56+AJ2-D2-AJ55
A58: N˚ | B58: Rubricas | C58: Perc. | D58: Previsto | E58: Recebido | F58: A Receber | G58: Gasto | H58: Saldo | I58: A gastar | J58: Result.
A59: 1 | B59: Aplicação em Fundos | C59: 0 | D59: 0 | E59: 0 | F59: 0 | G59: 0 | H59: 111371.52 | I59: 0 | J59: =H59-I59
A60: =A59+1 | B60: Passagens | C60: =D60/59992083 | D60: 1897000 | E60: =33902922*C60 | F60: =D60-E60 | G60: 0 | H60: =E60+G60 | I60: 0 | J60: =E60+F60+G60+I60 | L60: Resultado
A61: =A60+1 | B61: Diárias | C61: =D61/59992083 | D61: 975600 | E61: =33902922*C61 | F61: =D61-E61 | G61: 0 | H61: =E61+G61 | I61: 0 | J61: =E61+F61+G61+I61 | L61: Poupança
A62: =A61+1 | B62: Material de Consumo | C62: =D62/59992083 | D62: 390000 | E62: =33902922*C62 | F62: =D62-E62 | G62: 0 | H62: =E62+G62 | I62: 0 | J62: =E62+F62+G62+I62 | L62: Previsto
A63: =A62+1 | B63: Equipe Técnica | C63: =D63/59992083 | D63: 45126513 | E63: =33902922*C63 | F63: =D63-E63 | G63: 0 | H63: =E63+G63 | I63: 0 | J63: =E63+F63+G63+I63
A64: =A63+1 | B64: Serviço de Terceiros | C64: =D64/59992083 | D64: 2874122.2 | E64: =33902922*C64 | F64: =D64-E64 | G64: 0 | H64: =E64+G64 | I64: 0 | J64: =E64+F64+G64+I64 | L64: Inicio | M64: 45272
A65: =A64+1 | B65: FAPEU | C65: =D65/59992083 | D65: 4529402.3 | E65: =33902922*C65 | F65: =D65-E65 | G65: 0 | H65: =E65+G65 | I65: 0 | J65: =E65+F65+G65+I65 | L65: Duração | M65: 60 meses
A66: =A65+1 | B66: UFSC | C66: =D66/59992083 | D66: 4199445.8 | E66: =33902922*C66 | F66: =D66-E66 | G66: =-5919866-33902922-111372 | H66: =E66+G66 | I66: =-AJ55 | J66: =E66+F66+G66+I66 | L66: Fim | M66: 47099
B67: Totais | C67: =SUM(C60:C66) | D67: =SUM(D59:D66) | E67: =SUM(E59:E66) | F67: =SUM(F59:F66) | G67: =SUM(G59:G66) | H67: =SUM(H59:H66) | I67: =SUM(I59:I66) | J67: =SUM(J59:J66)
A70: Vigência do TED | D70: 45272 | E70: 47099
A71: Vigência de Execução | D71: =D70 | E71: =E70
A72: Vigência do Contrato | D72: 45314 | E72: 47099
A73: Fiscais | D73: Jucilei | E73: Ana

Sheet Prodesp
A1: N˚ | B1: Receita | D1: Até mai/26 | E1: 46174 | F1: 46204 | G1: 46235 | H1: 46266 | I1: 46296 | J1: 46327 | K1: 46357 | L1: 46388 | M1: 46419 | N1: 46447 | O1: 46478 | P1: Totais
A2: 1 | B2: Parcelas | D2: =E93 | E2: =1499855+1499855 | F2: 0 | G2: 1499855 | H2: 0 | I2: 0 | J2: 2249783 | K2: 0 | L2: 0 | M2: 2249783 | N2: 0 | O2: 749925 | P2: =SUM(D2:O2)
A3: N˚ | B3: Despesas | E3: =E1 | F3: =F1 | G3: =G1 | H3: =H1 | I3: =I1 | J3: =J1 | K3: =K1 | L3: =L1 | ... O3: =O1 | P3: Totais
A4: 1 | B4: Alberto Hauch Martinho | E4: =3173.83 | F4: =3173.83 | P4: =SUM(E4:O4)
A5: =A4+1 | B5: Alyne Zelinda de Barros | E5: =3548.24 | F5: =3548.24 | P5: =SUM(E5:O5)
A6: =A5+1 | B6: Davyd Carlos Martins | E6: =7652.5+797.57 | F6: =7652.5+797.57 | P6: =SUM(E6:O6)
A7: =A6+1 | B7: Débora Cristina Siridakis Correa | E7: =4813.76+288.83 | F7: =4813.76+288.83 | P7: =SUM(E7:O7)
A8: =A7+1 | B8: Gabriel da Cunha Lima | E8: =3721.04 | F8: =3721.04 | P8: =SUM(E8:O8)
A9: =A8+1 | B9: Graziane da Rocha Silveira | E9: =4297.8+257.87 | F9: =4297.8+257.87 | P9: =SUM(E9:O9)
A10: =A9+1 | B10: Inês Peglow | E10: =3907.09+801.71+423.79 | F10: =3907.09+801.71+423.79 | P10: =SUM(E10:O10)
A11: =A10+1 | B11: Karin Cristina Amorim | E11: =3597.65+431.72 | F11: =3597.65+431.72 | P11: =SUM(E11:O11)
A12: =A11+1 | B12: Lara Caldeira de Andrade e Silva | E12: =3907.09+234.43 | F12: =3907.09+234.43 | P12: =SUM(E12:O12)
A13: =A12+1 | B13: Lisiane do Carmo Nascimento de Oliveira Bispo | E13: =2606.08 | F13: =2606.08 | P13: =SUM(E13:O13)
A14: =A13+1 | B14: Mara Regina Bernardini | E14: =4626.83+694.02 | F14: =4626.83+694.02 | P14: =SUM(E14:O14)
A15: =A14+1 | B15: Marcos Antonio Braga | E15: =3548.24+638.68 | F15: =3548.24+638.68 | P15: =SUM(E15:O15)
A16: =A15+1 | B16: Marta Cristiani de Avila Rosa | E16: =3907.09+351.64 | F16: =3907.09+351.64 | P16: =SUM(E16:O16)
A17: =A16+1 | B17: Pedro Marques Abdo | E17: =3943.75+236.62 | F17: =3943.75+236.62 | P17: =SUM(E17:O17)
A18: =A17+1 | B18: Renilda de Quadros | E18: =4022.64+603.4 | F18: =4022.64+603.4 | P18: =SUM(E18:O18)
A19: =A18+1 | B19: Rithyelen Aliny da Silveira | E19: =3907.09+351.64 | F19: =3907.09+351.64 | P19: =SUM(E19:O19)
A20: =A19+1 | B20: Thiago de Almeida Rebollo | E20: 3550.24 | F20: 3551.24 | P20: =SUM(E20:O20)
A21: =A20+1 | B21: Alexandre Garcez Nunes | E21: =12180.93+730.88 | F21: =12180.93+730.88 | P21: =SUM(E21:O21)
A22: =A21+1 | B22: Bruno Maluche Neto | E22: =(19765.28+4743.67)*$Q$22 | F22: =(19765.28+4743.67)*$Q$22 | P22: =SUM(E22:O22) | Q22: =1-0.2574
A23: =A22+1 | B23: Fernanda Miranda | E23: =10052.21+904.7 | F23: =10052.21+904.7 | P23: =SUM(E23:O23)
A24: =A23+1 | B24: Giseli de Sousa | E24: =13593.2+1223.39 | F24: =13593.2+1223.39 | P24: =SUM(E24:O24)
A25: =A24+1 | B25: Joao Gabriel Crema | E25: =13592.7+2038.9 | F25: =13592.7+2038.9 | P25: =SUM(E25:O25)
A26: =A25+1 | B26: Josivan Laskoski | E26: =17670.52+2120.46 | F26: =17670.52+2120.46 | P26: =SUM(E26:O26)
A27: =A26+1 | B27: Marcelo Maciel Pereira | E27: =(11583.15+2779.96)*$Q$27 | F27: =(11583.15+2779.96)*$Q$27 | P27: =SUM(E27:O27) | Q27: =1-0.7862
A28: =A27+1 | B28: Morgana Leite | E28: =5994.65+539.52 | F28: =5994.65+539.52 | P28: =SUM(E28:O28)
A29: =A28+1 | B29: Rafael Berretta | E29: =5341.55+480.74 | F29: =5341.55+480.74 | P29: =SUM(E29:O29)
A30: =A29+1 | B30: Thaysa Momm Bastos | E30: =(6794.33+407.66)*$Q$30 | F30: =(6794.33+407.66)*$Q$30 | P30: =SUM(E30:O30) | Q30: =1-0.8144
A31: =A30+1 | B31: Alexandre Gonçalves | E31: =6153.88+369.23 | F31: =6153.88+369.23 | P31: =SUM(E31:O31)
A32: =A31+1 | B32: Aline Martins de Souza | E32: =5335.31+320.12 | F32: =5335.31+320.12 | P32: =SUM(E32:O32)
A33: =A32+1 | B33: Daniel Vieira Machado | E33: =12893.4 | F33: =12893.4 | P33: =SUM(E33:O33)
A34: =A33+1 | B34: Danilo Franklin Leite Lopes | E34: =7551.52 | F34: =7551.52 | P34: =SUM(E34:O34)
A35: =A34+1 | B35: Débora Machado Gonçalves | E35: =5635.44 | F35: =5635.44 | P35: =SUM(E35:O35)
A36: =A35+1 | B36: Deucélia Eva Pedroso | E36: =14406.21+864.37 | F36: =14406.21+864.37 | P36: =SUM(E36:O36)
A37: =A36+1 | B37: Eder Tagveira dos Santos | E37: 10500 | F37: 10500 | P37: =SUM(E37:O37)
A38: =A37+1 | B38: Elizabeth Ventura da Silva | E38: =4615.4+553.85 | F38: =4615.4+553.85 | P38: =SUM(E38:O38)
A39: =A38+1 | B39: Érika Cavalcante de Souza Tartari | E39: =6566.54 | F39: =6566.54 | P39: =SUM(E39:O39)
A40: =A39+1 | B40: Gabriel Domingos Adriano | E40: =6019.33 | F40: =6019.33 | P40: =SUM(E40:O40)
A41: =A40+1 | B41: Gabriel Phillipe Ferreira Perpetuo | E41: =4487.14 | F41: =4487.14 | P41: =SUM(E41:O41)
A42: =A41+1 | B42: Gastão Cassel | E42: =11091.26+1330.95 | F42: =11091.26+1330.95 | P42: =SUM(E42:O42)
A43: =A42+1 | B43: Gustavo Garcia Otto | E43: =4906.09+735.91 | F43: =4906.09+735.91 | P43: =SUM(E43:O43)
A44: =A43+1 | B44: Irene Rios da Silva | E44: =12153.91+729.23 | F44: =12153.91+729.23 | P44: =SUM(E44:O44)
A45: =A44+1 | B45: João Luiz Martins | E45: =6347.66+380.86 | F45: =6347.66+380.86 | P45: =SUM(E45:O45)
A46: =A45+1 | B46: Jorge Luiz Silva Hermenegildo | E46: =20543.33+1232.6 | F46: =20543.33+1232.6 | P46: =SUM(E46:O46)
A47: =A46+1 | B47: Junior Mateus Alves Camargo | E47: =13351.96+400.56 | F47: =13351.96+400.56 | P47: =SUM(E47:O47)
A48: =A47+1 | B48: Keyla Junko Shinohara | E48: =16181.63+1941.8 | F48: =16181.63+1941.8 | P48: =SUM(E48:O48)
A49: =A48+1 | B49: Leia Mayer Eyng | E49: =7989.29 | F49: =7989.29 | P49: =SUM(E49:O49)
A50: =A49+1 | B50: Luciana Paula Bonetti Silva | E50: 7113.75 | F50: 7113.75 | P50: =SUM(E50:O50)
A51: =A50+1 | B51: Maeli Faé | E51: =12620.75+757.24 | F51: =12620.75+757.24 | P51: =SUM(E51:O51)
A52: =A51+1 | B52: Paulo Roberto Xavier | E52: =8410.29+504.62 | F52: =8410.29+504.62 | P52: =SUM(E52:O52)
A53: =A52+1 | B53: Rafael Aleixo de Souza | E53: =10949.97+985.5 | F53: =10949.97+985.5 | P53: =SUM(E53:O53)
A54: =A53+1 | B54: Ronivaldo Pereira de Araujo | E54: =9630.93+866.78 | F54: =9630.93+866.78 | P54: =SUM(E54:O54)
A55: =A54+1 | B55: Rubens Costa da Silva | E55: =6566.54 | F55: =6566.54 | P55: =SUM(E55:O55)
A56: =A55+1 | B56: Amir Mattar Valente | E56: =26813.37+804.4 | F56: =26813.37+804.4 | P56: =SUM(E56:O56)
A57: =A56+1 | B57: Carla Santana | E57: =6565.16+787.82 | F57: =6565.16+787.82 | P57: =SUM(E57:O57)
A58: =A57+1 | B58: Caroline Fagundes | E58: =5086.62+305.2 | F58: =5086.62+305.2 | P58: =SUM(E58:O58)
A59: =A58+1 | B59: Daniela Vogel | E59: =(8390.54+1510.3)*$Q$59 | F59: =(8390.54+1510.3)*$Q$59 | P59: =SUM(E59:O59) | Q59: =1-0.4584
A60: =A59+1 | B60: Marciel Manoel dos Santos | E60: =25242.11+4543.58 | F60: =25242.11+4543.58 | P60: =SUM(E60:O60)
A61: =A60+1 | B61: Maurilia Maria Dias | E61: =1499.36+134.94 | F61: =1499.36+134.94 | P61: =SUM(E61:O61)
A62: =A61+1 | B62: Claudio de Marafigo | E62: =4414.43+662.16 | F62: =4414.43+662.16 | P62: =SUM(E62:O62)
A63: =A62+1 | B63: Cleber Tomaz | E63: =5312.97+159.39 | F63: =5312.97+159.39 | P63: =SUM(E63:O63)
A64: =A63+1 | B64: Eduardo Felipe Duarte Schmidt Hebbel | E64: =5278.53+158.36 | F64: =5278.53+158.36 | P64: =SUM(E64:O64)
A65: =A64+1 | B65: Gustavo Henrique Buch | E65: =10944.23+656.65 | F65: =10944.23+656.65 | P65: =SUM(E65:O65)
A66: =A65+1 | B66: Jardel Ferreira | E66: =5278.53+158.36 | F66: =5278.53+158.36 | P66: =SUM(E66:O66)
A67: =A66+1 | B67: Juan Morallys Lucena Silva | E67: =4817.79+144.53 | F67: =4817.79+144.53 | P67: =SUM(E67:O67)
A68: =A67+1 | B68: Luiza de Oliveira Santos | E68: 4377.69 | F68: 4377.69 | P68: =SUM(E68:O68)
A69: =A68+1 | B69: João Eugênio Cavallazzi | E69: =8065.65+483.94 | F69: =8065.65+483.94 | P69: =SUM(E69:O69)
A70: =A69+1 | B70: Encargos Trabalhistas | E70: =SUM(E4:E69)*0.8 | F70: =SUM(F4:F69)*0.8 | G70: =SUM(G4:G69)*0.8 | H70: =SUM(H4:H69)*0.8 | I70: =SUM(I4:I69)*0.8 | J70: =SUM(J4:J69)*0.8 | K70: =SUM(K4:K69)*0.8 | L70: =SUM(L4:L69)*0.8 | ... O70: =SUM(O4:O69)*0.8 | P70: =SUM(E70:O70)
A71: =A70+1 | B71: Aline Gambin | E71: 3200 | F71: 3200 | G71: 3200 | H71: 3200 | I71: 3200 | J71: 3200 | K71: 3200 | L71: 3200 | M71: 3200 | N71: 3200 | O71: 3200 | P71: =SUM(E71:O71)
A72: =A71+1 | B72: Amanda Maciel da Silva | E72: 1050 | F72: 1050 | G72: 1050 | H72: 1050 | I72: 1050 | J72: 1050 | K72: 1050 | L72: 1050 | M72: 1050 | N72: 1050 | O72: 1050 | P72: =SUM(E72:O72)
A73: =A72+1 | B73: Beatriz Martins Rachadel | E73: 1050 | F73: 1050 | G73: 1050 | H73: 1050 | I73: 1050 | J73: 1050 | K73: 1050 | L73: 1050 | M73: 1050 | N73: 1050 | O73: 1050 | P73: =SUM(E73:O73)
A74: =A73+1 | B74: Érica Milani Dellai | E74: 1050 | F74: 1050 | G74: 1050 | H74: 1050 | I74: 1050 | J74: 1050 | K74: 1050 | L74: 1050 | M74: 1050 | N74: 1050 | O74: 1050 | P74: =SUM(E74:O74)
A75: =A74+1 | B75: Eveliny Dias de Medeiros | E75: 3200 | F75: 3200 | G75: 3200 | H75: 3200 | I75: 3200 | J75: 3200 | K75: 3200 | L75: 3200 | M75: 3200 | N75: 3200 | O75: 3200 | P75: =SUM(E75:O75)
A76: =A75+1 | B76: Joanna de Souza Kehring | E76: 1050 | F76: 1050 | G76: 1050 | H76: 1050 | I76: 1050 | J76: 1050 | K76: 1050 | L76: 1050 | M76: 1050 | N76: 1050 | O76: 1050 | P76: =SUM(E76:O76)
A77: =A76+1 | B77: Júlia Mayer Eyng | E77: 1050 | F77: 1050 | P77: =SUM(E77:O77)
A78: =A77+1 | B78: Liandra Dos Santos Jesus | E78: 3200 | F78: 3200 | G78: 3200 | H78: 3200 | I78: 3200 | J78: 3200 | K78: 3200 | L78: 3200 | M78: 3200 | N78: 3200 | O78: 3200 | P78: =SUM(E78:O78)
A79: =A78+1 | B79: Serviços de Terceiros | E79: 4000 | F79: 4000 | G79: 4000 | H79: 4000 | I79: 4000 | J79: 4000 | K79: 4000 | L79: 4000 | M79: 4000 | N79: 4000 | O79: 4000 | P79: =SUM(E79:O79)
A80: =A79+1 | B80: Passagens aéreas | E80: 18000 | F80: 18000 | G80: 18000 | H80: 18000 | I80: 18000 | J80: 18000 | K80: 18000 | L80: 18000 | M80: 18000 | N80: 18000 | O80: 18000 | P80: =SUM(E80:O80)
A81: =A80+1 | B81: Diárias | E81: 12000 | F81: 12000 | G81: 12000 | H81: 12000 | I81: 12000 | J81: 12000 | K81: 12000 | L81: 12000 | M81: 12000 | N81: 12000 | O81: 12000 | P81: =SUM(E81:O81)
A82: =A81+1 | B82: Material de Consumo | E82: 2500 | F82: 2500 | G82: 2500 | H82: 2500 | I82: 2500 | J82: 2500 | K82: 2500 | L82: 2500 | M82: 2500 | N82: 2500 | O82: 2500 | P82: =SUM(E82:O82)
A83: subtotal | E83: =SUM(E4:E82) | F83: =SUM(F4:F82) | G83: =SUM(G4:G82) | H83: =SUM(H4:H82) | I83: =SUM(I4:I82) | J83: =SUM(J4:J82) | K83: =SUM(K4:K82) | L83: =SUM(L4:L82) | ... P83: =SUM(P4:P82)
A84: =A82+1 | B84: FAPEU | D84: 0.0827 | E84: =E2*$D$84 | F84: =F2*$D$84 | G84: =G2*$D$84 | H84: =H2*$D$84 | I84: =I2*$D$84 | J84: =J2*$D$84 | K84: =K2*$D$84 | L84: =L2*$D$84 | ... O84: =O2*$D$84 | P84: =SUM(E84:O84)
A85: =A84+1 | B85: UFSC | D85: 0.07 | E85: =E2*$D$85 | F85: =F2*$D$85 | G85: =G2*$D$85 | H85: =H2*$D$85 | I85: =I2*$D$85 | J85: =J2*$D$85 | K85: =K2*$D$85 | L85: =L2*$D$85 | ... O85: =O2*$D$85 | P85: =SUM(E85:O85)
A86: subtotal2 | E86: =SUM(E84:E85) | F86: =SUM(F84:F85) | G86: =SUM(G84:G85) | H86: =SUM(H84:H85) | I86: =SUM(I84:I85) | J86: =SUM(J84:J85) | K86: =SUM(K84:K85) | L86: =SUM(L84:L85) | ... P86: =SUM(P84:P85)
A87: Total Despesas | E87: =E86+E83 | F87: =F86+F83 | G87: =G86+G83 | H87: =H86+H83 | I87: =I86+I83 | J87: =J86+J83 | K87: =K86+K83 | L87: =L86+L83 | ... P87: =P86+P83
A88: Saldos | D88: =H93 | E88: =D88+E2-E87 | F88: =E88+F2-F87 | G88: =F88+G2-G87 | H88: =G88+H2-H87 | I88: =H88+I2-I87 | J88: =I88+J2-J87 | K88: =J88+K2-K87 | L88: =K88+L2-L87 | ... O88: =N88+O2-O87 | P88: =D88+P2-D2-P87
A90: N˚ | B90: Rubricas | C90: Perc. | D90: Previsto | E90: Recebido | F90: A Receber | G90: Gasto | H90: Saldo | I90: A gastar | J90: Result. | L90: Inicio | M90: 45530
A91: 1 | B91: Aplicação em Fundos | C91: 0 | D91: 0 | F91: 0 | G91: 0 | H91: 15137.85 | I91: 0 | J91: =H91-I91 | L91: Duração
A92: =A91+1 | B92: Custos do |Projeto | C92: =D92/22661520 | D92: 22661520 | E92: 12912464 | F92: =D92-E92 | G92: =-5308000-12912464 | H92: =E92+G92 | I92: =-P87 | J92: =E92+F92+G92+I92 | L92: Fim | M92: 46503
B93: Totais | C93: =SUM(C92:C92) | D93: =SUM(D91:D92) | E93: =SUM(E91:E92) | F93: =SUM(F91:F92) | G93: =SUM(G91:G92) | H93: =SUM(H91:H92) | I93: =SUM(I91:I92) | J93: =SUM(J91:J92)

Sheet DER-MG
A1: N˚ | B1: Receita | D1: Até mai/26 | E1: 46174 | F1: 46204 | G1: 46235 | H1: 46266 | I1: 46296 | J1: 46327 | K1: 46357 | L1: 46388 | M1: 46419 | N1: 46447 | O1: Totais
A2: 1 | B2: Parcelas | D2: =E45 | E2: =400462+794997.15+520629 | F2: 0 | G2: 390715 | H2: 0 | I2: 404706 | J2: 0 | K2: 374383 | L2: 0 | M2: 122341 | N2: 0 | O2: =SUM(D2:N2)
A3: N˚ | B3: Despesas | E3: =E1 | F3: =F1 | G3: =G1 | H3: =H1 | I3: =I1 | J3: =J1 | K3: =K1 | L3: =L1 | ... N3: =N1 | O3: Totais
A4: 1 | B4: Adam Pereira Bidiaki | E4: 7305.2 | F4: 7305.2 | G4: 7305.2 | H4: 7305.2 | I4: 7305.2 | J4: 7305.2 | K4: 7305.2 | L4: 7305.2 | M4: 7305.2 | N4: 7305.2 | O4: =SUM(E4:N4)
A5: =A4+1 | B5: Alcyr Spindola Filho | E5: 4377.69 | F5: 4377.69 | G5: 4377.69 | H5: 4377.69 | I5: 4377.69 | J5: 4377.69 | K5: 4377.69 | L5: 4377.69 | M5: 4377.69 | N5: 4377.69 | O5: =SUM(E5:N5)
A6: =A5+1 | B6: Elvis Fagundes Lisboa Junior | E6: 4696.2 | F6: 4696.2 | G6: 4696.2 | H6: 4696.2 | I6: 4696.2 | J6: 4696.2 | K6: 4696.2 | L6: 4696.2 | M6: 4696.2 | N6: 4696.2 | O6: =SUM(E6:N6)
A7: =A6+1 | B7: Emanuel Espíndola | E7: =12900.99+1548.12 | F7: =12900.99+1548.12 | O7: =SUM(E7:N7)
A8: =A7+1 | B8: Kennildo Bastos Gonçalves | E8: 8348.8 | F8: 8348.8 | G8: 8348.8 | H8: 8348.8 | I8: 8348.8 | J8: 8348.8 | K8: 8348.8 | L8: 8348.8 | M8: 8348.8 | N8: 8348.8 | O8: =SUM(E8:N8)
A9: =A8+1 | B9: Keven Dantas da Silva | E9: 3861.32 | F9: 3861.32 | G9: 3861.32 | H9: 3861.32 | I9: 3861.32 | J9: 3861.32 | K9: 3861.32 | L9: 3861.32 | M9: 3861.32 | N9: 3861.32 | O9: =SUM(E9:N9)
A10: =A9+1 | B10: Pâmela Andressa Lunelli | E10: 6261.6 | F10: 6261.6 | G10: 6261.6 | H10: 6261.6 | I10: 6261.6 | J10: 6261.6 | K10: 6261.6 | L10: 6261.6 | M10: 6261.6 | N10: 6261.6 | O10: =SUM(E10:N10)
A11: =A10+1 | B11: Encargos s/pessoal contratado | E11: =SUM(E4:E10)*0.85 | F11: =SUM(F4:F10)*0.85 | G11: =SUM(G4:G10)*0.85 | H11: =SUM(H4:H10)*0.85 | I11: =SUM(I4:I10)*0.85 | J11: =SUM(J4:J10)*0.85 | K11: =SUM(K4:K10)*0.85 | L11: =SUM(L4:L10)*0.85 | ... N11: =SUM(N4:N10)*0.85 | O11: =SUM(E11:N11)
A12: =A11+1 | B12: Alexis Camilo Pantoja Pantoja | E12: 3200 | F12: 3200 | G12: 3200 | H12: 3200 | I12: 3200 | J12: 3200 | K12: 3200 | L12: 3200 | M12: 3200 | N12: 3200 | O12: =SUM(E12:N12)
A13: =A12+1 | B13: Amably Cristina Platen | E13: 4850 | F13: 4850 | G13: 4850 | O13: =SUM(E13:N13)
A14: =A13+1 | B14: Angelo De Bortoli Sarto | E14: 1050 | F14: 1050 | G14: 1050 | H14: 1050 | I14: 1050 | J14: 1050 | K14: 1050 | L14: 1050 | O14: =SUM(E14:N14)
A15: =A14+1 | B15: Anita Bohme Behar | E15: 1050 | F15: 1050 | G15: 1050 | H15: 1050 | I15: 1050 | J15: 1050 | K15: 1050 | L15: 1050 | O15: =SUM(E15:N15)
A16: =A15+1 | B16: Catharina Vogel de Carvalho | E16: 1050 | F16: 1050 | G16: 1050 | O16: =SUM(E16:N16)
A17: =A16+1 | B17: Djonathan Willian Schafer | E17: 1050 | F17: 1050 | G17: 1050 | H17: 1050 | I17: 1050 | J17: 1050 | K17: 1050 | L17: 1050 | O17: =SUM(E17:N17)
A18: =A17+1 | B18: Douglas Cheffer | E18: 1050 | F18: 1050 | G18: 1050 | O18: =SUM(E18:N18)
A19: =A18+1 | B19: Felipe Tagliari de Oliveira | E19: 1050 | F19: 1050 | G19: 1050 | H19: 1050 | I19: 1050 | J19: 1050 | K19: 1050 | L19: 1050 | O19: =SUM(E19:N19)
A20: =A19+1 | B20: Gabriel Alves Abade | E20: 3200 | F20: 3200 | G20: 3200 | O20: =SUM(E20:N20)
A21: =A20+1 | B21: Heloisa Silveira Morimoto | E21: 1050 | F21: 1050 | G21: 1050 | O21: =SUM(E21:N21)
A22: =A21+1 | B22: João Pedro Darabas Cardoso | E22: 1050 | F22: 1050 | G22: 1050 | O22: =SUM(E22:N22)
A23: =A22+1 | B23: Luis Fernando Heisler Damazio | E23: 1050 | F23: 1050 | G23: 1050 | H23: 1050 | I23: 1050 | J23: 1050 | O23: =SUM(E23:N23)
A24: =A23+1 | B24: Mariana Souto dos Anjos | E24: 2200 | F24: 2200 | G24: 2200 | H24: 2200 | I24: 2200 | J24: 2200 | K24: 2200 | L24: 2200 | M24: 2200 | N24: 2200 | O24: =SUM(E24:N24)
A25: =A24+1 | B25: Marina Rodrigues Pavanati | E25: 1050 | F25: 1050 | G25: 1050 | H25: 1050 | I25: 1050 | J25: 1050 | K25: 1050 | L25: 1050 | O25: =SUM(E25:N25)
A26: =A25+1 | B26: Roberto Lima Guedes | E26: 3200 | F26: 3200 | G26: 3200 | O26: =SUM(E26:N26)
A27: =A26+1 | B27: Rufino Sérgio Panzo | E27: 1050 | F27: 1050 | G27: 1050 | H27: 1050 | I27: 1050 | J27: 1050 | K27: 1050 | O27: =SUM(E27:N27)
A28: =A27+1 | B28: Sander Alex Pereira | E28: 1050 | F28: 1050 | G28: 1050 | H28: 1050 | I28: 1050 | J28: 1050 | O28: =SUM(E28:N28)
A29: =A28+1 | B29: Simone Alleotti Tesser | E29: 1050 | F29: 1050 | G29: 1050 | H29: 1050 | I29: 1050 | J29: 1050 | K29: 1050 | L29: 1050 | M29: 1050 | N29: 1050 | O29: =SUM(E29:N29)
A30: =A29+1 | B30: Sofia Cunha Dalpiaz | E30: 1050 | F30: 1050 | G30: 1050 | O30: =SUM(E30:N30)
A31: =A30+1 | B31: Serviços de Terceiros | E31: 2500 | F31: 2500 | G31: 2500 | H31: 2500 | I31: 2500 | J31: 2500 | K31: 2500 | L31: 2500 | M31: 2500 | O31: =SUM(E31:N31)
A32: =A31+1 | B32: Passagens | E32: 6500 | F32: 6500 | G32: 6500 | H32: 6500 | I32: 6500 | J32: 6500 | K32: 6500 | L32: 6500 | M32: 6500 | O32: =SUM(E32:N32)
A33: =A32+1 | B33: Diárias | E33: 3500 | F33: 3500 | G33: 3500 | H33: 3500 | I33: 3500 | J33: 3500 | K33: 3500 | L33: 3500 | M33: 3500 | O33: =SUM(E33:N33)
A34: =A33+1 | B34: Materrial de Consumo | E34: 1000 | F34: 1000 | G34: 1000 | H34: 1000 | I34: 1000 | J34: 1000 | K34: 1000 | L34: 1000 | M34: 1000 | N34: 1000 | O34: =SUM(E34:N34)
E35: =SUM(E4:E34) | F35: =SUM(F4:F34) | G35: =SUM(G4:G34) | H35: =SUM(H4:H34) | I35: =SUM(I4:I34) | J35: =SUM(J4:J34) | K35: =SUM(K4:K34) | L35: =SUM(L4:L34) | ... N35: =SUM(N4:N34) | O35: =SUM(E35:N35)
A36: =A34+1 | B36: Fundação de Apoio | D36: 0.0825 | E36: =E2*$D$36 | F36: =F2*$D$36 | G36: =G2*$D$36 | H36: =H2*$D$36 | I36: =I2*$D$36 | J36: =J2*$D$36 | K36: =K2*$D$36 | L36: =L2*$D$36 | ... N36: =N2*$D$36 | O36: =SUM(E36:N36)
A37: =A36+1 | B37: Universidade Federal | D37: 0.07 | E37: =E2*$D$37 | F37: =F2*$D$37 | G37: =G2*$D$37 | H37: =H2*$D$37 | I37: =I2*$D$37 | J37: =J2*$D$37 | K37: =K2*$D$37 | L37: =L2*$D$37 | ... N37: =N2*$D$37 | O37: =SUM(E37:N37)
A38: subtotal2 | E38: =SUM(E36:E37) | F38: =SUM(F36:F37) | G38: =SUM(G36:G37) | H38: =SUM(H36:H37) | I38: =SUM(I36:I37) | J38: =SUM(J36:J37) | K38: =SUM(K36:K37) | L38: =SUM(L36:L37) | ... O38: =SUM(O36:O37)
A39: Total Despesas | E39: =E38+E35 | F39: =F38+F35 | G39: =G38+G35 | H39: =H38+H35 | I39: =I38+I35 | J39: =J38+J35 | K39: =K38+K35 | L39: =L38+L35 | ... O39: =O38+O35
A40: Saldos | D40: =H45 | E40: =D40+E2-E39 | F40: =E40+F2-F39 | G40: =F40+G2-G39 | H40: =G40+H2-H39 | I40: =H40+I2-I39 | J40: =I40+J2-J39 | K40: =J40+K2-K39 | L40: =K40+L2-L39 | ... N40: =M40+N2-N39 | O40: =D40+O2-D2-O39
A42: N˚ | B42: Rubricas | C42: Perc. | D42: Previsto | E42: Recebido | F42: A Receber | G42: Gasto | H42: Saldo | I42: A gastar | J42: Result. | L42: Inicio | M42: 45688
A43: 1 | B43: Aplicação em Fundos | C43: 0 | D43: 0 | E43: 0 | F43: 0 | G43: 0 | H43: 24804.89 | I43: 0 | J43: =H43-I43 | L43: Duração | M43: 24 meses
A44: =A43+1 | B44: Custos do |Projeto | C44: =D44/22661520 | D44: 6124945.3 | E44: 3116712.2 | F44: =D44-E44 | G44: =-1157800-3116712.19-24800 | H44: =E44+G44 | I44: =-O39 | J44: =E44+F44+G44+I44 | L44: Fim | M44: 46418
B45: Totais | C45: =SUM(C44:C44) | D45: =SUM(D43:D44) | E45: =SUM(E43:E44) | F45: =SUM(F43:F44) | G45: =SUM(G43:G44) | H45: =SUM(H43:H44) | I45: =SUM(I43:I44) | J45: =SUM(J43:J44)

Sheet Goias II
A1: N˚ | B1: Receita | D1: Até mai/26 | E1: 46174 | F1: 46204 | G1: 46235 | H1: 46266 | I1: 46296 | J1: 46327 | K1: 46357 | L1: 46388 | M1: 46419 | N1: Totais
A2: 1 | B2: Parcelas | D2: =E28 | E2: 138912 | F2: 744659 | G2: 0 | H2: 183961 | I2: 0 | J2: 557874 | K2: 0 | L2: 373913 | M2: =103900.8+25975.2 | N2: =SUM(D2:M2)
A3: N˚ | B3: Despesas | E3: =E1 | F3: =F1 | G3: =G1 | H3: =H1 | I3: =I1 | J3: =J1 | K3: =K1 | L3: =L1 | M3: =M1 | N3: Totais
A4: 1 | B4: Equipe a Contratar | E4: 3000 | F4: 12000 | G4: =F4 | H4: =G4 | I4: =H4 | J4: =I4 | K4: =J4 | L4: =K4 | M4: =L4 | N4: =SUM(E4:M4)
A5: =A4+1 | B5: Equipe a Contratar | E5: =E4 | F5: =F4 | G5: =G4 | H5: =H4 | I5: =I4 | J5: =J4 | K5: =K4 | L5: =L4 | M5: =M4 | N5: =SUM(E5:M5)
A6: =A5+1 | B6: Equipe a Contratar | E6: =E5 | F6: =F5 | G6: =G5 | H6: =H5 | I6: =I5 | J6: =J5 | K6: =K5 | L6: =L5 | M6: =M5 | N6: =SUM(E6:M6)
A7: =A6+1 | B7: Equipe a Contratar | E7: =E6 | F7: =F6 | G7: =G6 | H7: =H6 | I7: =I6 | J7: =J6 | K7: =K6 | L7: =L6 | M7: =M6 | N7: =SUM(E7:M7)
A8: =A7+1 | B8: Equipe a Contratar | E8: =E7 | F8: =F7 | G8: =G7 | H8: =H7 | I8: =I7 | J8: =J7 | K8: =K7 | L8: =L7 | M8: =M7 | N8: =SUM(E8:M8)
A9: =A8+1 | B9: Equipe a Contratar | E9: =E8 | F9: =F8 | G9: =G8 | H9: =H8 | I9: =I8 | J9: =J8 | K9: =K8 | L9: =L8 | M9: =M8 | N9: =SUM(E9:M9)
A10: =A9+1 | B10: Equipe a Contratar | E10: =E9 | F10: =F9 | G10: =G9 | H10: =H9 | I10: =I9 | J10: =J9 | K10: =K9 | L10: =L9 | M10: =M9 | N10: =SUM(E10:M10)
A11: =A10+1 | B11: Encargos s/pessoal contratado | E11: =SUM(E4:E10)*0.85 | F11: =SUM(F4:F10)*0.85 | G11: =SUM(G4:G10)*0.85 | H11: =SUM(H4:H10)*0.85 | I11: =SUM(I4:I10)*0.85 | J11: =SUM(J4:J10)*0.85 | K11: =SUM(K4:K10)*0.85 | L11: =SUM(L4:L10)*0.85 | M11: =SUM(M4:M10)*0.85 | N11: =SUM(E11:M11)
A12: =A11+1 | B12: Bolsistas | E12: 10000 | F12: 10000 | G12: 10000 | H12: 10000 | I12: 10000 | J12: 10000 | K12: 10000 | L12: 10000 | M12: 10000 | N12: =SUM(E12:M12)
A13: =A12+1 | B13: Bolsistas | E13: 10000 | F13: 10000 | G13: 10000 | H13: 10000 | I13: 10000 | J13: 10000 | K13: 10000 | L13: 10000 | M13: 10000 | N13: =SUM(E13:M13)
A14: =A13+1 | B14: Serviços de Terceiros | E14: 2500 | F14: 2500 | G14: 2500 | H14: 2500 | I14: 2500 | J14: 2500 | K14: 2500 | L14: 2500 | M14: 2500 | N14: =SUM(E14:M14)
A15: =A14+1 | B15: Passagens | E15: 6500 | F15: 6500 | G15: 6500 | H15: 6500 | I15: 6500 | J15: 6500 | K15: 6500 | L15: 6500 | M15: 6500 | N15: =SUM(E15:M15)
A16: =A15+1 | B16: Diárias | E16: 3500 | F16: 3500 | G16: 3500 | H16: 3500 | I16: 3500 | J16: 3500 | K16: 3500 | L16: 3500 | M16: 3500 | N16: =SUM(E16:M16)
A17: =A16+1 | B17: Materrial de Consumo | E17: 1000 | F17: 1000 | G17: 1000 | H17: 1000 | I17: 1000 | J17: 1000 | K17: 1000 | L17: 1000 | M17: 1000 | N17: =SUM(E17:M17)
E18: =SUM(E4:E17) | F18: =SUM(F4:F17) | G18: =SUM(G4:G17) | H18: =SUM(H4:H17) | I18: =SUM(I4:I17) | J18: =SUM(J4:J17) | K18: =SUM(K4:K17) | L18: =SUM(L4:L17) | M18: =SUM(M4:M17) | N18: =SUM(E18:M18)
A19: =A17+1 | B19: Fundação de Apoio | D19: 0.0825 | E19: =E2*$D$19 | F19: =F2*$D$19 | G19: =G2*$D$19 | H19: =H2*$D$19 | I19: =I2*$D$19 | J19: =J2*$D$19 | K19: =K2*$D$19 | L19: =L2*$D$19 | M19: =M2*$D$19 | N19: =SUM(E19:M19)
A20: =A19+1 | B20: Universidade Federal | D20: 0.07 | E20: =E2*$D$20 | F20: =F2*$D$20 | G20: =G2*$D$20 | H20: =H2*$D$20 | I20: =I2*$D$20 | J20: =J2*$D$20 | K20: =K2*$D$20 | L20: =L2*$D$20 | M20: =M2*$D$20 | N20: =SUM(E20:M20)
A21: subtotal2 | E21: =SUM(E19:E20) | F21: =SUM(F19:F20) | G21: =SUM(G19:G20) | H21: =SUM(H19:H20) | I21: =SUM(I19:I20) | J21: =SUM(J19:J20) | K21: =SUM(K19:K20) | L21: =SUM(L19:L20) | ... N21: =SUM(N19:N20)
A22: Total Despesas | E22: =E21+E18 | F22: =F21+F18 | G22: =G21+G18 | H22: =H21+H18 | I22: =I21+I18 | J22: =J21+J18 | K22: =K21+K18 | L22: =L21+L18 | ... N22: =N21+N18
A23: Saldos | D23: =H28 | E23: =D23+E2-E22 | F23: =E23+F2-F22 | G23: =F23+G2-G22 | H23: =G23+H2-H22 | I23: =H23+I2-I22 | J23: =I23+J2-J22 | K23: =J23+K2-K22 | L23: =K23+L2-L22 | M23: =L23+M2-M22 | N23: =D23+N2-D2-N22
A25: N˚ | B25: Rubricas | C25: Perc. | D25: Previsto | E25: Recebido | F25: A Receber | G25: Gasto | H25: Saldo | I25: A gastar | J25: Result. | L25: Inicio | M25: 46135
A26: 1 | B26: Aplicação em Fundos | C26: 0 | D26: 0 | E26: 0 | F26: 0 | G26: 0 | H26: 0 | I26: 0 | J26: =H26-I26 | L26: Duração | M26: 10 meses
A27: =A26+1 | B27: Custos do |Projeto | C27: =D27/22661520 | D27: 2129195 | E27: 0 | F27: =D27-E27 | G27: 0 | H27: =E27+G27 | I27: =-N22 | J27: =E27+F27+G27+I27 | L27: Fim | M27: 46440
B28: Totais | C28: =SUM(C27:C27) | D28: =SUM(D26:D27) | E28: =SUM(E26:E27) | F28: =SUM(F26:F27) | G28: =SUM(G26:G27) | H28: =SUM(H26:H27) | I28: =SUM(I26:I27) | J28: =SUM(J26:J27)

Sheet RUMO
A1: N˚ | B1: Receita | D1: Até mai/26 | E1: 46174 | F1: 46204 | G1: 46235 | H1: 46266 | I1: 46296 | J1: 46327 | K1: 46357 | L1: 46388 | M1: 46419 | N1: 46447 | O1: 46478 | P1: 46508 | Q1: 46539 | R1: 46569 | S1: 46600 | T1: 46631 | U1: 46661 | V1: 46692 | W1: Totais
A2: 1 | B2: Parcelas | D2: =E29 | E2: 176245.81 | F2: 208190.02 | G2: 229943.52 | H2: 218323.89 | I2: 224912.34 | J2: 213292.71 | K2: 230722.16 | L2: 213292.71 | M2: 213292.71 | N2: 224912.34 | O2: 213292.71 | P2: 169438.58 | Q2: 181058.21 | R2: 169438.58 | S2: 171815.44 | T2: 130477.8 | U2: 142097.42 | V2: 0 | W2: =SUM(D2:V2)
A3: N˚ | B3: Despesas | D3: % salário | E3: =E1 | F3: =F1 | G3: =G1 | H3: =H1 | I3: =I1 | J3: =J1 | K3: =K1 | L3: =L1 | ... V3: =V1 | W3: Totais
A4: 1 | B4: Adriane Merten | D4: 1 | E4: =(8297.73+497.86)*$D$4 | F4: =(8297.73+497.86)*$D$4 | G4: =(8297.73+497.86)*$D$4 | H4: =(8297.73+497.86)*$D$4 | I4: =(8297.73+497.86)*$D$4 | J4: =(8297.73+497.86)*$D$4 | K4: =(8297.73+497.86)*$D$4 | L4: =(8297.73+497.86)*$D$4 | M4: =(8297.73+497.86)*$D$4 | N4: =((8297.73+497.86)*$D$4)*1.05 | O4: =((8297.73+497.86)*$D$4)*1.05 | P4: =((8297.73+497.86)*$D$4)*1.05 | Q4: =((8297.73+497.86)*$D$4)*1.05 | R4: =((8297.73+497.86)*$D$4)*1.05 | S4: =((8297.73+497.86)*$D$4)*1.05 | T4: =((8297.73+497.86)*$D$4)*1.05 | U4: =((8297.73+497.86)*$D$4)*1.05 | W4: =SUM(E4:V4)
A5: =A4+1 | B5: André Ricardo Hadlich | D5: 0.5347 | E5: =(16009.77+2881.76)*$D$5 | F5: =(16009.77+2881.76)*$D$5 | G5: =(16009.77+2881.76)*$D$5 | H5: =(16009.77+2881.76)*$D$5 | I5: =(16009.77+2881.76)*$D$5 | J5: =(16009.77+2881.76)*$D$5 | K5: =(16009.77+2881.76)*$D$5 | L5: =(16009.77+2881.76)*$D$5 | M5: =(16009.77+2881.76)*$D$5 | N5: =((16009.77+2881.76)*$D$5)*1.05 | O5: =((16009.77+2881.76)*$D$5)*1.05 | P5: =((16009.77+2881.76)*$D$5)*1.05 | Q5: =((16009.77+2881.76)*$D$5)*1.05 | R5: =((16009.77+2881.76)*$D$5)*1.05 | S5: =((16009.77+2881.76)*$D$5)*1.05 | T5: =((16009.77+2881.76)*$D$5)*1.05 | U5: =((16009.77+2881.76)*$D$5)*1.05 | W5: =SUM(E5:V5)
A6: =A5+1 | B6: Bruno Maluche Neto | D6: 0.2574 | E6: =(19765.28+4743.67)*$D$6 | F6: =(19765.28+4743.67)*$D$6 | G6: =(19765.28+4743.67)*$D$6 | H6: =(19765.28+4743.67)*$D$6 | I6: =(19765.28+4743.67)*$D$6 | J6: =(19765.28+4743.67)*$D$6 | K6: =(19765.28+4743.67)*$D$6 | L6: =(19765.28+4743.67)*$D$6 | M6: =(19765.28+4743.67)*$D$6 | N6: =((19765.28+4743.67)*$D$6)*1.05 | O6: =((19765.28+4743.67)*$D$6)*1.05 | P6: =((19765.28+4743.67)*$D$6)*1.05 | Q6: =((19765.28+4743.67)*$D$6)*1.05 | R6: =((19765.28+4743.67)*$D$6)*1.05 | S6: =((19765.28+4743.67)*$D$6)*1.05 | T6: =((19765.28+4743.67)*$D$6)*1.05 | U6: =((19765.28+4743.67)*$D$6)*1.05 | W6: =SUM(E6:V6)
A7: =A6+1 | B7: Daniela Vogel | D7: 0.4584 | E7: =(8390.54+1510.3)*$D$7 | F7: =(8390.54+1510.3)*$D$7 | G7: =(8390.54+1510.3)*$D$7 | H7: =(8390.54+1510.3)*$D$7 | I7: =(8390.54+1510.3)*$D$7 | J7: =(8390.54+1510.3)*$D$7 | K7: =(8390.54+1510.3)*$D$7 | L7: =(8390.54+1510.3)*$D$7 | M7: =(8390.54+1510.3)*$D$7 | N7: =((8390.54+1510.3)*$D$7)*1.05 | O7: =((8390.54+1510.3)*$D$7)*1.05 | P7: =((8390.54+1510.3)*$D$7)*1.05 | Q7: =((8390.54+1510.3)*$D$7)*1.05 | R7: =((8390.54+1510.3)*$D$7)*1.05 | S7: =((8390.54+1510.3)*$D$7)*1.05 | T7: =((8390.54+1510.3)*$D$7)*1.05 | U7: =((8390.54+1510.3)*$D$7)*1.05 | W7: =SUM(E7:V7)
A8: =A7+1 | B8: Gabriel Lisboa Bordin | D8: 1 | E8: =5610*$D$8 | F8: =5610*$D$8 | G8: =5610*$D$8 | H8: =5610*$D$8 | I8: =5610*$D$8 | J8: =5610*$D$8 | K8: =5610*$D$8 | L8: =5610*$D$8 | M8: =5610*$D$8 | N8: =(5610*$D$8)*1.05 | O8: =(5610*$D$8)*1.05 | P8: =(5610*$D$8)*1.05 | Q8: =(5610*$D$8)*1.05 | R8: =(5610*$D$8)*1.05 | S8: =(5610*$D$8)*1.05 | T8: =(5610*$D$8)*1.05 | U8: =(5610*$D$8)*1.05 | W8: =SUM(E8:V8)
A9: =A8+1 | B9: Marcelo Maciel Pereira | D9: 0.7862 | E9: =(11583.15+2779.96)*$D$9 | F9: =(11583.15+2779.96)*$D$9 | G9: =(11583.15+2779.96)*$D$9 | H9: =(11583.15+2779.96)*$D$9 | I9: =(11583.15+2779.96)*$D$9 | J9: =(11583.15+2779.96)*$D$9 | K9: =(11583.15+2779.96)*$D$9 | L9: =(11583.15+2779.96)*$D$9 | M9: =(11583.15+2779.96)*$D$9 | N9: =((11583.15+2779.96)*$D$9)*1.05 | O9: =((11583.15+2779.96)*$D$9)*1.05 | P9: =((11583.15+2779.96)*$D$9)*1.05 | Q9: =((11583.15+2779.96)*$D$9)*1.05 | R9: =((11583.15+2779.96)*$D$9)*1.05 | S9: =((11583.15+2779.96)*$D$9)*1.05 | T9: =((11583.15+2779.96)*$D$9)*1.05 | U9: =((11583.15+2779.96)*$D$9)*1.05 | W9: =SUM(E9:V9)
A10: =A9+1 | B10: Thaísa Momm Bastos | D10: 0.8144 | E10: =(6794.33+407.66)*$D$10 | F10: =(6794.33+407.66)*$D$10 | G10: =(6794.33+407.66)*$D$10 | H10: =(6794.33+407.66)*$D$10 | I10: =(6794.33+407.66)*$D$10 | J10: =(6794.33+407.66)*$D$10 | K10: =(6794.33+407.66)*$D$10 | L10: =(6794.33+407.66)*$D$10 | M10: =(6794.33+407.66)*$D$10 | N10: =((6794.33+407.66)*$D$10)*1.05 | O10: =((6794.33+407.66)*$D$10)*1.05 | P10: =((6794.33+407.66)*$D$10)*1.05 | Q10: =((6794.33+407.66)*$D$10)*1.05 | R10: =((6794.33+407.66)*$D$10)*1.05 | S10: =((6794.33+407.66)*$D$10)*1.05 | T10: =((6794.33+407.66)*$D$10)*1.05 | U10: =((6794.33+407.66)*$D$10)*1.05 | W10: =SUM(E10:V10)
A11: =A10+1 | B11: Encargos s/pessoal contratado | E11: =SUM(E4:E10)*0.85 | F11: =SUM(F4:F10)*0.85 | G11: =SUM(G4:G10)*0.85 | H11: =SUM(H4:H10)*0.85 | I11: =SUM(I4:I10)*0.85 | J11: =SUM(J4:J10)*0.85 | K11: =SUM(K4:K10)*0.85 | L11: =SUM(L4:L10)*0.85 | ... V11: =SUM(V4:V10)*0.85 | W11: =SUM(E11:V11)
A12: =A11+1 | B12: Arthur Rosa dos Santos | E12: 1050 | F12: 1050 | G12: 1050 | H12: 1050 | W12: =SUM(E12:V12)
A13: =A12+1 | B13: Helena Schiemann Maia | E13: 1050 | F13: 1050 | W13: =SUM(E13:V13)
A14: =A13+1 | B14: Henrique Rafael Sousa de Oliveira | E14: 1050 | F14: 1050 | G14: 1050 | H14: 1050 | W14: =SUM(E14:V14)
A15: =A14+1 | B15: Serviços de Terceiros | E15: 3500 | F15: 3500 | G15: 3500 | H15: 3500 | I15: 3500 | J15: 3500 | K15: 3500 | L15: 3500 | M15: 3500 | N15: 3500 | O15: 3500 | P15: 3500 | Q15: 3500 | R15: 3500 | S15: 3500 | T15: 3500 | U15: 3500 | W15: =SUM(E15:V15)
A16: =A15+1 | B16: Passagens | E16: 4000 | F16: 4000 | G16: 4000 | H16: 4000 | I16: 4000 | J16: 4000 | K16: 4000 | L16: 4000 | M16: 4000 | N16: 4000 | O16: 4000 | P16: 4000 | Q16: 4000 | R16: 4000 | S16: 4000 | T16: 4000 | U16: 4000 | W16: =SUM(E16:V16)
A17: =A16+1 | B17: Diárias | E17: =15300/18 | F17: =15300/18 | G17: =15300/18 | H17: =15300/18 | I17: =15300/18 | J17: =15300/18 | K17: =15300/18 | L17: =15300/18 | ... U17: =15300/18 | W17: =SUM(E17:V17)
A18: =A17+1 | B18: Materrial de Consumo | E18: =41400/18 | F18: =41400/18 | G18: =41400/18 | H18: =41400/18 | I18: =41400/18 | J18: =41400/18 | K18: =41400/18 | L18: =41400/18 | ... U18: =41400/18 | W18: =SUM(E18:V18)
E19: =SUM(E4:E18) | F19: =SUM(F4:F18) | G19: =SUM(G4:G18) | H19: =SUM(H4:H18) | I19: =SUM(I4:I18) | J19: =SUM(J4:J18) | K19: =SUM(K4:K18) | L19: =SUM(L4:L18) | ... W19: =SUM(W4:W18)
A20: =A18+1 | B20: Fundação de Apoio | D20: 0.081726355 | E20: =E2*$D$20 | F20: =F2*$D$20 | G20: =G2*$D$20 | H20: =H2*$D$20 | I20: =I2*$D$20 | J20: =J2*$D$20 | K20: =K2*$D$20 | L20: =L2*$D$20 | ... V20: =V2*$D$20 | W20: =SUM(E20:V20)
A21: =A20+1 | B21: Universidade Federal | D21: 0.083479422 | E21: =E2*$D$21 | F21: =F2*$D$21 | G21: =G2*$D$21 | H21: =H2*$D$21 | I21: =I2*$D$21 | J21: =J2*$D$21 | K21: =K2*$D$21 | L21: =L2*$D$21 | ... V21: =V2*$D$21 | W21: =SUM(E21:V21)
A22: subtotal2 | E22: =SUM(E20:E21) | F22: =SUM(F20:F21) | G22: =SUM(G20:G21) | H22: =SUM(H20:H21) | I22: =SUM(I20:I21) | J22: =SUM(J20:J21) | K22: =SUM(K20:K21) | L22: =SUM(L20:L21) | ... W22: =SUM(W20:W21)
A23: Total Despesas | E23: =E22+E19 | F23: =F22+F19 | G23: =G22+G19 | H23: =H22+H19 | I23: =I22+I19 | J23: =J22+J19 | K23: =K22+K19 | L23: =L22+L19 | ... V23: =V22+V19 | W23: =SUM(E23:V23)
A24: Saldos | D24: =H29 | E24: =D24+E2-E23 | F24: =E24+F2-F23 | G24: =F24+G2-G23 | H24: =G24+H2-H23 | I24: =H24+I2-I23 | J24: =I24+J2-J23 | K24: =J24+K2-K23 | L24: =K24+L2-L23 | ... V24: =U24+V2-V23 | W24: =D24+W2-D2-W23
A26: N˚ | B26: Rubricas | C26: Perc. | D26: Previsto | E26: Recebido | F26: A Receber | G26: Gasto | H26: Saldo | I26: A gastar | J26: Result. | L26: Inicio | M26: 46148
A27: 1 | B27: Aplicação em Fundos | C27: 0 | D27: 0 | E27: 0 | F27: 0 | G27: 0 | H27: 0 | I27: 0 | J27: =H27-I27 | L27: Duração | M27: 18 meses
A28: =A27+1 | B28: Custos do |Projeto | C28: =D28/22661520 | D28: 3484532.1 | E28: 153785.19 | F28: =D28-E28 | G28: =48676.54-153785 | H28: =E28+G28 | I28: =-W23 | J28: =E28+F28+G28+I28 | L28: Fim | M28: 46697
B29: Totais | C29: =SUM(C28:C28) | D29: =SUM(D27:D28) | E29: =SUM(E27:E28) | F29: =SUM(F27:F28) | G29: =SUM(G27:G28) | H29: =SUM(H27:H28) | I29: =SUM(I27:I28) | J29: =SUM(J27:J28)
D31: =D28*7%

Sheet Goiás
A1: N˚ | B1: Receita | C1: Até mai/26 | D1: 46174 | E1: 46204 | F1: 46235 | G1: Totais
A2: 1 | B2: Parcelas | C2: =E36 | D2: 386470 | E2: 0 | F2: 177017 | G2: =SUM(C2:F2)
A3: N˚ | B3: Despesas | D3: =D1 | E3: =E1 | F3: =F1 | G3: Totais
A4: 1 | B4: Lucas Zomignani Oliveira | D4: 8196.43 | E4: 8196.43 | F4: 8196.43 | G4: =SUM(D4:F4)
A5: =A4+1 | B5: Encargos Trabalhistas | D5: =SUM(D4:D4)*0.85 | E5: =SUM(E4:E4)*0.85 | F5: =SUM(F4:F4)*0.85 | G5: =SUM(D5:F5)
A6: =A5+1 | B6: Fernando de Melo e Silva | D6: =77285.88/6 | E6: =77285.88/6 | G6: =SUM(D6:F6)
A7: =A6+1 | B7: Flavia Nascimento Pureza Mello | D7: 9000 | G7: =SUM(D7:F7)
A8: =A7+1 | B8: Encargos s/RPA - 20% | D8: =SUM(D6:D7)*0.2 | E8: =SUM(E6:E7)*0.2 | F8: =SUM(F6:F7)*0.2 | G8: =SUM(D8:F8)
A9: =A8+1 | B9: Danton Henrique Santos D'Almeida | D9: 3200 | E9: 3200 | F9: 3200 | G9: =SUM(D9:F9)
A10: =A9+1 | B10: Gabriel Martins Folador | D10: 1050 | E10: 1050 | F10: 1050 | G10: =SUM(D10:F10)
A11: =A10+1 | B11: Kamilly Alana Vendramini | D11: 1050 | E11: 1050 | F11: 1050 | G11: =SUM(D11:F11)
A12: =A11+1 | B12: Natalia Sagaz | D12: 2200 | E12: 2200 | F12: 2200 | G12: =SUM(D12:F12)
A13: =A12+1 | B13: Nathalia Julia Moura | D13: 1050 | E13: 1050 | F13: 1050 | G13: =SUM(D13:F13)
A14: =A13+1 | B14: Rian Fabiano Venezio | D14: 2200 | E14: 2200 | F14: 2200 | G14: =SUM(D14:F14)
A15: =A14+1 | B15: Serviços de Terceiros | D15: 3000 | E15: 3000 | F15: 3000 | G15: =SUM(D15:F15)
A16: =A15+1 | B16: Passagens e Locomoções | D16: 5000 | E16: 5000 | F16: 5000 | G16: =SUM(D16:F16)
A17: =A16+1 | B17: Diárias | D17: 2500 | E17: 2500 | F17: 2500 | G17: =SUM(D17:F17)
A18: =A17+1 | B18: Material de Consumo | D18: 3500 | E18: 3500 | F18: 3500 | G18: =SUM(D18:F18)
A19: subtotal | D19: =SUM(D4:D18) | E19: =SUM(E4:E18) | F19: =SUM(F4:F18) | G19: =SUM(G4:G18)
A20: =A18+1 | B20: FAPEU | C20: 0.1 | D20: =D2*$C$20 | E20: =E2*$C$20 | F20: =F2*$C$20 | G20: =SUM(D20:F20)
A21: =A20+1 | B21: UFSC | C21: 0.07 | D21: =D2*$C$21 | E21: =E2*$C$21 | F21: =F2*$C$21 | G21: =SUM(D21:F21)
A22: subtotal | D22: =SUM(D20:D21) | E22: =SUM(E20:E21) | F22: =SUM(F20:F21) | G22: =SUM(G20:G21)
A23: Total Despesas | D23: =D22+D19 | E23: =E22+E19 | F23: =F22+F19 | G23: =G22+G19
A24: Saldos | C24: =H36 | D24: =C24+D2-D23 | E24: =D24+E2-E23 | F24: =E24+F2-F23 | G24: =G2+C24-C2-G23
A26: N˚ | B26: Rubricas | C26: Perc. | D26: Previsto | E26: Recebido | F26: A Receber | G26: Gasto | H26: Saldo | I26: A gastar | J26: Result. | L26: Inicio | M26: 45863
A27: 1 | B27: Aplicação em Fundos | C27: 0 | D27: 0 | E27: 0 | F27: 0 | G27: 0 | H27: 9645 | I27: 0 | J27: =H27-I27 | L27: término | M27: 46167
A28: =A27+1 | B28: Equipe Técnica | C28: =D28/2553140 | D28: 1357928.3 | E28: =1989653*C28 | F28: =D28-E28 | G28: 0 | H28: =E28+G28 | I28: =-SUM(G4:G14) | J28: =E28+F28+G28+I28 | L28: Execução | M28: 10 meses
A29: =A28+1 | B29: Passagens / Locomoção | C29: =D29/2553140 | D29: 44800 | E29: =1989653*C29 | F29: =D29-E29 | G29: 0 | H29: =E29+G29 | I29: =-G16 | J29: =E29+F29+G29+I29
A30: =A29+1 | B30: Diárias | C30: =D30/2553140 | D30: 21377.92 | E30: =1989653*C30 | F30: =D30-E30 | G30: 0 | H30: =E30+G30 | I30: =-G17 | J30: =E30+F30+G30+I30
A31: =A30+1 | B31: Serviços de Terceiros | C31: =D31/2553140 | D31: 570000 | E31: =1989653*C31 | F31: =D31-E31 | G31: 0 | H31: =E31+G31 | I31: =-G15 | J31: =E31+F31+G31+I31
A32: =A31+1 | B32: Material de Consumo | C32: =D32/2553140 | D32: 35000 | E32: =1989653*C32 | F32: =D32-E32 | G32: 0 | H32: =E32+G32 | I32: =-G18 | J32: =E32+F32+G32+I32
A33: =A32+1 | B33: Equipamentos | C33: =D33/2553140 | D33: 90000 | E33: =1989653*C33 | F33: =D33-E33 | G33: 0 | H33: =E33+G33 | I33: 0 | J33: =E33+F33+G33+I33
A34: =A33+1 | B34: UFSC | C34: =D34/2553140 | D34: 178719.8 | E34: =1989653*C34 | F34: =D34-E34 | G34: 0 | H34: =E34+G34 | I34: =-G21 | J34: =E34+F34+G34+I34
A35: =A34+1 | B35: Fundação | C35: =D35/2553140 | D35: 255314 | E35: =1989653*C35 | F35: =D35-E35 | G35: -1464282.9 | H35: =E35+G35 | I35: =-G20 | J35: =E35+F35+G35+I35
B36: Totais | C36: =SUM(C27:C35) | D36: =SUM(D27:D35) | E36: =SUM(E27:E35) | F36: =SUM(F27:F35) | G36: =SUM(G27:G35) | H36: =SUM(H27:H35) | I36: =SUM(I27:I35) | J36: =SUM(J27:J35)
J38: 240770
J39: =J38-J36

Sheet SAC BIM
A1: N˚ | B1: Receita | D1: Até mai/26 | E1: 46174 | F1: 46204 | G1: 46235 | H1: 46266 | I1: 46296 | J1: 46327 | K1: 46357 | L1: 46388 | M1: 46419 | N1: 46447 | O1: 46478 | P1: 46508 | Q1: 46539 | R1: 46569 | S1: 46600 | T1: 46631 | U1: 46661 | V1: 46692 | W1: 46722 | X1: 46753 | Y1: 46784 | Z1: 46813 | AA1: 46844 | AB1: 46874 | AC1: 46905 | AD1: 46935 | AE1: 46966 | AF1: 46997 | AG1: 47027 | AH1: 47058 | AI1: 47088 | AJ1: 47119 | AK1: 47150 | AL1: 47178 | AM1: 47209 | AN1: 47239 | AO1: 47270 | AP1: 47300 | AQ1: 47331 | AR1: 47362 | AS1: 47392 | AT1: 47423 | AU1: 47453 | AV1: 47484 | AW1: 47515 | AX1: 47543 | AY1: 47574 | AZ1: 47604 | BA1: 47635 | BB1: 47665 | BC1: 47696 | BD1: 47727 | BE1: 47757 | BF1: 47788 | BG1: 47818 | BH1: Totais
A2: 1 | B2: Parcelas | D2: =E136 | E2: 0 | F2: 0 | G2: 0 | H2: 0 | I2: 0 | J2: 4050411 | K2: 0 | L2: 0 | M2: 0 | N2: 3654500 | O2: 0 | P2: 0 | Q2: 0 | R2: 3525320 | S2: 0 | T2: 0 | U2: 0 | V2: 3482260 | W2: 0 | X2: 0 | Y2: 0 | Z2: 3482260 | AA2: 0 | AB2: 0 | AC2: 0 | AD2: 3482260 | AE2: 0 | AF2: 0 | AG2: 0 | AH2: 3482260 | AI2: 0 | AJ2: 0 | AK2: 0 | AL2: 3482260 | AM2: 0 | AN2: 0 | AO2: 0 | AP2: 3482260 | AQ2: 0 | AR2: 0 | AS2: 0 | AT2: 2555948 | AU2: 0 | AV2: 0 | AW2: 0 | AX2: 2555948 | AY2: 0 | AZ2: 0 | BA2: 0 | BB2: 3534567 | BC2: 0 | BD2: 0 | BE2: 0 | BF2: 0 | BG2: 0 | BH2: =SUM(D2:BG2)
A3: N˚ | B3: Despesas | E3: =E1 | F3: =F1 | G3: =G1 | H3: =H1 | I3: =I1 | J3: =J1 | K3: =K1 | L3: =L1 | ... BG3: =BG1 | BH3: Totais
A4: 1 | B4: Alana Vargas Magalhães | E4: 11709.19 | F4: 11709.19 | G4: 11709.19 | H4: 11709.19 | I4: 11709.19 | J4: 11709.19 | K4: 11709.19 | L4: 11709.19 | M4: 11709.19 | N4: =M4*1.05 | O4: =N4 | P4: =O4 | Q4: =P4 | R4: =Q4 | S4: =R4 | T4: =S4 | U4: =T4 | V4: =U4 | ... Y4: =X4 | Z4: =Y4*1.05 | AA4: =Z4 | AB4: =AA4 | AC4: =AB4 | AD4: =AC4 | AE4: =AD4 | AF4: =AE4 | AG4: =AF4 | AH4: =AG4 | ... AK4: =AJ4 | AL4: =AK4*1.05 | AM4: =AL4 | AN4: =AM4 | AO4: =AN4 | AP4: =AO4 | AQ4: =AP4 | AR4: =AQ4 | AS4: =AR4 | AT4: =AS4 | ... AW4: =AV4 | BH4: =SUM(E4:BG4)
A5: =A4+1 | B5: Amanda Costa da Silva | E5: 4174.4 | F5: 4174.4 | G5: 4174.4 | H5: 4174.4 | I5: 4174.4 | J5: 4174.4 | K5: 4174.4 | L5: 4174.4 | M5: 4174.4 | N5: =M5*1.05 | O5: =N5 | P5: =O5 | Q5: =P5 | R5: =Q5 | S5: =R5 | T5: =S5 | U5: =T5 | V5: =U5 | ... Y5: =X5 | Z5: =Y5*1.05 | AA5: =Z5 | AB5: =AA5 | AC5: =AB5 | AD5: =AC5 | AE5: =AD5 | AF5: =AE5 | AG5: =AF5 | AH5: =AG5 | ... AK5: =AJ5 | AL5: =AK5*1.05 | AM5: =AL5 | AN5: =AM5 | AO5: =AN5 | AP5: =AO5 | AQ5: =AP5 | AR5: =AQ5 | AS5: =AR5 | AT5: =AS5 | ... AW5: =AV5 | BH5: =SUM(E5:BG5)
A6: =A5+1 | B6: Ana Carolina Riquerti Orsi | E6: 6067.48 | F6: 6067.48 | G6: 6067.48 | H6: 6067.48 | I6: 6067.48 | J6: 6067.48 | K6: 6067.48 | L6: 6067.48 | M6: 6067.48 | N6: =M6*1.05 | O6: =N6 | P6: =O6 | Q6: =P6 | R6: =Q6 | S6: =R6 | T6: =S6 | U6: =T6 | V6: =U6 | ... Y6: =X6 | Z6: =Y6*1.05 | AA6: =Z6 | AB6: =AA6 | AC6: =AB6 | AD6: =AC6 | AE6: =AD6 | AF6: =AE6 | AG6: =AF6 | AH6: =AG6 | ... AK6: =AJ6 | AL6: =AK6*1.05 | AM6: =AL6 | AN6: =AM6 | AO6: =AN6 | AP6: =AO6 | AQ6: =AP6 | AR6: =AQ6 | AS6: =AR6 | AT6: =AS6 | ... AW6: =AV6 | BH6: =SUM(E6:BG6)
A7: =A6+1 | B7: Ana Luiza Shimomura Spinelli | E7: 13208 | F7: 13208 | G7: 13208 | H7: 13208 | I7: 13208 | J7: 13208 | K7: 13208 | L7: 13208 | M7: 13208 | N7: =M7*1.05 | O7: =N7 | P7: =O7 | Q7: =P7 | R7: =Q7 | S7: =R7 | T7: =S7 | U7: =T7 | V7: =U7 | ... Y7: =X7 | Z7: =Y7*1.05 | AA7: =Z7 | AB7: =AA7 | AC7: =AB7 | AD7: =AC7 | AE7: =AD7 | AF7: =AE7 | AG7: =AF7 | AH7: =AG7 | ... AK7: =AJ7 | BH7: =SUM(E7:BG7)
A8: =A7+1 | B8: André Castellani Lopes | E8: 6165 | F8: 6165 | G8: 6165 | H8: 6165 | I8: 6165 | J8: 6165 | K8: 6165 | L8: 6165 | M8: 6165 | N8: =M8*1.05 | O8: =N8 | P8: =O8 | Q8: =P8 | R8: =Q8 | S8: =R8 | T8: =S8 | U8: =T8 | V8: =U8 | ... Y8: =X8 | Z8: =Y8*1.05 | AA8: =Z8 | AB8: =AA8 | AC8: =AB8 | AD8: =AC8 | AE8: =AD8 | AF8: =AE8 | AG8: =AF8 | AH8: =AG8 | ... AK8: =AJ8 | AL8: =AK8*1.05 | AM8: =AL8 | AN8: =AM8 | AO8: =AN8 | AP8: =AO8 | AQ8: =AP8 | AR8: =AQ8 | AS8: =AR8 | AT8: =AS8 | ... AW8: =AV8 | BH8: =SUM(E8:BG8)
A9: =A8+1 | B9: André Ricardo Hadlich | E9: =(16009.77+2881.76)*0.4653 | F9: =(16009.77+2881.76)*0.4653 | G9: =(16009.77+2881.76)*0.4653 | H9: =(16009.77+2881.76)*0.4653 | I9: =(16009.77+2881.76)*0.4653 | J9: =(16009.77+2881.76)*0.4653 | K9: =(16009.77+2881.76)*0.4653 | L9: =(16009.77+2881.76)*0.4653 | M9: =(16009.77+2881.76)*0.4653 | BH9: =SUM(E9:BG9)
A10: =A9+1 | B10: Antonio Venicius dos Santos | E10: =14980+1797.6 | F10: =14980+1797.6 | G10: =14980+1797.6 | H10: =14980+1797.6 | I10: =14980+1797.6 | J10: =14980+1797.6 | K10: =14980+1797.6 | L10: =14980+1797.6 | M10: =14980+1797.6 | BH10: =SUM(E10:BG10)
A11: =A10+1 | B11: Arthur de Matos Castro e Silva | E11: 5739.8 | F11: 5739.8 | G11: 5739.8 | H11: 5739.8 | I11: 5739.8 | J11: 5739.8 | K11: 5739.8 | L11: 5739.8 | M11: 5739.8 | N11: =M11*1.05 | O11: =N11 | P11: =O11 | Q11: =P11 | R11: =Q11 | S11: =R11 | T11: =S11 | U11: =T11 | V11: =U11 | ... Y11: =X11 | Z11: =Y11*1.05 | AA11: =Z11 | AB11: =AA11 | AC11: =AB11 | AD11: =AC11 | AE11: =AD11 | AF11: =AE11 | AG11: =AF11 | AH11: =AG11 | ... AK11: =AJ11 | AL11: =AK11*1.05 | AM11: =AL11 | AN11: =AM11 | AO11: =AN11 | AP11: =AO11 | AQ11: =AP11 | AR11: =AQ11 | AS11: =AR11 | AT11: =AS11 | ... AW11: =AV11 | BH11: =SUM(E11:BG11)
A12: =A11+1 | B12: Assis Arantes Junior | E12: =19102.95+1146.18 | F12: =19102.95+1146.18 | G12: =19102.95+1146.18 | H12: =19102.95+1146.18 | I12: =19102.95+1146.18 | J12: =19102.95+1146.18 | K12: =19102.95+1146.18 | L12: =19102.95+1146.18 | M12: =19102.95+1146.18 | N12: =M12*1.05 | O12: =N12 | P12: =O12 | Q12: =P12 | R12: =Q12 | S12: =R12 | T12: =S12 | U12: =T12 | V12: =U12 | ... Y12: =X12 | Z12: =Y12*1.05 | AA12: =Z12 | AB12: =AA12 | AC12: =AB12 | AD12: =AC12 | AE12: =AD12 | AF12: =AE12 | AG12: =AF12 | AH12: =AG12 | ... AK12: =AJ12 | BH12: =SUM(E12:BG12)
A13: =A12+1 | B13: Augusto Simioni de Lima | E13: 11709.19 | F13: 11709.19 | G13: 11709.19 | H13: 11709.19 | I13: 11709.19 | J13: 11709.19 | K13: 11709.19 | L13: 11709.19 | M13: 11709.19 | N13: =M13*1.05 | O13: =N13 | P13: =O13 | Q13: =P13 | R13: =Q13 | S13: =R13 | T13: =S13 | U13: =T13 | V13: =U13 | ... Y13: =X13 | Z13: =Y13*1.05 | AA13: =Z13 | AB13: =AA13 | AC13: =AB13 | AD13: =AC13 | AE13: =AD13 | AF13: =AE13 | AG13: =AF13 | AH13: =AG13 | ... AK13: =AJ13 | AL13: =AK13*1.05 | AM13: =AL13 | AN13: =AM13 | AO13: =AN13 | AP13: =AO13 | AQ13: =AP13 | AR13: =AQ13 | AS13: =AR13 | AT13: =AS13 | ... AW13: =AV13 | BH13: =SUM(E13:BG13)
A14: =A13+1 | B14: Bianca de Cordova Caetani | E14: 12279.43 | F14: 12279.43 | G14: 12279.43 | H14: 12279.43 | I14: 12279.43 | J14: 12279.43 | K14: 12279.43 | L14: 12279.43 | M14: 12279.43 | N14: =M14*1.05 | O14: =N14 | P14: =O14 | Q14: =P14 | R14: =Q14 | S14: =R14 | T14: =S14 | U14: =T14 | V14: =U14 | ... Y14: =X14 | Z14: =Y14*1.05 | AA14: =Z14 | AB14: =AA14 | AC14: =AB14 | AD14: =AC14 | AE14: =AD14 | AF14: =AE14 | AG14: =AF14 | AH14: =AG14 | ... AK14: =AJ14 | BH14: =SUM(E14:BG14)
A15: =A14+1 | B15: Bruno Duarte | E15: 7827 | F15: 7827 | G15: 7827 | H15: 7827 | I15: 7827 | J15: 7827 | K15: 7827 | L15: 7827 | M15: 7827 | N15: =M15*1.05 | O15: =N15 | P15: =O15 | Q15: =P15 | R15: =Q15 | S15: =R15 | T15: =S15 | U15: =T15 | V15: =U15 | ... Y15: =X15 | Z15: =Y15*1.05 | AA15: =Z15 | AB15: =AA15 | AC15: =AB15 | AD15: =AC15 | AE15: =AD15 | AF15: =AE15 | AG15: =AF15 | AH15: =AG15 | ... AK15: =AJ15 | AL15: =AK15*1.05 | AM15: =AL15 | AN15: =AM15 | AO15: =AN15 | AP15: =AO15 | AQ15: =AP15 | AR15: =AQ15 | AS15: =AR15 | AT15: =AS15 | ... AW15: =AV15 | BH15: =SUM(E15:BG15)
A16: =A15+1 | B16: Dorival Faria Quadros | E16: =20192.54+1817.33 | F16: =20192.54+1817.33 | G16: =20192.54+1817.33 | H16: =20192.54+1817.33 | I16: =20192.54+1817.33 | J16: =20192.54+1817.33 | K16: =20192.54+1817.33 | L16: =20192.54+1817.33 | M16: =20192.54+1817.33 | N16: =M16*1.05 | O16: =N16 | P16: =O16 | Q16: =P16 | R16: =Q16 | S16: =R16 | T16: =S16 | U16: =T16 | V16: =U16 | ... Y16: =X16 | Z16: =Y16*1.05 | AA16: =Z16 | AB16: =AA16 | AC16: =AB16 | AD16: =AC16 | AE16: =AD16 | AF16: =AE16 | AG16: =AF16 | AH16: =AG16 | ... AK16: =AJ16 | BH16: =SUM(E16:BG16)
A17: =A16+1 | B17: Edileuza Jose de Souza | E17: =2071.02+124.26 | F17: =2071.02+124.26 | G17: =2071.02+124.26 | H17: =2071.02+124.26 | I17: =2071.02+124.26 | J17: =2071.02+124.26 | K17: =2071.02+124.26 | L17: =2071.02+124.26 | M17: =2071.02+124.26 | N17: =M17*1.05 | O17: =N17 | P17: =O17 | Q17: =P17 | R17: =Q17 | S17: =R17 | T17: =S17 | U17: =T17 | V17: =U17 | ... Y17: =X17 | Z17: =Y17*1.05 | AA17: =Z17 | AB17: =AA17 | AC17: =AB17 | AD17: =AC17 | AE17: =AD17 | AF17: =AE17 | AG17: =AF17 | AH17: =AG17 | ... AK17: =AJ17 | AL17: =AK17*1.05 | AM17: =AL17 | AN17: =AM17 | AO17: =AN17 | AP17: =AO17 | AQ17: =AP17 | AR17: =AQ17 | AS17: =AR17 | AT17: =AS17 | ... AW17: =AV17 | BH17: =SUM(E17:BG17)
A18: =A17+1 | B18: Eduardo Francisco Fernandes | E18: =13248.91+1589.87 | F18: =13248.91+1589.87 | G18: =13248.91+1589.87 | H18: =13248.91+1589.87 | I18: =13248.91+1589.87 | J18: =13248.91+1589.87 | K18: =13248.91+1589.87 | L18: =13248.91+1589.87 | M18: =13248.91+1589.87 | BH18: =SUM(E18:BG18)
A19: =A18+1 | B19: Fabiano Giacobo | E19: =36908.46+4429.02 | F19: =36908.46+4429.02 | G19: =36908.46+4429.02 | H19: =36908.46+4429.02 | I19: =36908.46+4429.02 | J19: =36908.46+4429.02 | K19: =36908.46+4429.02 | L19: =36908.46+4429.02 | M19: =36908.46+4429.02 | BH19: =SUM(E19:BG19)
A20: =A19+1 | B20: Fernando Borges Weimer | E20: 11709.19 | F20: 11709.19 | G20: 11709.19 | H20: 11709.19 | I20: 11709.19 | J20: 11709.19 | K20: 11709.19 | L20: 11709.19 | M20: 11709.19 | BH20: =SUM(E20:BG20)
A21: =A20+1 | B21: Gabriel Gutjhar Stolf | E21: 6412 | F21: 6412 | G21: 6412 | H21: 6412 | I21: 6412 | J21: 6412 | K21: 6412 | L21: 6412 | M21: 6412 | N21: =M21*1.05 | O21: =N21 | P21: =O21 | Q21: =P21 | R21: =Q21 | S21: =R21 | T21: =S21 | U21: =T21 | V21: =U21 | ... Y21: =X21 | Z21: =Y21*1.05 | AA21: =Z21 | AB21: =AA21 | AC21: =AB21 | AD21: =AC21 | AE21: =AD21 | AF21: =AE21 | AG21: =AF21 | AH21: =AG21 | ... AK21: =AJ21 | AL21: =AK21*1.05 | AM21: =AL21 | AN21: =AM21 | AO21: =AN21 | AP21: =AO21 | AQ21: =AP21 | AR21: =AQ21 | AS21: =AR21 | AT21: =AS21 | ... AW21: =AV21 | BH21: =SUM(E21:BG21)
A22: =A21+1 | B22: Jean Lucas Giuliani Oliveira | E22: 13133.08 | F22: 13133.08 | G22: 13133.08 | H22: 13133.08 | I22: 13133.08 | J22: 13133.08 | K22: 13133.08 | L22: 13133.08 | M22: 13133.08 | N22: =M22*1.05 | O22: =N22 | P22: =O22 | Q22: =P22 | R22: =Q22 | S22: =R22 | T22: =S22 | U22: =T22 | V22: =U22 | ... Y22: =X22 | Z22: =Y22*1.05 | AA22: =Z22 | AB22: =AA22 | AC22: =AB22 | AD22: =AC22 | AE22: =AD22 | AF22: =AE22 | AG22: =AF22 | AH22: =AG22 | ... AK22: =AJ22 | BH22: =SUM(E22:BG22)
A23: =A22+1 | B23: Jece Janer Moreira Lopes | E23: =31876.76+2868.91 | F23: =31876.76+2868.91 | G23: =31876.76+2868.91 | H23: =31876.76+2868.91 | I23: =31876.76+2868.91 | J23: =31876.76+2868.91 | K23: =31876.76+2868.91 | L23: =31876.76+2868.91 | M23: =31876.76+2868.91 | N23: =M23*1.05 | O23: =N23 | P23: =O23 | Q23: =P23 | R23: =Q23 | S23: =R23 | T23: =S23 | U23: =T23 | V23: =U23 | W23: =V23 | BH23: =SUM(E23:BG23)
A24: =A23+1 | B24: José dos Santos Magalhães | E24: =22461.64+2021.55 | F24: =22461.64+2021.55 | G24: =22461.64+2021.55 | H24: =22461.64+2021.55 | I24: =22461.64+2021.55 | J24: =22461.64+2021.55 | K24: =22461.64+2021.55 | L24: =22461.64+2021.55 | M24: =22461.64+2021.55 | N24: =M24*1.05 | O24: =N24 | P24: =O24 | Q24: =P24 | R24: =Q24 | S24: =R24 | T24: =S24 | U24: =T24 | V24: =U24 | ... Y24: =X24 | Z24: =Y24*1.05 | AA24: =Z24 | AB24: =AA24 | AC24: =AB24 | AD24: =AC24 | AE24: =AD24 | AF24: =AE24 | AG24: =AF24 | AH24: =AG24 | ... AK24: =AJ24 | AL24: =AK24*1.05 | AM24: =AL24 | AN24: =AM24 | AO24: =AN24 | AP24: =AO24 | AQ24: =AP24 | AR24: =AQ24 | AS24: =AR24 | AT24: =AS24 | ... AW24: =AV24 | BH24: =SUM(E24:BG24)
A25: =A24+1 | B25: José Pedro Francisconi Junior | E25: =22609.42+678.28 | F25: =22609.42+678.28 | G25: =22609.42+678.28 | H25: =22609.42+678.28 | I25: =22609.42+678.28 | J25: =22609.42+678.28 | K25: =22609.42+678.28 | L25: =22609.42+678.28 | M25: =22609.42+678.28 | N25: =M25*1.05 | O25: =N25 | P25: =O25 | Q25: =P25 | R25: =Q25 | S25: =R25 | T25: =S25 | U25: =T25 | V25: =U25 | ... Y25: =X25 | Z25: =Y25*1.05 | AA25: =Z25 | AB25: =AA25 | AC25: =AB25 | AD25: =AC25 | AE25: =AD25 | AF25: =AE25 | AG25: =AF25 | AH25: =AG25 | ... AK25: =AJ25 | BH25: =SUM(E25:BG25)
A26: =A25+1 | B26: Julia Saint Martin Rodrigues da Silva | E26: 4696.2 | F26: 4696.2 | G26: 4696.2 | H26: 4696.2 | I26: 4696.2 | J26: 4696.2 | K26: 4696.2 | L26: 4696.2 | M26: 4696.2 | N26: =M26*1.05 | O26: =N26 | P26: =O26 | Q26: =P26 | R26: =Q26 | S26: =R26 | T26: =S26 | U26: =T26 | V26: =U26 | ... Y26: =X26 | Z26: =Y26*1.05 | AA26: =Z26 | AB26: =AA26 | AC26: =AB26 | AD26: =AC26 | AE26: =AD26 | AF26: =AE26 | AG26: =AF26 | AH26: =AG26 | ... AK26: =AJ26 | AL26: =AK26*1.05 | AM26: =AL26 | AN26: =AM26 | AO26: =AN26 | AP26: =AO26 | AQ26: =AP26 | AR26: =AQ26 | AS26: =AR26 | AT26: =AS26 | ... AW26: =AV26 | BH26: =SUM(E26:BG26)
A27: =A26+1 | B27: Juliana Vieira dos Santos Albuquerque | E27: =9924+595.44 | F27: =9924+595.44 | G27: =9924+595.44 | H27: =9924+595.44 | I27: =9924+595.44 | J27: =9924+595.44 | K27: =9924+595.44 | L27: =9924+595.44 | M27: =9924+595.44 | N27: =M27*1.05 | O27: =N27 | P27: =O27 | Q27: =P27 | R27: =Q27 | S27: =R27 | T27: =S27 | U27: =T27 | V27: =U27 | ... Y27: =X27 | Z27: =Y27*1.05 | AA27: =Z27 | AB27: =AA27 | AC27: =AB27 | AD27: =AC27 | AE27: =AD27 | AF27: =AE27 | AG27: =AF27 | AH27: =AG27 | ... AK27: =AJ27 | AL27: =AK27*1.05 | AM27: =AL27 | AN27: =AM27 | AO27: =AN27 | AP27: =AO27 | AQ27: =AP27 | AR27: =AQ27 | AS27: =AR27 | AT27: =AS27 | ... AW27: =AV27 | BH27: =SUM(E27:BG27)
A28: =A27+1 | B28: Laís Torreão de Castro | E28: =13152.67 | F28: =13152.67 | G28: =13152.67 | H28: =13152.67 | I28: =13152.67 | J28: =13152.67 | K28: =13152.67 | L28: =13152.67 | M28: =13152.67 | N28: =M28*1.05 | O28: =N28 | P28: =O28 | Q28: =P28 | R28: =Q28 | S28: =R28 | T28: =S28 | U28: =T28 | V28: =U28 | ... Y28: =X28 | Z28: =Y28*1.05 | AA28: =Z28 | AB28: =AA28 | AC28: =AB28 | AD28: =AC28 | AE28: =AD28 | AF28: =AE28 | AG28: =AF28 | AH28: =AG28 | ... AK28: =AJ28 | AL28: =AK28*1.05 | AM28: =AL28 | AN28: =AM28 | AO28: =AN28 | AP28: =AO28 | AQ28: =AP28 | AR28: =AQ28 | AS28: =AR28 | AT28: =AS28 | ... AW28: =AV28 | BH28: =SUM(E28:BG28)
A29: =A28+1 | B29: Lauro Costa Girão Borges | E29: =24996.75 | F29: =24996.75 | G29: =24996.75 | H29: =24996.75 | I29: =24996.75 | J29: =24996.75 | K29: =24996.75 | L29: =24996.75 | M29: =24996.75 | BH29: =SUM(E29:BG29)
A30: =A29+1 | B30: Leticia Pinto da Silva | E30: 13133.08 | F30: 13133.08 | G30: 13133.08 | H30: 13133.08 | I30: 13133.08 | J30: 13133.08 | K30: 13133.08 | L30: 13133.08 | M30: 13133.08 | N30: =M30*1.05 | O30: =N30 | P30: =O30 | Q30: =P30 | R30: =Q30 | S30: =R30 | T30: =S30 | U30: =T30 | V30: =U30 | ... Y30: =X30 | Z30: =Y30*1.05 | AA30: =Z30 | AB30: =AA30 | AC30: =AB30 | AD30: =AC30 | AE30: =AD30 | AF30: =AE30 | AG30: =AF30 | AH30: =AG30 | ... AK30: =AJ30 | AL30: =AK30*1.05 | AM30: =AL30 | AN30: =AM30 | AO30: =AN30 | AP30: =AO30 | AQ30: =AP30 | AR30: =AQ30 | AS30: =AR30 | AT30: =AS30 | ... AW30: =AV30 | BH30: =SUM(E30:BG30)
A31: =A30+1 | B31: Lucas de Oliveira Antunes | E31: 11709.19 | F31: 11709.19 | G31: 11709.19 | H31: 11709.19 | I31: 11709.19 | J31: 11709.19 | K31: 11709.19 | L31: 11709.19 | M31: 11709.19 | N31: =M31*1.05 | O31: =N31 | P31: =O31 | Q31: =P31 | R31: =Q31 | S31: =R31 | T31: =S31 | U31: =T31 | V31: =U31 | ... Y31: =X31 | Z31: =Y31*1.05 | AA31: =Z31 | AB31: =AA31 | AC31: =AB31 | AD31: =AC31 | AE31: =AD31 | AF31: =AE31 | AG31: =AF31 | AH31: =AG31 | ... AK31: =AJ31 | AL31: =AK31*1.05 | AM31: =AL31 | AN31: =AM31 | AO31: =AN31 | AP31: =AO31 | AQ31: =AP31 | AR31: =AQ31 | AS31: =AR31 | AT31: =AS31 | ... AW31: =AV31 | BH31: =SUM(E31:BG31)
A32: =A31+1 | B32: Luis Eduardo Sousa e Silva | E32: =3961.56+237.69 | F32: =3961.56+237.69 | G32: =3961.56+237.69 | H32: =3961.56+237.69 | I32: =3961.56+237.69 | J32: =3961.56+237.69 | K32: =3961.56+237.69 | L32: =3961.56+237.69 | M32: =3961.56+237.69 | BH32: =SUM(E32:BG32)
A33: =A32+1 | B33: Luiz Augusto de Assis Peixoto | E33: 12523.2 | F33: 12523.2 | G33: 12523.2 | H33: 12523.2 | I33: 12523.2 | J33: 12523.2 | K33: 12523.2 | L33: 12523.2 | M33: 12523.2 | BH33: =SUM(E33:BG33)
A34: =A33+1 | B34: Maria Aparecida Francelino dos Santos | E34: =2817.72+422.66 | F34: =2817.72+422.66 | G34: =2817.72+422.66 | H34: =2817.72+422.66 | I34: =2817.72+422.66 | J34: =2817.72+422.66 | K34: =2817.72+422.66 | L34: =2817.72+422.66 | M34: =2817.72+422.66 | BH34: =SUM(E34:BG34)
A35: =A34+1 | B35: Paola Cemin da Silva | E35: =12893.4+773.6 | F35: =12893.4+773.6 | G35: =12893.4+773.6 | H35: =12893.4+773.6 | I35: =12893.4+773.6 | J35: =12893.4+773.6 | K35: =12893.4+773.6 | L35: =12893.4+773.6 | M35: =12893.4+773.6 | N35: =M35*1.05 | O35: =N35 | P35: =O35 | Q35: =P35 | R35: =Q35 | S35: =R35 | T35: =S35 | U35: =T35 | V35: =U35 | ... Y35: =X35 | Z35: =Y35*1.05 | AA35: =Z35 | AB35: =AA35 | AC35: =AB35 | AD35: =AC35 | AE35: =AD35 | AF35: =AE35 | AG35: =AF35 | AH35: =AG35 | ... AK35: =AJ35 | BH35: =SUM(E35:BG35)
A36: =A35+1 | B36: Paulo Roberto dos Santos | E36: =19230.87+2884.53 | F36: =19230.87+2884.53 | G36: =19230.87+2884.53 | H36: =19230.87+2884.53 | I36: =19230.87+2884.53 | J36: =19230.87+2884.53 | K36: =19230.87+2884.53 | L36: =19230.87+2884.53 | M36: =19230.87+2884.53 | BH36: =SUM(E36:BG36)
A37: =A36+1 | B37: Priscila Lammel | E37: =8295.01+497.7 | F37: =8295.01+497.7 | G37: =8295.01+497.7 | H37: =8295.01+497.7 | I37: =8295.01+497.7 | J37: =8295.01+497.7 | K37: =8295.01+497.7 | L37: =8295.01+497.7 | M37: =8295.01+497.7 | BH37: =SUM(E37:BG37)
A38: =A37+1 | B38: Rafael Cardoso Cunha | E38: =18873.4+1698.61 | F38: =18873.4+1698.61 | G38: =18873.4+1698.61 | H38: =18873.4+1698.61 | I38: =18873.4+1698.61 | J38: =18873.4+1698.61 | K38: =18873.4+1698.61 | L38: =18873.4+1698.61 | M38: =18873.4+1698.61 | N38: =M38*1.05 | O38: =N38 | P38: =O38 | Q38: =P38 | R38: =Q38 | S38: =R38 | T38: =S38 | U38: =T38 | V38: =U38 | ... Y38: =X38 | Z38: =Y38*1.05 | AA38: =Z38 | AB38: =AA38 | AC38: =AB38 | AD38: =AC38 | AE38: =AD38 | AF38: =AE38 | AG38: =AF38 | AH38: =AG38 | ... AK38: =AJ38 | BH38: =SUM(E38:BG38)
A39: =A38+1 | B39: Rafael Cassimiro Barbosa | E39: =11709.19+351.28 | F39: =11709.19+351.28 | G39: =11709.19+351.28 | H39: =11709.19+351.28 | I39: =11709.19+351.28 | J39: =11709.19+351.28 | K39: =11709.19+351.28 | L39: =11709.19+351.28 | M39: =11709.19+351.28 | N39: =M39*1.05 | O39: =N39 | P39: =O39 | Q39: =P39 | R39: =Q39 | S39: =R39 | T39: =S39 | U39: =T39 | V39: =U39 | ... Y39: =X39 | Z39: =Y39*1.05 | AA39: =Z39 | AB39: =AA39 | AC39: =AB39 | AD39: =AC39 | AE39: =AD39 | AF39: =AE39 | AG39: =AF39 | AH39: =AG39 | ... AK39: =AJ39 | AL39: =AK39*1.05 | AM39: =AL39 | AN39: =AM39 | AO39: =AN39 | AP39: =AO39 | AQ39: =AP39 | AR39: =AQ39 | AS39: =AR39 | AT39: =AS39 | ... AW39: =AV39 | BH39: =SUM(E39:BG39)
A40: =A39+1 | B40: Renata Alcantara Lima | E40: =11709.19 | F40: =11709.19 | G40: =11709.19 | H40: =11709.19 | I40: =11709.19 | J40: =11709.19 | K40: =11709.19 | L40: =11709.19 | M40: =11709.19 | N40: =M40*1.05 | O40: =N40 | P40: =O40 | Q40: =P40 | R40: =Q40 | S40: =R40 | T40: =S40 | U40: =T40 | V40: =U40 | ... Y40: =X40 | Z40: =Y40*1.05 | AA40: =Z40 | AB40: =AA40 | AC40: =AB40 | AD40: =AC40 | AE40: =AD40 | AF40: =AE40 | AG40: =AF40 | AH40: =AG40 | ... AK40: =AJ40 | AL40: =AK40*1.05 | AM40: =AL40 | AN40: =AM40 | AO40: =AN40 | AP40: =AO40 | AQ40: =AP40 | AR40: =AQ40 | AS40: =AR40 | AT40: =AS40 | ... AW40: =AV40 | BH40: =SUM(E40:BG40)
A41: =A40+1 | B41: Rildo Ap. F. Andrade | E41: =26035.63+3905.34 | F41: =26035.63+3905.34 | G41: =26035.63+3905.34 | H41: =26035.63+3905.34 | I41: =26035.63+3905.34 | J41: =26035.63+3905.34 | K41: =26035.63+3905.34 | L41: =26035.63+3905.34 | M41: =26035.63+3905.34 | BH41: =SUM(E41:BG41)
A42: =A41+1 | B42: Rodrigo Varella | E42: =13050.82+783.05 | F42: =13050.82+783.05 | G42: =13050.82+783.05 | H42: =13050.82+783.05 | I42: =13050.82+783.05 | J42: =13050.82+783.05 | K42: =13050.82+783.05 | L42: =13050.82+783.05 | M42: =13050.82+783.05 | N42: =M42*1.05 | O42: =N42 | P42: =O42 | Q42: =P42 | R42: =Q42 | S42: =R42 | T42: =S42 | U42: =T42 | V42: =U42 | ... Y42: =X42 | Z42: =Y42*1.05 | AA42: =Z42 | AB42: =AA42 | AC42: =AB42 | AD42: =AC42 | AE42: =AD42 | AF42: =AE42 | AG42: =AF42 | AH42: =AG42 | ... AK42: =AJ42 | AL42: =AK42*1.05 | AM42: =AL42 | AN42: =AM42 | AO42: =AN42 | AP42: =AO42 | AQ42: =AP42 | AR42: =AQ42 | AS42: =AR42 | AT42: =AS42 | ... AW42: =AV42 | BH42: =SUM(E42:BG42)
A43: =A42+1 | B43: Sandréia Schmidt Silvano | E43: =21835.08+1704.16 | F43: =21835.08+1704.16 | G43: =21835.08+1704.16 | H43: =21835.08+1704.16 | I43: =21835.08+1704.16 | J43: =21835.08+1704.16 | K43: =21835.08+1704.16 | L43: =21835.08+1704.16 | M43: =21835.08+1704.16 | BH43: =SUM(E43:BG43)
A44: =A43+1 | B44: Sofia Souza | E44: 11709.19 | F44: 11709.19 | G44: 11709.19 | H44: 11709.19 | I44: 11709.19 | J44: 11709.19 | K44: 11709.19 | L44: 11709.19 | M44: 11709.19 | BH44: =SUM(E44:BG44)
A45: =A44+1 | B45: Wanderson Bruno Alcides de Morais e Silva | E45: 11709.19 | F45: 11709.19 | G45: 11709.19 | H45: 11709.19 | I45: 11709.19 | J45: 11709.19 | K45: 11709.19 | L45: 11709.19 | M45: 11709.19 | BH45: =SUM(E45:BG45)
A46: =A45+1 | B46: Wesley Miranda de Carvalho | E46: 10755.17 | F46: 10756.17 | G46: 10757.17 | H46: 10758.17 | I46: 10759.17 | J46: 10760.17 | K46: 10761.17 | L46: 10762.17 | M46: 10763.17 | BH46: =SUM(E46:BG46)
A47: =A46+1 | B47: Encargos Trabalhistas | E47: =(SUM(E4:E41)*0.8) | F47: =(SUM(F4:F41)*0.8) | G47: =(SUM(G4:G41)*0.8) | H47: =(SUM(H4:H41)*0.8) | I47: =(SUM(I4:I41)*0.8) | J47: =(SUM(J4:J41)*0.8) | K47: =(SUM(K4:K41)*0.8) | L47: =(SUM(L4:L41)*0.8) | ... AW47: =(SUM(AW4:AW41)*0.8) | BH47: =SUM(E47:BG47) | CN47: 5236091 | CO47: =BH47-CN47
A48: =A47+1 | B48: Agatha Nascimento | E48: 1050 | F48: 1050 | G48: 1050 | H48: 1050 | I48: 1050 | J48: 1050 | K48: 1050 | L48: 1050 | M48: 1050 | BH48: =SUM(E48:BG48)
A49: =A48+1 | B49: Amabille Buglione Peruch | E49: 1050 | F49: 1050 | G49: 1050 | H49: 1050 | I49: 1050 | J49: 1050 | K49: 1050 | L49: 1050 | M49: 1050 | BH49: =SUM(E49:BG49)
A50: =A49+1 | B50: Ana Beatriz Silva Barreto | E50: 1050 | F50: 1050 | G50: 1050 | H50: 1050 | I50: 1050 | J50: 1050 | K50: 1050 | L50: 1050 | M50: 1050 | BH50: =SUM(E50:BG50)
A51: =A50+1 | B51: Ana Júlia Luchezi Lazzari | E51: 1050 | F51: 1050 | G51: 1050 | H51: 1050 | I51: 1050 | J51: 1050 | K51: 1050 | L51: 1050 | M51: 1050 | BH51: =SUM(E51:BG51)
A52: =A51+1 | B52: Ana Luiza Herrerias de Jesus | E52: 1050 | F52: 1050 | G52: 1050 | H52: 1050 | I52: 1050 | J52: 1050 | K52: 1050 | L52: 1050 | M52: 1050 | BH52: =SUM(E52:BG52)
A53: =A52+1 | B53: André Fazolo | E53: 1050 | F53: 1050 | G53: 1050 | H53: 1050 | I53: 1050 | J53: 1050 | K53: 1050 | L53: 1050 | M53: 1050 | BH53: =SUM(E53:BG53)
A54: =A53+1 | B54: Andreilson Ferreira da Silva | E54: 1050 | F54: 1050 | G54: 1050 | H54: 1050 | I54: 1050 | J54: 1050 | K54: 1050 | L54: 1050 | M54: 1050 | BH54: =SUM(E54:BG54)
A55: =A54+1 | B55: Arthur Biava Camargo | E55: 1050 | F55: 1050 | G55: 1050 | H55: 1050 | I55: 1050 | J55: 1050 | K55: 1050 | L55: 1050 | M55: 1050 | BH55: =SUM(E55:BG55)
A56: =A55+1 | B56: Bárbara Martins Folador | E56: 2200 | F56: 2200 | G56: 2200 | H56: 2200 | I56: 2200 | J56: 2200 | K56: 2200 | L56: 2200 | M56: 2200 | BH56: =SUM(E56:BG56)
A57: =A56+1 | B57: Bernardo Perin Cima | E57: 3200 | F57: 3200 | G57: 3200 | H57: 3200 | I57: 3200 | J57: 3200 | K57: 3200 | L57: 3200 | M57: 3200 | BH57: =SUM(E57:BG57)
A58: =A57+1 | B58: Bruno Carlo Celeguim De Amattos | E58: 4000 | F58: 4000 | G58: 4000 | H58: 4000 | I58: 4000 | J58: 4000 | K58: 4000 | L58: 4000 | M58: 4000 | BH58: =SUM(E58:BG58)
A59: =A58+1 | B59: Caroline Bueno dos Anjos | E59: 1050 | F59: 1050 | G59: 1050 | H59: 1050 | I59: 1050 | J59: 1050 | K59: 1050 | L59: 1050 | M59: 1050 | BH59: =SUM(E59:BG59)
A60: =A59+1 | B60: Cirilo Albino Nunes | E60: 2200 | F60: 2200 | G60: 2200 | H60: 2200 | I60: 2200 | J60: 2200 | K60: 2200 | L60: 2200 | M60: 2200 | BH60: =SUM(E60:BG60)
A61: =A60+1 | B61: Daniel Weiss | E61: 1050 | F61: 1050 | G61: 1050 | H61: 1050 | I61: 1050 | J61: 1050 | K61: 1050 | BH61: =SUM(E61:BG61)
A62: =A61+1 | B62: David Willian Henequim | E62: 1050 | F62: 1050 | G62: 1050 | H62: 1050 | I62: 1050 | J62: 1050 | K62: 1050 | L62: 1050 | M62: 1050 | BH62: =SUM(E62:BG62)
A63: =A62+1 | B63: Débora Casasola | E63: 1625 | F63: 1625 | BH63: =SUM(E63:BG63)
A64: =A63+1 | B64: Estefani de Oliveira | E64: 1050 | F64: 1050 | G64: 1050 | H64: 1050 | I64: 1050 | J64: 1050 | K64: 1050 | L64: 1050 | M64: 1050 | BH64: =SUM(E64:BG64)
A65: =A64+1 | B65: Felipe Miranda | E65: 1050 | F65: 1050 | G65: 1050 | H65: 1050 | I65: 1050 | J65: 1050 | K65: 1050 | L65: 1050 | M65: 1050 | BH65: =SUM(E65:BG65)
A66: =A65+1 | B66: Fernanda Mayumi Maekawa Arruda | E66: 1050 | F66: 1050 | G66: 1050 | H66: 1050 | I66: 1050 | J66: 1050 | K66: 1050 | L66: 1050 | M66: 1050 | BH66: =SUM(E66:BG66)
A67: =A66+1 | B67: Fernando Seabra | E67: 3000 | F67: 3000 | G67: 3000 | H67: 3000 | I67: 3000 | J67: 3000 | K67: 3000 | L67: 3000 | M67: 3000 | N67: 3000 | O67: 3000 | P67: 3000 | Q67: 3000 | R67: 3000 | S67: 3000 | T67: 3000 | U67: 3000 | V67: 3000 | W67: 3000 | BH67: =SUM(E67:BG67)
A68: =A67+1 | B68: Gabriel Almeida Ribeiro | E68: 1050 | F68: 1050 | G68: 1050 | H68: 1050 | I68: 1050 | J68: 1050 | K68: 1050 | L68: 1050 | M68: 1050 | BH68: =SUM(E68:BG68)
A69: =A68+1 | B69: Gabriel Dal Pont | E69: 1050 | F69: 1050 | G69: 1050 | H69: 1050 | I69: 1050 | J69: 1050 | K69: 1050 | L69: 1050 | M69: 1050 | BH69: =SUM(E69:BG69)
A70: =A69+1 | B70: Gabriel Silveira da Silva | E70: 1050 | F70: 1050 | G70: 1050 | H70: 1050 | I70: 1050 | J70: 1050 | K70: 1050 | L70: 1050 | M70: 1050 | BH70: =SUM(E70:BG70)
A71: =A70+1 | B71: Geovana Mohr Thomas | E71: 1050 | F71: 1050 | G71: 1050 | H71: 1050 | BH71: =SUM(E71:BG71)
A72: =A71+1 | B72: Giorgia Hack Barreto Dariva | E72: 2200 | F72: 2200 | G72: 2200 | H72: 2200 | I72: 2200 | J72: 2200 | K72: 2200 | L72: 2200 | M72: 2200 | BH72: =SUM(E72:BG72)
A73: =A72+1 | B73: Giovana Beatriz Vogel da Silva | E73: 1050 | F73: 1050 | G73: 1050 | H73: 1050 | I73: 1050 | J73: 1050 | K73: 1050 | L73: 1050 | M73: 1050 | BH73: =SUM(E73:BG73)
A74: =A73+1 | B74: Giulia Glienke | E74: 1050 | F74: 1050 | G74: 1050 | H74: 1050 | I74: 1050 | J74: 1050 | K74: 1050 | L74: 1050 | M74: 1050 | BH74: =SUM(E74:BG74)
A75: =A74+1 | B75: Giulia Pimentel Cia Koike | E75: 1625 | F75: 1625 | G75: 1625 | H75: 1625 | I75: 1625 | J75: 1625 | K75: 1625 | L75: 1625 | M75: 1625 | BH75: =SUM(E75:BG75)
A76: =A75+1 | B76: Ian Rick das Neves Lima | E76: 1050 | F76: 1050 | G76: 1050 | H76: 1050 | I76: 1050 | J76: 1050 | K76: 1050 | L76: 1050 | M76: 1050 | BH76: =SUM(E76:BG76)
A77: =A76+1 | B77: Iara Carolini Pinheiro | E77: 3200 | F77: 3200 | G77: 3200 | H77: 3200 | I77: 3200 | J77: 3200 | K77: 3200 | L77: 3200 | M77: 3200 | BH77: =SUM(E77:BG77)
A78: =A77+1 | B78: Igor Bombassaro Suzin | E78: 1050 | F78: 1050 | G78: 1050 | H78: 1050 | I78: 1050 | J78: 1050 | K78: 1050 | L78: 1050 | M78: 1050 | BH78: =SUM(E78:BG78)
A79: =A78+1 | B79: Isadora Waltrick | E79: 1050 | F79: 1050 | G79: 1050 | H79: 1050 | I79: 1050 | J79: 1050 | K79: 1050 | L79: 1050 | M79: 1050 | BH79: =SUM(E79:BG79)
A80: =A79+1 | B80: Jhenifer Carolione Santos Schmidt Hebbel | E80: 1050 | F80: 1050 | G80: 1050 | BH80: =SUM(E80:BG80)
A81: =A80+1 | B81: João Lucas De Siqueira Rosa | E81: 2000 | F81: 2000 | G81: 2000 | H81: 2000 | BH81: =SUM(E81:BG81)
A82: =A81+1 | B82: Julia Fernanda Mafra Menger | E82: 1050 | F82: 1050 | G82: 1050 | H82: 1050 | I82: 1050 | J82: 1050 | K82: 1050 | L82: 1050 | M82: 1050 | BH82: =SUM(E82:BG82)
A83: =A82+1 | B83: Júlia Martins Prudêncio | E83: 1050 | F83: 1050 | G83: 1050 | H83: 1050 | I83: 1050 | J83: 1050 | K83: 1050 | L83: 1050 | M83: 1050 | BH83: =SUM(E83:BG83)
A84: =A83+1 | B84: Laiara Machado Serafim | E84: 2200 | F84: 2200 | G84: 2200 | H84: 2200 | I84: 2200 | J84: 2200 | K84: 2200 | L84: 2200 | M84: 2200 | BH84: =SUM(E84:BG84)
A85: =A84+1 | B85: Lucas de Medeiros Gomes Matuo | E85: 1050 | F85: 1050 | G85: 1050 | H85: 1050 | I85: 1050 | J85: 1050 | K85: 1050 | L85: 1050 | M85: 1050 | BH85: =SUM(E85:BG85)
A86: =A85+1 | B86: Lucas Lorival Machado | E86: 1050 | F86: 1050 | G86: 1050 | H86: 1050 | I86: 1050 | J86: 1050 | K86: 1050 | L86: 1050 | M86: 1050 | BH86: =SUM(E86:BG86)
A87: =A86+1 | B87: Luciana Rohde | E87: 3000 | BH87: =SUM(E87:BG87)
A88: =A87+1 | B88: Luís Henrique Da Silva Simão | E88: 1050 | F88: 1050 | G88: 1050 | H88: 1050 | I88: 1050 | J88: 1050 | K88: 1050 | L88: 1050 | M88: 1050 | BH88: =SUM(E88:BG88)
A89: =A88+1 | B89: Luísa Mendes Amaral de Lima | E89: 1050 | F89: 1050 | G89: 1050 | H89: 1050 | I89: 1050 | J89: 1050 | K89: 1050 | L89: 1050 | M89: 1050 | BH89: =SUM(E89:BG89)
A90: =A89+1 | B90: Maria Eduarda Borges Oliveira | E90: 1050 | F90: 1050 | G90: 1050 | H90: 1050 | I90: 1050 | J90: 1050 | K90: 1050 | L90: 1050 | M90: 1050 | BH90: =SUM(E90:BG90)
A91: =A90+1 | B91: Maria Eduarda Gonçalves | E91: 2200 | F91: 2200 | G91: 2200 | H91: 2200 | I91: 2200 | J91: 2200 | K91: 2200 | L91: 2200 | M91: 2200 | BH91: =SUM(E91:BG91)
A92: =A91+1 | B92: Maria Fernanda Fagundes Alamini | E92: 2200 | F92: 2200 | G92: 2200 | H92: 2200 | I92: 2200 | J92: 2200 | K92: 2200 | L92: 2200 | M92: 2200 | BH92: =SUM(E92:BG92)
A93: =A92+1 | B93: Maria Luiza Queiroga Lemos Souza Cavalcante Costa | E93: 2200 | F93: 2200 | G93: 2200 | H93: 2200 | I93: 2200 | J93: 2200 | K93: 2200 | L93: 2200 | M93: 2200 | BH93: =SUM(E93:BG93)
A94: =A93+1 | B94: Mariana Souza dos Santos | E94: 1050 | F94: 1050 | G94: 1050 | H94: 1050 | I94: 1050 | J94: 1050 | K94: 1050 | L94: 1050 | M94: 1050 | BH94: =SUM(E94:BG94)
A95: =A94+1 | B95: Miguel Marchi Jasper | E95: 1050 | F95: 1050 | G95: 1050 | H95: 1050 | I95: 1050 | J95: 1050 | K95: 1050 | L95: 1050 | M95: 1050 | BH95: =SUM(E95:BG95)
A96: =A95+1 | B96: Milena Leão | E96: 2200 | F96: 2200 | G96: 2200 | H96: 2200 | I96: 2200 | J96: 2200 | K96: 2200 | L96: 2200 | M96: 2200 | BH96: =SUM(E96:BG96)
A97: =A96+1 | B97: Milena Welter Sotoriva | E97: 1050 | F97: 1050 | G97: 1050 | H97: 1050 | I97: 1050 | J97: 1050 | K97: 1050 | L97: 1050 | M97: 1050 | BH97: =SUM(E97:BG97)
A98: =A97+1 | B98: Monalisa Teixeira | E98: 1050 | F98: 1050 | G98: 1050 | H98: 1050 | I98: 1050 | J98: 1050 | K98: 1050 | L98: 1050 | M98: 1050 | BH98: =SUM(E98:BG98)
A99: =A98+1 | B99: Naely Terezinha Costa | E99: 1050 | F99: 1050 | G99: 1050 | H99: 1050 | I99: 1050 | J99: 1050 | K99: 1050 | L99: 1050 | M99: 1050 | BH99: =SUM(E99:BG99)
A100: =A99+1 | B100: Renata Pacheco | E100: 2500 | BH100: =SUM(E100:BG100)
...

Sheet DNIT 2026
E1: 46235 | F1: 46266 | G1: 46296 | H1: 46327 | I1: 46357 | J1: 46388 | K1: 46419 | L1: 46447 | M1: 46478 | N1: 46508 | O1: 46539 | P1: 46569 | Q1: 46600 | R1: 46631 | S1: 46661 | T1: 46692 | U1: 46722 | V1: 46753 | W1: 46784 | X1: 46813 | Y1: 46844 | Z1: 46874 | AA1: 46905 | AB1: 46935 | AC1: 46966 | AD1: 46997 | AE1: 47027 | AF1: 47058 | AG1: 47088 | AH1: 47119 | AI1: 47150 | AJ1: 47178 | AK1: 47209 | AL1: 47239 | AM1: 47270 | AN1: 47300 | AO1: 47331 | AP1: 47362 | AQ1: 47392 | AR1: 47423 | AS1: 47453 | AT1: 47484 | AU1: 47515 | AV1: 47543 | AW1: 47574 | AX1: 47604 | AY1: 47635 | AZ1: 47665 | BA1: 47696 | BB1: 47727 | BC1: 47757 | BD1: 47788 | BE1: 47818 | BF1: 47849 | BG1: 47880 | BH1: 47908 | BI1: 47939 | BJ1: 47969 | BK1: 48000 | BL1: 48030
A2: N˚ | B2: Receita | D2: Até mai/2026 | E2: Mês 1 | F2: Mês 2 | G2: Mês 3 | H2: Mês 4 | I2: Mês 5 | J2: Mês 6 | K2: Mês 7 | L2: Mês 8 | M2: Mês 9 | N2: Mês 10 | O2: Mês 11 | P2: Mês 12 | Q2: Mês 13 | R2: Mês 14 | S2: Mês 15 | T2: Mês 16 | U2: Mês 17 | V2: Mês 18 | W2: Mês 19 | X2: Mês 20 | Y2: Mês 21 | Z2: Mês 22 | AA2: Mês 23 | AB2: Mês 24 | AC2: Mês 25 | AD2: Mês 26 | AE2: Mês 27 | AF2: Mês 28 | AG2: Mês 29 | AH2: Mês 30 | AI2: Mês 31 | AJ2: Mês 32 | AK2: Mês 33 | AL2: Mês 34 | AM2: Mês 35 | AN2: Mês 36 | AO2: Mês 37 | AP2: Mês 38 | AQ2: Mês 39 | AR2: Mês 40 | AS2: Mês 41 | AT2: Mês 42 | AU2: Mês 43 | AV2: Mês 44 | AW2: Mês 45 | AX2: Mês 46 | AY2: Mês 47 | AZ2: Mês 48 | BA2: Mês 49 | BB2: Mês 50 | BC2: Mês 51 | BD2: Mês 52 | BE2: Mês 53 | BF2: Mês 54 | BG2: Mês 55 | BH2: Mês 56 | BI2: Mês 57 | BJ2: Mês 58 | BK2: Mês 59 | BL2: Mês 60 | BM2: Totais
A3: 1 | B3: Parcelas | D3: =E102 | E3: 4935112 | F3: 0 | G3: 0 | H3: 4776605 | I3: 0 | J3: 0 | K3: 0 | L3: 4621485 | M3: 0 | N3: 0 | O3: 0 | P3: 6954175 | Q3: 0 | R3: 0 | S3: 0 | T3: 7464248 | U3: 0 | V3: 0 | W3: 0 | X3: 6920267 | Y3: 0 | Z3: 0 | AA3: 0 | AB3: 7097170 | AC3: 0 | AD3: 0 | AE3: 0 | AF3: 6800937 | AG3: 0 | AH3: 0 | AI3: 0 | AJ3: 6735127 | AK3: 0 | AL3: 0 | AM3: 0 | AN3: 6887097 | AO3: 0 | AP3: 0 | AQ3: 0 | AR3: 6652381 | AS3: 0 | AT3: 0 | AU3: 0 | AV3: 6499459 | AW3: 0 | AX3: 0 | AY3: 0 | AZ3: 6331343 | BA3: 0 | BB3: 0 | BC3: 0 | BD3: 5995102 | BE3: 0 | BF3: 0 | BG3: 0 | BH3: 5874097 | BI3: 0 | BJ3: 0 | BK3: 0 | BL3: 0 | BM3: =SUM(D3:BL3)
A4: N˚ | B4: Despesas | E4: =E2 | F4: =F2 | G4: =G2 | H4: =H2 | I4: =I2 | J4: =J2 | K4: =K2 | L4: =L2 | ... BL4: =BL2 | BM4: Totais
A5: 1 | B5: Alexandre Garcez Nunes | E5: =12180.93+730.88 | F5: =12180.93+730.88 | G5: =12180.93+730.88 | H5: =12180.93+730.88 | I5: =12180.93+730.88 | J5: =12180.93+730.88 | K5: =12180.93+730.88 | L5: =12180.93+730.88 | ... BL5: =12180.93+730.88 | BM5: =SUM(E5:BL5)
A6: =A5+1 | B6: Bruno Maluche Neto | E6: =19765.28+4743.67 | F6: =19765.28+4743.67 | G6: =19765.28+4743.67 | H6: =19765.28+4743.67 | I6: =19765.28+4743.67 | J6: =19765.28+4743.67 | K6: =19765.28+4743.67 | L6: =19765.28+4743.67 | ... BL6: =19765.28+4743.67 | BM6: =SUM(E6:BL6)
A7: =A6+1 | B7: Fernanda Miranda | E7: =10052.21+904.7 | F7: =10052.21+904.7 | G7: =10052.21+904.7 | H7: =10052.21+904.7 | I7: =10052.21+904.7 | J7: =10052.21+904.7 | K7: =10052.21+904.7 | L7: =10052.21+904.7 | ... BL7: =10052.21+904.7 | BM7: =SUM(E7:BL7)
A8: =A7+1 | B8: Giseli de Sousa | E8: =13593.2+1223.39 | F8: =13593.2+1223.39 | G8: =13593.2+1223.39 | H8: =13593.2+1223.39 | I8: =13593.2+1223.39 | J8: =13593.2+1223.39 | K8: =13593.2+1223.39 | L8: =13593.2+1223.39 | ... BL8: =13593.2+1223.39 | BM8: =SUM(E8:BL8)
A9: =A8+1 | B9: Joao Gabriel Crema | E9: =13592.7+2038.9 | F9: =13592.7+2038.9 | G9: =13592.7+2038.9 | H9: =13592.7+2038.9 | I9: =13592.7+2038.9 | J9: =13592.7+2038.9 | K9: =13592.7+2038.9 | L9: =13592.7+2038.9 | ... BL9: =13592.7+2038.9 | BM9: =SUM(E9:BL9)
A10: =A9+1 | B10: Josivan Laskoski | E10: =17670.52+2120.46 | F10: =17670.52+2120.46 | G10: =17670.52+2120.46 | H10: =17670.52+2120.46 | I10: =17670.52+2120.46 | J10: =17670.52+2120.46 | K10: =17670.52+2120.46 | L10: =17670.52+2120.46 | ... BL10: =17670.52+2120.46 | BM10: =SUM(E10:BL10)
A11: =A10+1 | B11: Marcelo Maciel Pereira | E11: =11583.15+2779.96 | F11: =11583.15+2779.96 | G11: =11583.15+2779.96 | H11: =11583.15+2779.96 | I11: =11583.15+2779.96 | J11: =11583.15+2779.96 | K11: =11583.15+2779.96 | L11: =11583.15+2779.96 | ... BL11: =11583.15+2779.96 | BM11: =SUM(E11:BL11)
A12: =A11+1 | B12: Morgana Leite | E12: =5994.65+539.52 | F12: =5994.65+539.52 | G12: =5994.65+539.52 | H12: =5994.65+539.52 | I12: =5994.65+539.52 | J12: =5994.65+539.52 | K12: =5994.65+539.52 | L12: =5994.65+539.52 | ... BL12: =5994.65+539.52 | BM12: =SUM(E12:BL12)
A13: =A12+1 | B13: Rafael Berretta | E13: =5341.55+480.74 | F13: =5341.55+480.74 | G13: =5341.55+480.74 | H13: =5341.55+480.74 | I13: =5341.55+480.74 | J13: =5341.55+480.74 | K13: =5341.55+480.74 | L13: =5341.55+480.74 | ... BL13: =5341.55+480.74 | BM13: =SUM(E13:BL13)
A14: =A13+1 | B14: Thaysa Momm Bastos | E14: =6794.33+407.66 | F14: =6794.33+407.66 | G14: =6794.33+407.66 | H14: =6794.33+407.66 | I14: =6794.33+407.66 | J14: =6794.33+407.66 | K14: =6794.33+407.66 | L14: =6794.33+407.66 | ... BL14: =6794.33+407.66 | BM14: =SUM(E14:BL14)
A15: =A14+1 | B15: Alexandre Gonçalves | E15: =6153.88+369.23 | F15: =6153.88+369.23 | G15: =6153.88+369.23 | H15: =6153.88+369.23 | I15: =6153.88+369.23 | J15: =6153.88+369.23 | K15: =6153.88+369.23 | L15: =6153.88+369.23 | ... BL15: =6153.88+369.23 | BM15: =SUM(E15:BL15)
A16: =A15+1 | B16: Aline Martins de Souza | E16: =5335.31+320.12 | F16: =5335.31+320.12 | G16: =5335.31+320.12 | H16: =5335.31+320.12 | I16: =5335.31+320.12 | J16: =5335.31+320.12 | K16: =5335.31+320.12 | L16: =5335.31+320.12 | ... BL16: =5335.31+320.12 | BM16: =SUM(E16:BL16)
A17: =A16+1 | B17: Daniel Vieira Machado | E17: =12893.4 | F17: =12893.4 | G17: =12893.4 | H17: =12893.4 | I17: =12893.4 | J17: =12893.4 | K17: =12893.4 | L17: =12893.4 | ... BL17: =12893.4 | BM17: =SUM(E17:BL17)
A18: =A17+1 | B18: Danilo Franklin Leite Lopes | E18: =7551.52 | F18: =7551.52 | G18: =7551.52 | H18: =7551.52 | I18: =7551.52 | J18: =7551.52 | K18: =7551.52 | L18: =7551.52 | ... BL18: =7551.52 | BM18: =SUM(E18:BL18)
A19: =A18+1 | B19: Débora Machado Gonçalves | E19: =5635.44 | F19: =5635.44 | G19: =5635.44 | H19: =5635.44 | I19: =5635.44 | J19: =5635.44 | K19: =5635.44 | L19: =5635.44 | ... BL19: =5635.44 | BM19: =SUM(E19:BL19)
A20: =A19+1 | B20: Deucélia Eva Pedroso | E20: =14406.21+864.37 | F20: =14406.21+864.37 | G20: =14406.21+864.37 | H20: =14406.21+864.37 | I20: =14406.21+864.37 | J20: =14406.21+864.37 | K20: =14406.21+864.37 | L20: =14406.21+864.37 | ... BL20: =14406.21+864.37 | BM20: =SUM(E20:BL20)
A21: =A20+1 | B21: Eder Tagveira dos Santos | E21: 10500 | F21: 10501 | G21: 10502 | H21: 10503 | I21: 10504 | J21: 10505 | K21: 10506 | L21: 10507 | M21: 10508 | N21: 10509 | O21: 10510 | P21: 10511 | Q21: 10512 | R21: 10513 | S21: 10514 | T21: 10515 | U21: 10516 | V21: 10517 | W21: 10518 | X21: 10519 | Y21: 10520 | Z21: 10521 | AA21: 10522 | AB21: 10523 | AC21: 10524 | AD21: 10525 | AE21: 10526 | AF21: 10527 | AG21: 10528 | AH21: 10529 | AI21: 10530 | AJ21: 10531 | AK21: 10532 | AL21: 10533 | AM21: 10534 | AN21: 10535 | AO21: 10536 | AP21: 10537 | AQ21: 10538 | AR21: 10539 | AS21: 10540 | AT21: 10541 | AU21: 10542 | AV21: 10543 | AW21: 10544 | AX21: 10545 | AY21: 10546 | AZ21: 10547 | BA21: 10548 | BB21: 10549 | BC21: 10550 | BD21: 10551 | BE21: 10552 | BF21: 10553 | BG21: 10554 | BH21: 10555 | BI21: 10556 | BJ21: 10557 | BK21: 10558 | BL21: 10559 | BM21: =SUM(E21:BL21)
A22: =A21+1 | B22: Elizabeth Ventura da Silva | E22: =4615.4+553.85 | F22: =4615.4+553.85 | G22: =4615.4+553.85 | H22: =4615.4+553.85 | I22: =4615.4+553.85 | J22: =4615.4+553.85 | K22: =4615.4+553.85 | L22: =4615.4+553.85 | ... BL22: =4615.4+553.85 | BM22: =SUM(E22:BL22)
A23: =A22+1 | B23: Érika Cavalcante de Souza Tartari | E23: =6566.54 | F23: =6566.54 | G23: =6566.54 | H23: =6566.54 | I23: =6566.54 | J23: =6566.54 | K23: =6566.54 | L23: =6566.54 | ... BL23: =6566.54 | BM23: =SUM(E23:BL23)
A24: =A23+1 | B24: Gabriel Domingos Adriano | E24: =6019.33 | F24: =6019.33 | G24: =6019.33 | H24: =6019.33 | I24: =6019.33 | J24: =6019.33 | K24: =6019.33 | L24: =6019.33 | ... BL24: =6019.33 | BM24: =SUM(E24:BL24)
A25: =A24+1 | B25: Gabriel Phillipe Ferreira Perpetuo | E25: =4487.14 | F25: =4487.14 | G25: =4487.14 | H25: =4487.14 | I25: =4487.14 | J25: =4487.14 | K25: =4487.14 | L25: =4487.14 | ... BL25: =4487.14 | BM25: =SUM(E25:BL25)
A26: =A25+1 | B26: Gastão Cassel | E26: =11091.26+1330.95 | F26: =11091.26+1330.95 | G26: =11091.26+1330.95 | H26: =11091.26+1330.95 | I26: =11091.26+1330.95 | J26: =11091.26+1330.95 | K26: =11091.26+1330.95 | L26: =11091.26+1330.95 | ... BL26: =11091.26+1330.95 | BM26: =SUM(E26:BL26)
A27: =A26+1 | B27: Gustavo Garcia Otto | E27: =4906.09+735.91 | F27: =4906.09+735.91 | G27: =4906.09+735.91 | H27: =4906.09+735.91 | I27: =4906.09+735.91 | J27: =4906.09+735.91 | K27: =4906.09+735.91 | L27: =4906.09+735.91 | ... BL27: =4906.09+735.91 | BM27: =SUM(E27:BL27)
A28: =A27+1 | B28: Irene Rios da Silva | E28: =12153.91+729.23 | F28: =12153.91+729.23 | G28: =12153.91+729.23 | H28: =12153.91+729.23 | I28: =12153.91+729.23 | J28: =12153.91+729.23 | K28: =12153.91+729.23 | L28: =12153.91+729.23 | ... BL28: =12153.91+729.23 | BM28: =SUM(E28:BL28)
A29: =A28+1 | B29: João Luiz Martins | E29: =6347.66+380.86 | F29: =6347.66+380.86 | G29: =6347.66+380.86 | H29: =6347.66+380.86 | I29: =6347.66+380.86 | J29: =6347.66+380.86 | K29: =6347.66+380.86 | L29: =6347.66+380.86 | ... BL29: =6347.66+380.86 | BM29: =SUM(E29:BL29)
A30: =A29+1 | B30: Jorge Luiz Silva Hermenegildo | E30: =20543.33+1232.6 | F30: =20543.33+1232.6 | G30: =20543.33+1232.6 | H30: =20543.33+1232.6 | I30: =20543.33+1232.6 | J30: =20543.33+1232.6 | K30: =20543.33+1232.6 | L30: =20543.33+1232.6 | ... BL30: =20543.33+1232.6 | BM30: =SUM(E30:BL30)
A31: =A30+1 | B31: Junior Mateus Alves Camargo | E31: =13351.96+400.56 | F31: =13351.96+400.56 | G31: =13351.96+400.56 | H31: =13351.96+400.56 | I31: =13351.96+400.56 | J31: =13351.96+400.56 | K31: =13351.96+400.56 | L31: =13351.96+400.56 | ... BL31: =13351.96+400.56 | BM31: =SUM(E31:BL31)
A32: =A31+1 | B32: Keyla Junko Shinohara | E32: =16181.63+1941.8 | F32: =16181.63+1941.8 | G32: =16181.63+1941.8 | H32: =16181.63+1941.8 | I32: =16181.63+1941.8 | J32: =16181.63+1941.8 | K32: =16181.63+1941.8 | L32: =16181.63+1941.8 | ... BL32: =16181.63+1941.8 | BM32: =SUM(E32:BL32)
A33: =A32+1 | B33: Leia Mayer Eyng | E33: =7989.29 | F33: =7989.29 | G33: =7989.29 | H33: =7989.29 | I33: =7989.29 | J33: =7989.29 | K33: =7989.29 | L33: =7989.29 | ... BL33: =7989.29 | BM33: =SUM(E33:BL33)
A34: =A33+1 | B34: Luciana Paula Bonetti Silva | E34: 7113.75 | F34: 7114.75 | G34: 7115.75 | H34: 7116.75 | I34: 7117.75 | J34: 7118.75 | K34: 7119.75 | L34: 7120.75 | M34: 7121.75 | N34: 7122.75 | O34: 7123.75 | P34: 7124.75 | Q34: 7125.75 | R34: 7126.75 | S34: 7127.75 | T34: 7128.75 | U34: 7129.75 | V34: 7130.75 | W34: 7131.75 | X34: 7132.75 | Y34: 7133.75 | Z34: 7134.75 | AA34: 7135.75 | AB34: 7136.75 | AC34: 7137.75 | AD34: 7138.75 | AE34: 7139.75 | AF34: 7140.75 | AG34: 7141.75 | AH34: 7142.75 | AI34: 7143.75 | AJ34: 7144.75 | AK34: 7145.75 | AL34: 7146.75 | AM34: 7147.75 | AN34: 7148.75 | AO34: 7149.75 | AP34: 7150.75 | AQ34: 7151.75 | AR34: 7152.75 | AS34: 7153.75 | AT34: 7154.75 | AU34: 7155.75 | AV34: 7156.75 | AW34: 7157.75 | AX34: 7158.75 | AY34: 7159.75 | AZ34: 7160.75 | BA34: 7161.75 | BB34: 7162.75 | BC34: 7163.75 | BD34: 7164.75 | BE34: 7165.75 | BF34: 7166.75 | BG34: 7167.75 | BH34: 7168.75 | BI34: 7169.75 | BJ34: 7170.75 | BK34: 7171.75 | BL34: 7172.75 | BM34: =SUM(E34:BL34)
A35: =A34+1 | B35: Maeli Faé | E35: =12620.75+757.24 | F35: =12620.75+757.24 | G35: =12620.75+757.24 | H35: =12620.75+757.24 | I35: =12620.75+757.24 | J35: =12620.75+757.24 | K35: =12620.75+757.24 | L35: =12620.75+757.24 | ... BL35: =12620.75+757.24 | BM35: =SUM(E35:BL35)
A36: =A35+1 | B36: Paulo Roberto Xavier | E36: =8410.29+504.62 | F36: =8410.29+504.62 | G36: =8410.29+504.62 | H36: =8410.29+504.62 | I36: =8410.29+504.62 | J36: =8410.29+504.62 | K36: =8410.29+504.62 | L36: =8410.29+504.62 | ... BL36: =8410.29+504.62 | BM36: =SUM(E36:BL36)
A37: =A36+1 | B37: Rafael Aleixo de Souza | E37: =10949.97+985.5 | F37: =10949.97+985.5 | G37: =10949.97+985.5 | H37: =10949.97+985.5 | I37: =10949.97+985.5 | J37: =10949.97+985.5 | K37: =10949.97+985.5 | L37: =10949.97+985.5 | ... BL37: =10949.97+985.5 | BM37: =SUM(E37:BL37)
A38: =A37+1 | B38: Ronivaldo Pereira de Araujo | E38: =9630.93+866.78 | F38: =9630.93+866.78 | G38: =9630.93+866.78 | H38: =9630.93+866.78 | I38: =9630.93+866.78 | J38: =9630.93+866.78 | K38: =9630.93+866.78 | L38: =9630.93+866.78 | ... BL38: =9630.93+866.78 | BM38: =SUM(E38:BL38)
A39: =A38+1 | B39: Rubens Costa da Silva | E39: =6566.54 | F39: =6566.54 | G39: =6566.54 | H39: =6566.54 | I39: =6566.54 | J39: =6566.54 | K39: =6566.54 | L39: =6566.54 | ... BL39: =6566.54 | BM39: =SUM(E39:BL39)
A40: =A39+1 | B40: Amir Mattar Valente | E40: =26813.37+804.4 | F40: =26813.37+804.4 | G40: =26813.37+804.4 | H40: =26813.37+804.4 | I40: =26813.37+804.4 | J40: =26813.37+804.4 | K40: =26813.37+804.4 | L40: =26813.37+804.4 | ... BL40: =26813.37+804.4 | BM40: =SUM(E40:BL40)
A41: =A40+1 | B41: Carla Santana | E41: =6565.16+787.82 | F41: =6565.16+787.82 | G41: =6565.16+787.82 | H41: =6565.16+787.82 | I41: =6565.16+787.82 | J41: =6565.16+787.82 | K41: =6565.16+787.82 | L41: =6565.16+787.82 | ... BL41: =6565.16+787.82 | BM41: =SUM(E41:BL41)
A42: =A41+1 | B42: Caroline Fagundes | E42: =5086.62+305.2 | F42: =5086.62+305.2 | G42: =5086.62+305.2 | H42: =5086.62+305.2 | I42: =5086.62+305.2 | J42: =5086.62+305.2 | K42: =5086.62+305.2 | L42: =5086.62+305.2 | ... BL42: =5086.62+305.2 | BM42: =SUM(E42:BL42)
A43: =A42+1 | B43: Daniela Vogel | E43: =8390.54+1510.3 | F43: =8390.54+1510.3 | G43: =8390.54+1510.3 | H43: =8390.54+1510.3 | I43: =8390.54+1510.3 | J43: =8390.54+1510.3 | K43: =8390.54+1510.3 | L43: =8390.54+1510.3 | ... BL43: =8390.54+1510.3 | BM43: =SUM(E43:BL43)
A44: =A43+1 | B44: Marciel Manoel dos Santos | E44: =25242.11+4543.58 | F44: =25242.11+4543.58 | G44: =25242.11+4543.58 | H44: =25242.11+4543.58 | I44: =25242.11+4543.58 | J44: =25242.11+4543.58 | K44: =25242.11+4543.58 | L44: =25242.11+4543.58 | ... BL44: =25242.11+4543.58 | BM44: =SUM(E44:BL44)
A45: =A44+1 | B45: Maurilia Maria Dias | E45: =1499.36+134.94 | F45: =1499.36+134.94 | G45: =1499.36+134.94 | H45: =1499.36+134.94 | I45: =1499.36+134.94 | J45: =1499.36+134.94 | K45: =1499.36+134.94 | L45: =1499.36+134.94 | ... BL45: =1499.36+134.94 | BM45: =SUM(E45:BL45)
A46: =A45+1 | B46: Claudio de Marafigo | E46: =4414.43+662.16 | F46: =4414.43+662.16 | G46: =4414.43+662.16 | H46: =4414.43+662.16 | I46: =4414.43+662.16 | J46: =4414.43+662.16 | K46: =4414.43+662.16 | L46: =4414.43+662.16 | ... BL46: =4414.43+662.16 | BM46: =SUM(E46:BL46)
A47: =A46+1 | B47: Cleber Tomaz | E47: =5312.97+159.39 | F47: =5312.97+159.39 | G47: =5312.97+159.39 | H47: =5312.97+159.39 | I47: =5312.97+159.39 | J47: =5312.97+159.39 | K47: =5312.97+159.39 | L47: =5312.97+159.39 | ... BL47: =5312.97+159.39 | BM47: =SUM(E47:BL47)
A48: =A47+1 | B48: Eduardo Felipe Duarte Schmidt Hebbel | E48: =5278.53+158.36 | F48: =5278.53+158.36 | G48: =5278.53+158.36 | H48: =5278.53+158.36 | I48: =5278.53+158.36 | J48: =5278.53+158.36 | K48: =5278.53+158.36 | L48: =5278.53+158.36 | ... BL48: =5278.53+158.36 | BM48: =SUM(E48:BL48)
A49: =A48+1 | B49: Gustavo Henrique Buch | E49: =10944.23+656.65 | F49: =10944.23+656.65 | G49: =10944.23+656.65 | H49: =10944.23+656.65 | I49: =10944.23+656.65 | J49: =10944.23+656.65 | K49: =10944.23+656.65 | L49: =10944.23+656.65 | ... BL49: =10944.23+656.65 | BM49: =SUM(E49:BL49)
A50: =A49+1 | B50: Jardel Ferreira | E50: =5278.53+158.36 | F50: =5278.53+158.36 | G50: =5278.53+158.36 | H50: =5278.53+158.36 | I50: =5278.53+158.36 | J50: =5278.53+158.36 | K50: =5278.53+158.36 | L50: =5278.53+158.36 | ... BL50: =5278.53+158.36 | BM50: =SUM(E50:BL50)
A51: =A50+1 | B51: Juan Morallys Lucena Silva | E51: =4817.79+144.53 | F51: =4817.79+144.53 | G51: =4817.79+144.53 | H51: =4817.79+144.53 | I51: =4817.79+144.53 | J51: =4817.79+144.53 | K51: =4817.79+144.53 | L51: =4817.79+144.53 | ... BL51: =4817.79+144.53 | BM51: =SUM(E51:BL51)
A52: =A51+1 | B52: Luiza de Oliveira Santos | E52: 4377.69 | F52: 4378.69 | G52: 4379.69 | H52: 4380.69 | I52: 4381.69 | J52: 4382.69 | K52: 4383.69 | L52: 4384.69 | M52: 4385.69 | N52: 4386.69 | O52: 4387.69 | P52: 4388.69 | Q52: 4389.69 | R52: 4390.69 | S52: 4391.69 | T52: 4392.69 | U52: 4393.69 | V52: 4394.69 | W52: 4395.69 | X52: 4396.69 | Y52: 4397.69 | Z52: 4398.69 | AA52: 4399.69 | AB52: 4400.69 | AC52: 4401.69 | AD52: 4402.69 | AE52: 4403.69 | AF52: 4404.69 | AG52: 4405.69 | AH52: 4406.69 | AI52: 4407.69 | AJ52: 4408.69 | AK52: 4409.69 | AL52: 4410.69 | AM52: 4411.69 | AN52: 4412.69 | AO52: 4413.69 | AP52: 4414.69 | AQ52: 4415.69 | AR52: 4416.69 | AS52: 4417.69 | AT52: 4418.69 | AU52: 4419.69 | AV52: 4420.69 | AW52: 4421.69 | AX52: 4422.69 | AY52: 4423.69 | AZ52: 4424.69 | BA52: 4425.69 | BB52: 4426.69 | BC52: 4427.69 | BD52: 4428.69 | BE52: 4429.69 | BF52: 4430.69 | BG52: 4431.69 | BH52: 4432.69 | BI52: 4433.69 | BJ52: 4434.69 | BK52: 4435.69 | BL52: 4436.69 | BM52: =SUM(E52:BL52)
A53: =A52+1 | B53: João Eugênio Cavallazzi | E53: =8065.65+483.94 | F53: =8065.65+483.94 | G53: =8065.65+483.94 | H53: =8065.65+483.94 | I53: =8065.65+483.94 | J53: =8065.65+483.94 | K53: =8065.65+483.94 | L53: =8065.65+483.94 | ... BL53: =8065.65+483.94 | BM53: =SUM(E53:BL53)
A54: =A53+1 | B54: Alberto Hauch Martinho | E54: =3173.83 | F54: =3173.83 | G54: =3173.83 | H54: =3173.83 | I54: =3173.83 | J54: =3173.83 | K54: =3173.83 | L54: =3173.83 | ... T54: =3173.83 | BM54: =SUM(E54:BL54)
A55: =A54+1 | B55: Alyne Zelinda de Barros | E55: =3548.24 | F55: =3548.24 | G55: =3548.24 | H55: =3548.24 | I55: =3548.24 | J55: =3548.24 | K55: =3548.24 | L55: =3548.24 | ... T55: =3548.24 | BM55: =SUM(E55:BL55)
A56: =A55+1 | B56: Davyd Carlos Martins | E56: =7652.5+797.57 | F56: =7652.5+797.57 | G56: =7652.5+797.57 | H56: =7652.5+797.57 | I56: =7652.5+797.57 | J56: =7652.5+797.57 | K56: =7652.5+797.57 | L56: =7652.5+797.57 | ... T56: =7652.5+797.57 | BM56: =SUM(E56:BL56)
A57: =A56+1 | B57: Débora Cristina Siridakis Correa | E57: =4813.76+288.83 | F57: =4813.76+288.83 | G57: =4813.76+288.83 | H57: =4813.76+288.83 | I57: =4813.76+288.83 | J57: =4813.76+288.83 | K57: =4813.76+288.83 | L57: =4813.76+288.83 | ... T57: =4813.76+288.83 | BM57: =SUM(E57:BL57)
A58: =A57+1 | B58: Gabriel da Cunha Lima | E58: =3721.04 | F58: =3721.04 | G58: =3721.04 | H58: =3721.04 | I58: =3721.04 | J58: =3721.04 | K58: =3721.04 | L58: =3721.04 | ... T58: =3721.04 | BM58: =SUM(E58:BL58)
A59: =A58+1 | B59: Graziane da Rocha Silveira | E59: =4297.8+257.87 | F59: =4297.8+257.87 | G59: =4297.8+257.87 | H59: =4297.8+257.87 | I59: =4297.8+257.87 | J59: =4297.8+257.87 | K59: =4297.8+257.87 | L59: =4297.8+257.87 | ... T59: =4297.8+257.87 | BM59: =SUM(E59:BL59)
A60: =A59+1 | B60: Inês Peglow | E60: =3907.09+801.71+423.79 | F60: =3907.09+801.71+423.79 | G60: =3907.09+801.71+423.79 | H60: =3907.09+801.71+423.79 | I60: =3907.09+801.71+423.79 | J60: =3907.09+801.71+423.79 | K60: =3907.09+801.71+423.79 | L60: =3907.09+801.71+423.79 | ... T60: =3907.09+801.71+423.79 | BM60: =SUM(E60:BL60)
A61: =A60+1 | B61: Karin Cristina Amorim | E61: =3597.65+431.72 | F61: =3597.65+431.72 | G61: =3597.65+431.72 | H61: =3597.65+431.72 | I61: =3597.65+431.72 | J61: =3597.65+431.72 | K61: =3597.65+431.72 | L61: =3597.65+431.72 | ... T61: =3597.65+431.72 | BM61: =SUM(E61:BL61)
A62: =A61+1 | B62: Lara Caldeira de Andrade e Silva | E62: =3907.09+234.43 | F62: =3907.09+234.43 | G62: =3907.09+234.43 | H62: =3907.09+234.43 | I62: =3907.09+234.43 | J62: =3907.09+234.43 | K62: =3907.09+234.43 | L62: =3907.09+234.43 | ... T62: =3907.09+234.43 | BM62: =SUM(E62:BL62)
A63: =A62+1 | B63: Lisiane do Carmo Nascimento de Oliveira Bispo | E63: =2606.08 | F63: =2606.08 | G63: =2606.08 | H63: =2606.08 | I63: =2606.08 | J63: =2606.08 | K63: =2606.08 | L63: =2606.08 | ... T63: =2606.08 | BM63: =SUM(E63:BL63)
A64: =A63+1 | B64: Mara Regina Bernardini | E64: =4626.83+694.02 | F64: =4626.83+694.02 | G64: =4626.83+694.02 | H64: =4626.83+694.02 | I64: =4626.83+694.02 | J64: =4626.83+694.02 | K64: =4626.83+694.02 | L64: =4626.83+694.02 | ... T64: =4626.83+694.02 | BM64: =SUM(E64:BL64)
A65: =A64+1 | B65: Marcos Antonio Braga | E65: =3548.24+638.68 | F65: =3548.24+638.68 | G65: =3548.24+638.68 | H65: =3548.24+638.68 | I65: =3548.24+638.68 | J65: =3548.24+638.68 | K65: =3548.24+638.68 | L65: =3548.24+638.68 | ... T65: =3548.24+638.68 | BM65: =SUM(E65:BL65)
A66: =A65+1 | B66: Marta Cristiani de Avila Rosa | E66: =3907.09+351.64 | F66: =3907.09+351.64 | G66: =3907.09+351.64 | H66: =3907.09+351.64 | I66: =3907.09+351.64 | J66: =3907.09+351.64 | K66: =3907.09+351.64 | L66: =3907.09+351.64 | ... T66: =3907.09+351.64 | BM66: =SUM(E66:BL66)
A67: =A66+1 | B67: Pedro Marques Abdo | E67: =3943.75+236.62 | F67: =3943.75+236.62 | G67: =3943.75+236.62 | H67: =3943.75+236.62 | I67: =3943.75+236.62 | J67: =3943.75+236.62 | K67: =3943.75+236.62 | L67: =3943.75+236.62 | ... T67: =3943.75+236.62 | BM67: =SUM(E67:BL67)
A68: =A67+1 | B68: Renilda de Quadros | E68: =4022.64+603.4 | F68: =4022.64+603.4 | G68: =4022.64+603.4 | H68: =4022.64+603.4 | I68: =4022.64+603.4 | J68: =4022.64+603.4 | K68: =4022.64+603.4 | L68: =4022.64+603.4 | ... T68: =4022.64+603.4 | BM68: =SUM(E68:BL68)
A69: =A68+1 | B69: Rithyelen Aliny da Silveira | E69: =3907.09+351.64 | F69: =3907.09+351.64 | G69: =3907.09+351.64 | H69: =3907.09+351.64 | I69: =3907.09+351.64 | J69: =3907.09+351.64 | K69: =3907.09+351.64 | L69: =3907.09+351.64 | ... T69: =3907.09+351.64 | BM69: =SUM(E69:BL69)
A70: =A69+1 | B70: Thiago de Almeida Rebollo | E70: 3550.24 | F70: 3551.24 | G70: 3552.24 | H70: 3553.24 | I70: 3554.24 | J70: 3555.24 | K70: 3556.24 | L70: 3557.24 | M70: 3558.24 | N70: 3559.24 | O70: 3560.24 | P70: 3561.24 | Q70: 3562.24 | R70: 3563.24 | S70: 3564.24 | T70: 3565.24 | BM70: =SUM(E70:BL70)
A71: =A70+1 | B71: Encargos Trabalhistas | E71: =SUM(E5:E70)*36.5% | F71: =SUM(F5:F70)*36.5% | G71: =SUM(G5:G70)*36.5% | H71: =SUM(H5:H70)*36.5% | I71: =SUM(I5:I70)*36.5% | J71: =SUM(J5:J70)*36.5% | K71: =SUM(K5:K70)*36.5% | L71: =SUM(L5:L70)*36.5% | ... BL71: =SUM(BL5:BL70)*36.5% | BM71: =SUM(E71:BL71)
A72: =A71+1 | B72: Provisão | E72: =SUM(E5:E39)*0.4 | F72: =SUM(F5:F39)*0.4 | G72: =SUM(G5:G39)*0.4 | H72: =SUM(H5:H39)*0.4 | I72: =SUM(I5:I39)*0.4 | J72: =SUM(J5:J39)*0.4 | K72: =SUM(K5:K39)*0.4 | L72: =SUM(L5:L39)*0.4 | ... BL72: =SUM(BL5:BL39)*0.4 | BM72: =SUM(E72:BL72)
A73: =A72+1 | B73: Auxilio Alimentação | E73: =$A$39*1100 | F73: =$A$39*1100 | G73: =$A$39*1100 | H73: =$A$39*1100 | I73: =$A$39*1100 | J73: =$A$39*1100 | K73: =$A$39*1100 | L73: =$A$39*1100 | ... BL73: =$A$39*1100 | BM73: =SUM(E73:BL73) | BN73: =SUM(BM5:BM73)
A74: =A73+1 | B74: Bolsista | E74: 58000 | F74: =E74 | G74: =F74 | H74: =G74 | I74: =H74 | J74: =I74 | K74: =J74 | L74: =K74 | M74: =L74 | ... BL74: =BK74 | BM74: =SUM(E74:BL74)
A75: =A74+1 | B75: Bolsista | E75: =E74 | F75: =E75 | G75: =F75 | H75: =G75 | I75: =H75 | J75: =I75 | K75: =J75 | L75: =K75 | M75: =L75 | ... BL75: =BK75 | BM75: =SUM(E75:BL75)
A76: =A75+1 | B76: Bolsista | E76: =E75 | F76: =E76 | G76: =F76 | H76: =G76 | I76: =H76 | J76: =I76 | K76: =J76 | L76: =K76 | M76: =L76 | ... BL76: =BK76 | BM76: =SUM(E76:BL76)
A77: =A76+1 | B77: Bolsista | E77: =E76 | F77: =E77 | G77: =F77 | H77: =G77 | I77: =H77 | J77: =I77 | K77: =J77 | L77: =K77 | M77: =L77 | ... BL77: =BK77 | BM77: =SUM(E77:BL77) | BN77: =SUM(BM74:BM77)
A78: =A77+1 | B78: Serviços de Terceiros | E78: 20000 | F78: =E78 | G78: =F78 | H78: =G78 | I78: =H78 | J78: =I78 | K78: =J78 | L78: =K78 | M78: =L78 | ... BL78: =BK78 | BM78: =SUM(E78:BL78)
A79: =A78+1 | B79: Equipamentos | G79: 80000 | H79: =G79 | I79: =H79 | J79: =I79 | K79: =J79 | L79: =K79 | M79: =L79 | N79: =M79 | O79: =N79 | P79: =O79 | BM79: =SUM(E79:BL79)
A80: =A79+1 | B80: Despesas com Viagens | E80: 56000 | F80: =E80 | G80: =F80 | H80: =G80 | I80: =H80 | J80: =I80 | K80: =J80 | L80: =K80 | M80: =L80 | ... BL80: =BK80 | BM80: =SUM(E80:BL80)
A81: =A80+1 | B81: Diárias | E81: 30000 | F81: =E81 | G81: =F81 | H81: =G81 | I81: =H81 | J81: =I81 | K81: =J81 | L81: =K81 | M81: =L81 | ... BL81: =BK81 | BM81: =SUM(E81:BL81)
A82: =A81+1 | B82: Material de Consumo | E82: 4000 | F82: =E82 | G82: =F82 | H82: =G82 | I82: =H82 | J82: =I82 | K82: =J82 | L82: =K82 | M82: =L82 | ... BL82: =BK82 | BM82: =SUM(E82:BL82)
A83: subtotal | E83: =SUM(E5:E82) | F83: =SUM(F5:F82) | G83: =SUM(G5:G82) | H83: =SUM(H5:H82) | I83: =SUM(I5:I82) | J83: =SUM(J5:J82) | K83: =SUM(K5:K82) | L83: =SUM(L5:L82) | ... BM83: =SUM(BM5:BM82)
A84: =A82+1 | B84: FAPEU | D84: 0.0726 | E84: =E3*$D$84 | F84: =F3*$D$84 | G84: =G3*$D$84 | H84: =H3*$D$84 | I84: =I3*$D$84 | J84: =J3*$D$84 | K84: =K3*$D$84 | L84: =L3*$D$84 | ... BL84: =BL3*$D$84 | BM84: =SUM(E84:BL84)
A85: =A84+1 | B85: Centro Tecnológico | D85: 0.01 | E85: =E3*$D$85 | F85: =F3*$D$85 | G85: =G3*$D$85 | H85: =H3*$D$85 | I85: =I3*$D$85 | J85: =J3*$D$85 | K85: =K3*$D$85 | L85: =L3*$D$85 | ... BL85: =BL3*$D$85 | BM85: =SUM(E85:BL85)
A86: =A85+1 | B86: E.C.V. | D86: 0.02 | E86: =E3*$D$86 | F86: =F3*$D$86 | G86: =G3*$D$86 | H86: =H3*$D$86 | I86: =I3*$D$86 | J86: =J3*$D$86 | K86: =K3*$D$86 | L86: =L3*$D$86 | ... BL86: =BL3*$D$86 | BM86: =SUM(E86:BL86)
A87: =A86+1 | B87: UFSC | D87: 0.04 | E87: =E3*$D$87 | F87: =F3*$D$87 | G87: =G3*$D$87 | H87: =H3*$D$87 | I87: =I3*$D$87 | J87: =J3*$D$87 | K87: =K3*$D$87 | L87: =L3*$D$87 | ... BL87: =BL3*$D$87 | BM87: =SUM(E87:BL87)
A88: subtotal2 | E88: =SUM(E84:E87) | F88: =SUM(F84:F87) | G88: =SUM(G84:G87) | H88: =SUM(H84:H87) | I88: =SUM(I84:I87) | J88: =SUM(J84:J87) | K88: =SUM(K84:K87) | L88: =SUM(L84:L87) | ... BM88: =SUM(BM84:BM87)
A89: Total Despesas | E89: =E88+E83 | F89: =F88+F83 | G89: =G88+G83 | H89: =H88+H83 | I89: =I88+I83 | J89: =J88+J83 | K89: =K88+K83 | L89: =L88+L83 | ... BM89: =BM88+BM83
A90: Saldos | D90: =H102 | E90: =D90+E3-E89 | F90: =E90+F3-F89 | G90: =F90+G3-G89 | H90: =G90+H3-H89 | I90: =H90+I3-I89 | J90: =I90+J3-J89 | K90: =J90+K3-K89 | L90: =K90+L3-L89 | ... BL90: =BK90+BL3-BL89 | BM90: =D90+BM3-D3-BM89
A92: N˚ | B92: Rubricas | C92: Perc. | D92: Previsto | E92: Recebido | F92: A Receber | G92: Gasto | H92: Saldo | I92: A gastar | J92: Result.
A93: 1 | B93: Aplicação em Fundos | C93: 0 | D93: 0 | E93: 0 | F93: 0 | G93: 0 | H93: 0 | I93: 0 | J93: =H93-I93
A94: =A93+1 | B94: Passagens | C94: =D94/94544605 | D94: 3570000 | E94: 0 | F94: =D94-E94 | G94: 0 | H94: =E94+G94 | I94: =-BM80 | J94: =E94+F94+G94+I94
A95: =A94+1 | B95: Diárias | C95: =D95/94544605 | D95: 2183678.4 | E95: 0 | F95: =D95-E95 | G95: 0 | H95: =E95+G95 | I95: =-BM81 | J95: =E95+F95+G95+I95
A96: =A95+1 | B96: Material de Consumo | C96: =D96/94544605 | D96: 305810.13 | E96: 0 | F96: =D96-E96 | G96: 0 | H96: =E96+G96 | I96: =-BM82 | J96: =E96+F96+G96+I96
A97: =A96+1 | B97: Equipe Técnica | C97: =D97/94544605 | D97: 72800966 | E97: 0 | F97: =D97-E97 | G97: 0 | H97: =E97+G97 | I97: =-SUM(BM5:BM77) | J97: =E97+F97+G97+I97
A98: =A97+1 | B98: Equipamentos | C98: =D98/94544605 | D98: 840000 | E98: 0 | F98: =D98-E98 | G98: 0 | H98: =E98+G98 | I98: =-BM79 | J98: =E98+F98+G98+I98
A99: =A98+1 | B99: Serviço de Terceiros | C99: =D99/94544605 | D99: 1362090 | E99: 0 | F99: =D99-E99 | G99: 0 | H99: =E99+G99 | I99: =-BM78 | J99: =E99+F99+G99+I99
A100: =A99+1 | B100: FAPEU | C100: =D100/94544605 | D100: 6863938.3 | E100: 0 | F100: =D100-E100 | G100: 0 | H100: =E100+G100 | I100: =-BM84 | J100: =E100+F100+G100+I100
A101: =A100+1 | B101: UFSC | C101: =D101/94544605 | D101: 6618122.3 | E101: 0 | F101: =D101-E101 | G101: 0 | H101: =E101+G101 | I101: =-SUM(BM85:BM87) | J101: =E101+F101+G101+I101
...
